Workbook

Sheet README
B1: LOKAL - META DAY-ON-DAY NETWORK & DEMOGRAPHIC SPLITS (Oct 1-5, 2026)
B3: PURPOSE
B4: Diagnose the Trial CAC increase over Oct 1-5 and test whether it is a uniform account-wide shock (as hypothesised: a step-up around mid-day Saturday Oct 3) or concentrated in specific segments / scaled adsets.
B6: DATA & GRANULARITY
B7: Source: Meta Ads API, account 2078697462372876 (Lokal), pulled 5 Oct. Raw pulls are on the RAW_* tabs; every summary tab is built from them with SUMIFS formulas (nothing is hardcoded).
B8: The API returns DAILY granularity only. Hourly data is not available, so the exact 'around 12pm Saturday' timing cannot be confirmed from ad data. Windows are Before = Oct 1-2 (Thu-Fri) and After = Oct 3-4 (Sat-Sun).
B9: Trial = app_custom_event_fb_mobile_purchase (the Rs 2 trial). Install = mobile_app_install. CPI = spend / installs. Trial CAC = spend / trials. Install-Trial % = trials / installs.
B11: THREE CAVEATS - READ BEFORE DRAWING CONCLUSIONS
B12: 1. ATTRIBUTION LAG. Oct 3-5 trials are still attributing (purchases land over several days). The most recent days therefore read with FEWER trials than they will finally have, so their Trial CAC is OVERSTATED. Oct 1-2 are fully matured; Oct 3 is mostly matured; Oct 4-5 are the least mature.
B13: 2. HEAVY BUDGET SCALING. On Oct 3-4 budgets were scaled up aggressively across ~40 adsets (towards the October plan). A large same-day budget jump resets an adset's learning and temporarily lifts its CAC, independent of any auction or app change.
B14: 3. NO RELEASE NOTES. Unlike the August report, there is no known Play Store release in this window to correlate against. There is therefore no 'Login vs Rollout' tab; that dose-response check needs the internal dashboard and a known build timeline.
B16: WHAT THE DATA SHOWS (stated conservatively)
... B24: DECISIVE CHECKS: (1) re-pull Oct 3-5 in 3-4 days once trials have fully attributed and re-read the daily CAC; (2) if a systemic cause is still suspected, confirm there was no app release and check internal login-success % by app version; (3) hold budgets flat for 48h to let the scaled adsets exit learning, then re-measure.

Sheet Daily Trend (Meta)
A1: Date | B1: Spend (Rs) | C1: CPM | D1: CTR % | E1: Installs | F1: Trials | G1: CPI | H1: Install-Trial % | I1: Trial CAC | J1: Note
A2: Oct 1 | B2: =RAW_Daily!C2 | C2: =RAW_Daily!E2 | D2: =RAW_Daily!F2 | E2: =RAW_Daily!G2 | F2: =RAW_Daily!H2 | G2: =IFERROR(RAW_Daily!C2/RAW_Daily!G2,"-") | H2: =IFERROR(RAW_Daily!H2/RAW_Daily!G2*100,"-") | I2: =IFERROR(RAW_Daily!C2/RAW_Daily!H2,"-")
A3: Oct 2 | B3: =RAW_Daily!C3 | C3: =RAW_Daily!E3 | D3: =RAW_Daily!F3 | E3: =RAW_Daily!G3 | F3: =RAW_Daily!H3 | G3: =IFERROR(RAW_Daily!C3/RAW_Daily!G3,"-") | H3: =IFERROR(RAW_Daily!H3/RAW_Daily!G3*100,"-") | I3: =IFERROR(RAW_Daily!C3/RAW_Daily!H3,"-")
A4: Oct 3 | B4: =RAW_Daily!C4 | C4: =RAW_Daily!E4 | D4: =RAW_Daily!F4 | E4: =RAW_Daily!G4 | F4: =RAW_Daily!H4 | G4: =IFERROR(RAW_Daily!C4/RAW_Daily!G4,"-") | H4: =IFERROR(RAW_Daily!H4/RAW_Daily!G4*100,"-") | I4: =IFERROR(RAW_Daily!C4/RAW_Daily!H4,"-") | J4: Sat - heavy mid-day budget scaling across account
A5: Oct 4 | B5: =RAW_Daily!C5 | C5: =RAW_Daily!E5 | D5: =RAW_Daily!F5 | E5: =RAW_Daily!G5 | F5: =RAW_Daily!H5 | G5: =IFERROR(RAW_Daily!C5/RAW_Daily!G5,"-") | H5: =IFERROR(RAW_Daily!H5/RAW_Daily!G5*100,"-") | I5: =IFERROR(RAW_Daily!C5/RAW_Daily!H5,"-") | J5: Sun - scaling continues
A6: Oct 5 | B6: =RAW_Daily!C6 | C6: =RAW_Daily!E6 | D6: =RAW_Daily!F6 | E6: =RAW_Daily!G6 | F6: =RAW_Daily!H6 | G6: =IFERROR(RAW_Daily!C6/RAW_Daily!G6,"-") | H6: =IFERROR(RAW_Daily!H6/RAW_Daily!G6*100,"-") | I6: =IFERROR(RAW_Daily!C6/RAW_Daily!H6,"-") | J6: Mon - partial day, trials still attributing

Sheet Window Summary
A1: WINDOW SUMMARY - Oct 5 is a partial day and is shown separately, not blended. CAC on Oct 3-5 is understated-trials still attributing.
A2: Window | B2: Spend (Rs) | C2: Days | D2: Avg spend/day | E2: Installs | F2: CPI | G2: Trials | H2: Install-Trial % | I2: Trial CAC
A3: Before: Oct 1-2 (Thu-Fri, pre-Sat) | B3: =SUMIFS(RAW_Daily!$C$2:$C$6,RAW_Daily!$B$2:$B$6,">=1",RAW_Daily!$B$2:$B$6,"<=2") | C3: 2 | D3: =SUMIFS(RAW_Daily!$C$2:$C$6,RAW_Daily!$B$2:$B$6,">=1",RAW_Daily!$B$2:$B$6,"<=2")/2 | E3: =SUMIFS(RAW_Daily!$G$2:$G$6,RAW_Daily!$B$2:$B$6,">=1",RAW_Daily!$B$2:$B$6,"<=2") | F3: =IFERROR(SUMIFS(RAW_Daily!$C$2:$C$6,RAW_Daily!$B$2:$B$6,">=1",RAW_Daily!$B$2:$B$6,"<=2")/SUMIFS(RAW_Daily!$G$2:$G$6,RAW_Daily!$B$2:$B$6,">=1",RAW_Daily!$B$2:$B$6,"<=2"),"-") | G3: =SUMIFS(RAW_Daily!$H$2:$H$6,RAW_Daily!$B$2:$B$6,">=1",RAW_Daily!$B$2:$B$6,"<=2") | H3: =IFERROR(SUMIFS(RAW_Daily!$H$2:$H$6,RAW_Daily!$B$2:$B$6,">=1",RAW_Daily!$B$2:$B$6,"<=2")/SUMIFS(RAW_Daily!$G$2:$G$6,RAW_Daily!$B$2:$B$6,">=1",RAW_Daily!$B$2:$B$6,"<=2")*100,"-") | I3: =IFERROR(SUMIFS(RAW_Daily!$C$2:$C$6,RAW_Daily!$B$2:$B$6,">=1",RAW_Daily!$B$2:$B$6,"<=2")/SUMIFS(RAW_Daily!$H$2:$H$6,RAW_Daily!$B$2:$B$6,">=1",RAW_Daily!$B$2:$B$6,"<=2"),"-")
A4: After: Oct 3-4 (Sat-Sun) | B4: =SUMIFS(RAW_Daily!$C$2:$C$6,RAW_Daily!$B$2:$B$6,">=3",RAW_Daily!$B$2:$B$6,"<=4") | C4: 2 | D4: =SUMIFS(RAW_Daily!$C$2:$C$6,RAW_Daily!$B$2:$B$6,">=3",RAW_Daily!$B$2:$B$6,"<=4")/2 | E4: =SUMIFS(RAW_Daily!$G$2:$G$6,RAW_Daily!$B$2:$B$6,">=3",RAW_Daily!$B$2:$B$6,"<=4") | F4: =IFERROR(SUMIFS(RAW_Daily!$C$2:$C$6,RAW_Daily!$B$2:$B$6,">=3",RAW_Daily!$B$2:$B$6,"<=4")/SUMIFS(RAW_Daily!$G$2:$G$6,RAW_Daily!$B$2:$B$6,">=3",RAW_Daily!$B$2:$B$6,"<=4"),"-") | G4: =SUMIFS(RAW_Daily!$H$2:$H$6,RAW_Daily!$B$2:$B$6,">=3",RAW_Daily!$B$2:$B$6,"<=4") | H4: =IFERROR(SUMIFS(RAW_Daily!$H$2:$H$6,RAW_Daily!$B$2:$B$6,">=3",RAW_Daily!$B$2:$B$6,"<=4")/SUMIFS(RAW_Daily!$G$2:$G$6,RAW_Daily!$B$2:$B$6,">=3",RAW_Daily!$B$2:$B$6,"<=4")*100,"-") | I4: =IFERROR(SUMIFS(RAW_Daily!$C$2:$C$6,RAW_Daily!$B$2:$B$6,">=3",RAW_Daily!$B$2:$B$6,"<=4")/SUMIFS(RAW_Daily!$H$2:$H$6,RAW_Daily!$B$2:$B$6,">=3",RAW_Daily!$B$2:$B$6,"<=4"),"-")
A5: Oct 5 (Mon, partial day) | B5: =SUMIFS(RAW_Daily!$C$2:$C$6,RAW_Daily!$B$2:$B$6,">=5",RAW_Daily!$B$2:$B$6,"<=5") | C5: 1 | D5: =SUMIFS(RAW_Daily!$C$2:$C$6,RAW_Daily!$B$2:$B$6,">=5",RAW_Daily!$B$2:$B$6,"<=5")/1 | E5: =SUMIFS(RAW_Daily!$G$2:$G$6,RAW_Daily!$B$2:$B$6,">=5",RAW_Daily!$B$2:$B$6,"<=5") | F5: =IFERROR(SUMIFS(RAW_Daily!$C$2:$C$6,RAW_Daily!$B$2:$B$6,">=5",RAW_Daily!$B$2:$B$6,"<=5")/SUMIFS(RAW_Daily!$G$2:$G$6,RAW_Daily!$B$2:$B$6,">=5",RAW_Daily!$B$2:$B$6,"<=5"),"-") | G5: =SUMIFS(RAW_Daily!$H$2:$H$6,RAW_Daily!$B$2:$B$6,">=5",RAW_Daily!$B$2:$B$6,"<=5") | H5: =IFERROR(SUMIFS(RAW_Daily!$H$2:$H$6,RAW_Daily!$B$2:$B$6,">=5",RAW_Daily!$B$2:$B$6,"<=5")/SUMIFS(RAW_Daily!$G$2:$G$6,RAW_Daily!$B$2:$B$6,">=5",RAW_Daily!$B$2:$B$6,"<=5")*100,"-") | I5: =IFERROR(SUMIFS(RAW_Daily!$C$2:$C$6,RAW_Daily!$B$2:$B$6,">=5",RAW_Daily!$B$2:$B$6,"<=5")/SUMIFS(RAW_Daily!$H$2:$H$6,RAW_Daily!$B$2:$B$6,">=5",RAW_Daily!$B$2:$B$6,"<=5"),"-")

Sheet Network Split
A1: NETWORK (PUBLISHER PLATFORM) SPLIT - share of spend/installs/trials + CPI + Trial CAC, per window. If CAC rose on both FB and IG together it is uniform, not a network shift.
A2: Window | B2: Segment | C2: Spend (Rs) | D2: Spend % | E2: Installs | F2: Install % | G2: Trials | H2: CPI | I2: Trial CAC | J2: Inflation
A3: Before Oct 1-2 | B3: Facebook | C3: =SUMIFS(RAW_Network!$D$2:$D$21,RAW_Network!$B$2:$B$21,">=1",RAW_Network!$B$2:$B$21,"<=2",RAW_Network!$C$2:$C$21,"Facebook") | D3: =IFERROR(SUMIFS(RAW_Network!$D$2:$D$21,RAW_Network!$B$2:$B$21,">=1",RAW_Network!$B$2:$B$21,"<=2",RAW_Network!$C$2:$C$21,"Facebook")/SUMIFS(RAW_Network!$D$2:$D$21,RAW_Network!$B$2:$B$21,">=1",RAW_Network!$B$2:$B$21,"<=2")*100,"-") | E3: =SUMIFS(RAW_Network!$E$2:$E$21,RAW_Network!$B$2:$B$21,">=1",RAW_Network!$B$2:$B$21,"<=2",RAW_Network!$C$2:$C$21,"Facebook") | F3: =IFERROR(SUMIFS(RAW_Network!$E$2:$E$21,RAW_Network!$B$2:$B$21,">=1",RAW_Network!$B$2:$B$21,"<=2",RAW_Network!$C$2:$C$21,"Facebook")/SUMIFS(RAW_Network!$E$2:$E$21,RAW_Network!$B$2:$B$21,">=1",RAW_Network!$B$2:$B$21,"<=2")*100,"-") | G3: =SUMIFS(RAW_Network!$F$2:$F$21,RAW_Network!$B$2:$B$21,">=1",RAW_Network!$B$2:$B$21,"<=2",RAW_Network!$C$2:$C$21,"Facebook") | H3: =IFERROR(SUMIFS(RAW_Network!$D$2:$D$21,RAW_Network!$B$2:$B$21,">=1",RAW_Network!$B$2:$B$21,"<=2",RAW_Network!$C$2:$C$21,"Facebook")/SUMIFS(RAW_Network!$E$2:$E$21,RAW_Network!$B$2:$B$21,">=1",RAW_Network!$B$2:$B$21,"<=2",RAW_Network!$C$2:$C$21,"Facebook"),"-") | I3: =IFERROR(SUMIFS(RAW_Network!$D$2:$D$21,RAW_Network!$B$2:$B$21,">=1",RAW_Network!$B$2:$B$21,"<=2",RAW_Network!$C$2:$C$21,"Facebook")/SUMIFS(RAW_Network!$F$2:$F$21,RAW_Network!$B$2:$B$21,">=1",RAW_Network!$B$2:$B$21,"<=2",RAW_Network!$C$2:$C$21,"Facebook"),"-")
B4: Instagram | C4: =SUMIFS(RAW_Network!$D$2:$D$21,RAW_Network!$B$2:$B$21,">=1",RAW_Network!$B$2:$B$21,"<=2",RAW_Network!$C$2:$C$21,"Instagram") | D4: =IFERROR(SUMIFS(RAW_Network!$D$2:$D$21,RAW_Network!$B$2:$B$21,">=1",RAW_Network!$B$2:$B$21,"<=2",RAW_Network!$C$2:$C$21,"Instagram")/SUMIFS(RAW_Network!$D$2:$D$21,RAW_Network!$B$2:$B$21,">=1",RAW_Network!$B$2:$B$21,"<=2")*100,"-") | E4: =SUMIFS(RAW_Network!$E$2:$E$21,RAW_Network!$B$2:$B$21,">=1",RAW_Network!$B$2:$B$21,"<=2",RAW_Network!$C$2:$C$21,"Instagram") | F4: =IFERROR(SUMIFS(RAW_Network!$E$2:$E$21,RAW_Network!$B$2:$B$21,">=1",RAW_Network!$B$2:$B$21,"<=2",RAW_Network!$C$2:$C$21,"Instagram")/SUMIFS(RAW_Network!$E$2:$E$21,RAW_Network!$B$2:$B$21,">=1",RAW_Network!$B$2:$B$21,"<=2")*100,"-") | G4: =SUMIFS(RAW_Network!$F$2:$F$21,RAW_Network!$B$2:$B$21,">=1",RAW_Network!$B$2:$B$21,"<=2",RAW_Network!$C$2:$C$21,"Instagram") | H4: =IFERROR(SUMIFS(RAW_Network!$D$2:$D$21,RAW_Network!$B$2:$B$21,">=1",RAW_Network!$B$2:$B$21,"<=2",RAW_Network!$C$2:$C$21,"Instagram")/SUMIFS(RAW_Network!$E$2:$E$21,RAW_Network!$B$2:$B$21,">=1",RAW_Network!$B$2:$B$21,"<=2",RAW_Network!$C$2:$C$21,"Instagram"),"-") | I4: =IFERROR(SUMIFS(RAW_Network!$D$2:$D$21,RAW_Network!$B$2:$B$21,">=1",RAW_Network!$B$2:$B$21,"<=2",RAW_Network!$C$2:$C$21,"Instagram")/SUMIFS(RAW_Network!$F$2:$F$21,RAW_Network!$B$2:$B$21,">=1",RAW_Network!$B$2:$B$21,"<=2",RAW_Network!$C$2:$C$21,"Instagram"),"-")
B5: Audience Network | C5: =SUMIFS(RAW_Network!$D$2:$D$21,RAW_Network!$B$2:$B$21,">=1",RAW_Network!$B$2:$B$21,"<=2",RAW_Network!$C$2:$C$21,"Audience Network") | D5: =IFERROR(SUMIFS(RAW_Network!$D$2:$D$21,RAW_Network!$B$2:$B$21,">=1",RAW_Network!$B$2:$B$21,"<=2",RAW_Network!$C$2:$C$21,"Audience Network")/SUMIFS(RAW_Network!$D$2:$D$21,RAW_Network!$B$2:$B$21,">=1",RAW_Network!$B$2:$B$21,"<=2")*100,"-") | E5: =SUMIFS(RAW_Network!$E$2:$E$21,RAW_Network!$B$2:$B$21,">=1",RAW_Network!$B$2:$B$21,"<=2",RAW_Network!$C$2:$C$21,"Audience Network") | F5: =IFERROR(SUMIFS(RAW_Network!$E$2:$E$21,RAW_Network!$B$2:$B$21,">=1",RAW_Network!$B$2:$B$21,"<=2",RAW_Network!$C$2:$C$21,"Audience Network")/SUMIFS(RAW_Network!$E$2:$E$21,RAW_Network!$B$2:$B$21,">=1",RAW_Network!$B$2:$B$21,"<=2")*100,"-") | G5: =SUMIFS(RAW_Network!$F$2:$F$21,RAW_Network!$B$2:$B$21,">=1",RAW_Network!$B$2:$B$21,"<=2",RAW_Network!$C$2:$C$21,"Audience Network") | H5: =IFERROR(SUMIFS(RAW_Network!$D$2:$D$21,RAW_Network!$B$2:$B$21,">=1",RAW_Network!$B$2:$B$21,"<=2",RAW_Network!$C$2:$C$21,"Audience Network")/SUMIFS(RAW_Network!$E$2:$E$21,RAW_Network!$B$2:$B$21,">=1",RAW_Network!$B$2:$B$21,"<=2",RAW_Network!$C$2:$C$21,"Audience Network"),"-") | I5: =IFERROR(SUMIFS(RAW_Network!$D$2:$D$21,RAW_Network!$B$2:$B$21,">=1",RAW_Network!$B$2:$B$21,"<=2",RAW_Network!$C$2:$C$21,"Audience Network")/SUMIFS(RAW_Network!$F$2:$F$21,RAW_Network!$B$2:$B$21,">=1",RAW_Network!$B$2:$B$21,"<=2",RAW_Network!$C$2:$C$21,"Audience Network"),"-")
B6: Threads | C6: =SUMIFS(RAW_Network!$D$2:$D$21,RAW_Network!$B$2:$B$21,">=1",RAW_Network!$B$2:$B$21,"<=2",RAW_Network!$C$2:$C$21,"Threads") | D6: =IFERROR(SUMIFS(RAW_Network!$D$2:$D$21,RAW_Network!$B$2:$B$21,">=1",RAW_Network!$B$2:$B$21,"<=2",RAW_Network!$C$2:$C$21,"Threads")/SUMIFS(RAW_Network!$D$2:$D$21,RAW_Network!$B$2:$B$21,">=1",RAW_Network!$B$2:$B$21,"<=2")*100,"-") | E6: =SUMIFS(RAW_Network!$E$2:$E$21,RAW_Network!$B$2:$B$21,">=1",RAW_Network!$B$2:$B$21,"<=2",RAW_Network!$C$2:$C$21,"Threads") | F6: =IFERROR(SUMIFS(RAW_Network!$E$2:$E$21,RAW_Network!$B$2:$B$21,">=1",RAW_Network!$B$2:$B$21,"<=2",RAW_Network!$C$2:$C$21,"Threads")/SUMIFS(RAW_Network!$E$2:$E$21,RAW_Network!$B$2:$B$21,">=1",RAW_Network!$B$2:$B$21,"<=2")*100,"-") | G6: =SUMIFS(RAW_Network!$F$2:$F$21,RAW_Network!$B$2:$B$21,">=1",RAW_Network!$B$2:$B$21,"<=2",RAW_Network!$C$2:$C$21,"Threads") | H6: =IFERROR(SUMIFS(RAW_Network!$D$2:$D$21,RAW_Network!$B$2:$B$21,">=1",RAW_Network!$B$2:$B$21,"<=2",RAW_Network!$C$2:$C$21,"Threads")/SUMIFS(RAW_Network!$E$2:$E$21,RAW_Network!$B$2:$B$21,">=1",RAW_Network!$B$2:$B$21,"<=2",RAW_Network!$C$2:$C$21,"Threads"),"-") | I6: =IFERROR(SUMIFS(RAW_Network!$D$2:$D$21,RAW_Network!$B$2:$B$21,">=1",RAW_Network!$B$2:$B$21,"<=2",RAW_Network!$C$2:$C$21,"Threads")/SUMIFS(RAW_Network!$F$2:$F$21,RAW_Network!$B$2:$B$21,">=1",RAW_Network!$B$2:$B$21,"<=2",RAW_Network!$C$2:$C$21,"Threads"),"-")
A7: After Oct 3-4 | B7: Facebook | C7: =SUMIFS(RAW_Network!$D$2:$D$21,RAW_Network!$B$2:$B$21,">=3",RAW_Network!$B$2:$B$21,"<=4",RAW_Network!$C$2:$C$21,"Facebook") | D7: =IFERROR(SUMIFS(RAW_Network!$D$2:$D$21,RAW_Network!$B$2:$B$21,">=3",RAW_Network!$B$2:$B$21,"<=4",RAW_Network!$C$2:$C$21,"Facebook")/SUMIFS(RAW_Network!$D$2:$D$21,RAW_Network!$B$2:$B$21,">=3",RAW_Network!$B$2:$B$21,"<=4")*100,"-") | E7: =SUMIFS(RAW_Network!$E$2:$E$21,RAW_Network!$B$2:$B$21,">=3",RAW_Network!$B$2:$B$21,"<=4",RAW_Network!$C$2:$C$21,"Facebook") | F7: =IFERROR(SUMIFS(RAW_Network!$E$2:$E$21,RAW_Network!$B$2:$B$21,">=3",RAW_Network!$B$2:$B$21,"<=4",RAW_Network!$C$2:$C$21,"Facebook")/SUMIFS(RAW_Network!$E$2:$E$21,RAW_Network!$B$2:$B$21,">=3",RAW_Network!$B$2:$B$21,"<=4")*100,"-") | G7: =SUMIFS(RAW_Network!$F$2:$F$21,RAW_Network!$B$2:$B$21,">=3",RAW_Network!$B$2:$B$21,"<=4",RAW_Network!$C$2:$C$21,"Facebook") | H7: =IFERROR(SUMIFS(RAW_Network!$D$2:$D$21,RAW_Network!$B$2:$B$21,">=3",RAW_Network!$B$2:$B$21,"<=4",RAW_Network!$C$2:$C$21,"Facebook")/SUMIFS(RAW_Network!$E$2:$E$21,RAW_Network!$B$2:$B$21,">=3",RAW_Network!$B$2:$B$21,"<=4",RAW_Network!$C$2:$C$21,"Facebook"),"-") | I7: =IFERROR(SUMIFS(RAW_Network!$D$2:$D$21,RAW_Network!$B$2:$B$21,">=3",RAW_Network!$B$2:$B$21,"<=4",RAW_Network!$C$2:$C$21,"Facebook")/SUMIFS(RAW_Network!$F$2:$F$21,RAW_Network!$B$2:$B$21,">=3",RAW_Network!$B$2:$B$21,"<=4",RAW_Network!$C$2:$C$21,"Facebook"),"-") | J7: =IFERROR(H7/H3,"-")
B8: Instagram | C8: =SUMIFS(RAW_Network!$D$2:$D$21,RAW_Network!$B$2:$B$21,">=3",RAW_Network!$B$2:$B$21,"<=4",RAW_Network!$C$2:$C$21,"Instagram") | D8: =IFERROR(SUMIFS(RAW_Network!$D$2:$D$21,RAW_Network!$B$2:$B$21,">=3",RAW_Network!$B$2:$B$21,"<=4",RAW_Network!$C$2:$C$21,"Instagram")/SUMIFS(RAW_Network!$D$2:$D$21,RAW_Network!$B$2:$B$21,">=3",RAW_Network!$B$2:$B$21,"<=4")*100,"-") | E8: =SUMIFS(RAW_Network!$E$2:$E$21,RAW_Network!$B$2:$B$21,">=3",RAW_Network!$B$2:$B$21,"<=4",RAW_Network!$C$2:$C$21,"Instagram") | F8: =IFERROR(SUMIFS(RAW_Network!$E$2:$E$21,RAW_Network!$B$2:$B$21,">=3",RAW_Network!$B$2:$B$21,"<=4",RAW_Network!$C$2:$C$21,"Instagram")/SUMIFS(RAW_Network!$E$2:$E$21,RAW_Network!$B$2:$B$21,">=3",RAW_Network!$B$2:$B$21,"<=4")*100,"-") | G8: =SUMIFS(RAW_Network!$F$2:$F$21,RAW_Network!$B$2:$B$21,">=3",RAW_Network!$B$2:$B$21,"<=4",RAW_Network!$C$2:$C$21,"Instagram") | H8: =IFERROR(SUMIFS(RAW_Network!$D$2:$D$21,RAW_Network!$B$2:$B$21,">=3",RAW_Network!$B$2:$B$21,"<=4",RAW_Network!$C$2:$C$21,"Instagram")/SUMIFS(RAW_Network!$E$2:$E$21,RAW_Network!$B$2:$B$21,">=3",RAW_Network!$B$2:$B$21,"<=4",RAW_Network!$C$2:$C$21,"Instagram"),"-") | I8: =IFERROR(SUMIFS(RAW_Network!$D$2:$D$21,RAW_Network!$B$2:$B$21,">=3",RAW_Network!$B$2:$B$21,"<=4",RAW_Network!$C$2:$C$21,"Instagram")/SUMIFS(RAW_Network!$F$2:$F$21,RAW_Network!$B$2:$B$21,">=3",RAW_Network!$B$2:$B$21,"<=4",RAW_Network!$C$2:$C$21,"Instagram"),"-") | J8: =IFERROR(H8/H4,"-")
B9: Audience Network | C9: =SUMIFS(RAW_Network!$D$2:$D$21,RAW_Network!$B$2:$B$21,">=3",RAW_Network!$B$2:$B$21,"<=4",RAW_Network!$C$2:$C$21,"Audience Network") | D9: =IFERROR(SUMIFS(RAW_Network!$D$2:$D$21,RAW_Network!$B$2:$B$21,">=3",RAW_Network!$B$2:$B$21,"<=4",RAW_Network!$C$2:$C$21,"Audience Network")/SUMIFS(RAW_Network!$D$2:$D$21,RAW_Network!$B$2:$B$21,">=3",RAW_Network!$B$2:$B$21,"<=4")*100,"-") | E9: =SUMIFS(RAW_Network!$E$2:$E$21,RAW_Network!$B$2:$B$21,">=3",RAW_Network!$B$2:$B$21,"<=4",RAW_Network!$C$2:$C$21,"Audience Network") | F9: =IFERROR(SUMIFS(RAW_Network!$E$2:$E$21,RAW_Network!$B$2:$B$21,">=3",RAW_Network!$B$2:$B$21,"<=4",RAW_Network!$C$2:$C$21,"Audience Network")/SUMIFS(RAW_Network!$E$2:$E$21,RAW_Network!$B$2:$B$21,">=3",RAW_Network!$B$2:$B$21,"<=4")*100,"-") | G9: =SUMIFS(RAW_Network!$F$2:$F$21,RAW_Network!$B$2:$B$21,">=3",RAW_Network!$B$2:$B$21,"<=4",RAW_Network!$C$2:$C$21,"Audience Network") | H9: =IFERROR(SUMIFS(RAW_Network!$D$2:$D$21,RAW_Network!$B$2:$B$21,">=3",RAW_Network!$B$2:$B$21,"<=4",RAW_Network!$C$2:$C$21,"Audience Network")/SUMIFS(RAW_Network!$E$2:$E$21,RAW_Network!$B$2:$B$21,">=3",RAW_Network!$B$2:$B$21,"<=4",RAW_Network!$C$2:$C$21,"Audience Network"),"-") | I9: =IFERROR(SUMIFS(RAW_Network!$D$2:$D$21,RAW_Network!$B$2:$B$21,">=3",RAW_Network!$B$2:$B$21,"<=4",RAW_Network!$C$2:$C$21,"Audience Network")/SUMIFS(RAW_Network!$F$2:$F$21,RAW_Network!$B$2:$B$21,">=3",RAW_Network!$B$2:$B$21,"<=4",RAW_Network!$C$2:$C$21,"Audience Network"),"-") | J9: =IFERROR(H9/H5,"-")
B10: Threads | C10: =SUMIFS(RAW_Network!$D$2:$D$21,RAW_Network!$B$2:$B$21,">=3",RAW_Network!$B$2:$B$21,"<=4",RAW_Network!$C$2:$C$21,"Threads") | D10: =IFERROR(SUMIFS(RAW_Network!$D$2:$D$21,RAW_Network!$B$2:$B$21,">=3",RAW_Network!$B$2:$B$21,"<=4",RAW_Network!$C$2:$C$21,"Threads")/SUMIFS(RAW_Network!$D$2:$D$21,RAW_Network!$B$2:$B$21,">=3",RAW_Network!$B$2:$B$21,"<=4")*100,"-") | E10: =SUMIFS(RAW_Network!$E$2:$E$21,RAW_Network!$B$2:$B$21,">=3",RAW_Network!$B$2:$B$21,"<=4",RAW_Network!$C$2:$C$21,"Threads") | F10: =IFERROR(SUMIFS(RAW_Network!$E$2:$E$21,RAW_Network!$B$2:$B$21,">=3",RAW_Network!$B$2:$B$21,"<=4",RAW_Network!$C$2:$C$21,"Threads")/SUMIFS(RAW_Network!$E$2:$E$21,RAW_Network!$B$2:$B$21,">=3",RAW_Network!$B$2:$B$21,"<=4")*100,"-") | G10: =SUMIFS(RAW_Network!$F$2:$F$21,RAW_Network!$B$2:$B$21,">=3",RAW_Network!$B$2:$B$21,"<=4",RAW_Network!$C$2:$C$21,"Threads") | H10: =IFERROR(SUMIFS(RAW_Network!$D$2:$D$21,RAW_Network!$B$2:$B$21,">=3",RAW_Network!$B$2:$B$21,"<=4",RAW_Network!$C$2:$C$21,"Threads")/SUMIFS(RAW_Network!$E$2:$E$21,RAW_Network!$B$2:$B$21,">=3",RAW_Network!$B$2:$B$21,"<=4",RAW_Network!$C$2:$C$21,"Threads"),"-") | I10: =IFERROR(SUMIFS(RAW_Network!$D$2:$D$21,RAW_Network!$B$2:$B$21,">=3",RAW_Network!$B$2:$B$21,"<=4",RAW_Network!$C$2:$C$21,"Threads")/SUMIFS(RAW_Network!$F$2:$F$21,RAW_Network!$B$2:$B$21,">=3",RAW_Network!$B$2:$B$21,"<=4",RAW_Network!$C$2:$C$21,"Threads"),"-") | J10: =IFERROR(H10/H6,"-")

Sheet Daily Network FB vs IG
A1: DAILY NETWORK - Facebook vs Instagram (Oct 1-5). Both rising together = uniform, not a network shift. Oct 3-5 trials still attributing.
A2: Date | B2: FB Spend | C2: FB CPI | D2: FB Trial CAC | E2: FB Trials | F2: IG Spend | G2: IG CPI | H2: IG Trial CAC | I2: IG Trials
A3: Oct 1 | B3: =SUMIFS(RAW_Network!$D$2:$D$21,RAW_Network!$B$2:$B$21,"1",RAW_Network!$C$2:$C$21,"Facebook") | C3: =IFERROR(SUMIFS(RAW_Network!$D$2:$D$21,RAW_Network!$B$2:$B$21,"1",RAW_Network!$C$2:$C$21,"Facebook")/SUMIFS(RAW_Network!$E$2:$E$21,RAW_Network!$B$2:$B$21,"1",RAW_Network!$C$2:$C$21,"Facebook"),"-") | D3: =IFERROR(SUMIFS(RAW_Network!$D$2:$D$21,RAW_Network!$B$2:$B$21,"1",RAW_Network!$C$2:$C$21,"Facebook")/SUMIFS(RAW_Network!$F$2:$F$21,RAW_Network!$B$2:$B$21,"1",RAW_Network!$C$2:$C$21,"Facebook"),"-") | E3: =SUMIFS(RAW_Network!$F$2:$F$21,RAW_Network!$B$2:$B$21,"1",RAW_Network!$C$2:$C$21,"Facebook") | F3: =SUMIFS(RAW_Network!$D$2:$D$21,RAW_Network!$B$2:$B$21,"1",RAW_Network!$C$2:$C$21,"Instagram") | G3: =IFERROR(SUMIFS(RAW_Network!$D$2:$D$21,RAW_Network!$B$2:$B$21,"1",RAW_Network!$C$2:$C$21,"Instagram")/SUMIFS(RAW_Network!$E$2:$E$21,RAW_Network!$B$2:$B$21,"1",RAW_Network!$C$2:$C$21,"Instagram"),"-") | H3: =IFERROR(SUMIFS(RAW_Network!$D$2:$D$21,RAW_Network!$B$2:$B$21,"1",RAW_Network!$C$2:$C$21,"Instagram")/SUMIFS(RAW_Network!$F$2:$F$21,RAW_Network!$B$2:$B$21,"1",RAW_Network!$C$2:$C$21,"Instagram"),"-") | I3: =SUMIFS(RAW_Network!$F$2:$F$21,RAW_Network!$B$2:$B$21,"1",RAW_Network!$C$2:$C$21,"Instagram")
A4: Oct 2 | B4: =SUMIFS(RAW_Network!$D$2:$D$21,RAW_Network!$B$2:$B$21,"2",RAW_Network!$C$2:$C$21,"Facebook") | C4: =IFERROR(SUMIFS(RAW_Network!$D$2:$D$21,RAW_Network!$B$2:$B$21,"2",RAW_Network!$C$2:$C$21,"Facebook")/SUMIFS(RAW_Network!$E$2:$E$21,RAW_Network!$B$2:$B$21,"2",RAW_Network!$C$2:$C$21,"Facebook"),"-") | D4: =IFERROR(SUMIFS(RAW_Network!$D$2:$D$21,RAW_Network!$B$2:$B$21,"2",RAW_Network!$C$2:$C$21,"Facebook")/SUMIFS(RAW_Network!$F$2:$F$21,RAW_Network!$B$2:$B$21,"2",RAW_Network!$C$2:$C$21,"Facebook"),"-") | E4: =SUMIFS(RAW_Network!$F$2:$F$21,RAW_Network!$B$2:$B$21,"2",RAW_Network!$C$2:$C$21,"Facebook") | F4: =SUMIFS(RAW_Network!$D$2:$D$21,RAW_Network!$B$2:$B$21,"2",RAW_Network!$C$2:$C$21,"Instagram") | G4: =IFERROR(SUMIFS(RAW_Network!$D$2:$D$21,RAW_Network!$B$2:$B$21,"2",RAW_Network!$C$2:$C$21,"Instagram")/SUMIFS(RAW_Network!$E$2:$E$21,RAW_Network!$B$2:$B$21,"2",RAW_Network!$C$2:$C$21,"Instagram"),"-") | H4: =IFERROR(SUMIFS(RAW_Network!$D$2:$D$21,RAW_Network!$B$2:$B$21,"2",RAW_Network!$C$2:$C$21,"Instagram")/SUMIFS(RAW_Network!$F$2:$F$21,RAW_Network!$B$2:$B$21,"2",RAW_Network!$C$2:$C$21,"Instagram"),"-") | I4: =SUMIFS(RAW_Network!$F$2:$F$21,RAW_Network!$B$2:$B$21,"2",RAW_Network!$C$2:$C$21,"Instagram")
A5: Oct 3 | B5: =SUMIFS(RAW_Network!$D$2:$D$21,RAW_Network!$B$2:$B$21,"3",RAW_Network!$C$2:$C$21,"Facebook") | C5: =IFERROR(SUMIFS(RAW_Network!$D$2:$D$21,RAW_Network!$B$2:$B$21,"3",RAW_Network!$C$2:$C$21,"Facebook")/SUMIFS(RAW_Network!$E$2:$E$21,RAW_Network!$B$2:$B$21,"3",RAW_Network!$C$2:$C$21,"Facebook"),"-") | D5: =IFERROR(SUMIFS(RAW_Network!$D$2:$D$21,RAW_Network!$B$2:$B$21,"3",RAW_Network!$C$2:$C$21,"Facebook")/SUMIFS(RAW_Network!$F$2:$F$21,RAW_Network!$B$2:$B$21,"3",RAW_Network!$C$2:$C$21,"Facebook"),"-") | E5: =SUMIFS(RAW_Network!$F$2:$F$21,RAW_Network!$B$2:$B$21,"3",RAW_Network!$C$2:$C$21,"Facebook") | F5: =SUMIFS(RAW_Network!$D$2:$D$21,RAW_Network!$B$2:$B$21,"3",RAW_Network!$C$2:$C$21,"Instagram") | G5: =IFERROR(SUMIFS(RAW_Network!$D$2:$D$21,RAW_Network!$B$2:$B$21,"3",RAW_Network!$C$2:$C$21,"Instagram")/SUMIFS(RAW_Network!$E$2:$E$21,RAW_Network!$B$2:$B$21,"3",RAW_Network!$C$2:$C$21,"Instagram"),"-") | H5: =IFERROR(SUMIFS(RAW_Network!$D$2:$D$21,RAW_Network!$B$2:$B$21,"3",RAW_Network!$C$2:$C$21,"Instagram")/SUMIFS(RAW_Network!$F$2:$F$21,RAW_Network!$B$2:$B$21,"3",RAW_Network!$C$2:$C$21,"Instagram"),"-") | I5: =SUMIFS(RAW_Network!$F$2:$F$21,RAW_Network!$B$2:$B$21,"3",RAW_Network!$C$2:$C$21,"Instagram")
A6: Oct 4 | B6: =SUMIFS(RAW_Network!$D$2:$D$21,RAW_Network!$B$2:$B$21,"4",RAW_Network!$C$2:$C$21,"Facebook") | C6: =IFERROR(SUMIFS(RAW_Network!$D$2:$D$21,RAW_Network!$B$2:$B$21,"4",RAW_Network!$C$2:$C$21,"Facebook")/SUMIFS(RAW_Network!$E$2:$E$21,RAW_Network!$B$2:$B$21,"4",RAW_Network!$C$2:$C$21,"Facebook"),"-") | D6: =IFERROR(SUMIFS(RAW_Network!$D$2:$D$21,RAW_Network!$B$2:$B$21,"4",RAW_Network!$C$2:$C$21,"Facebook")/SUMIFS(RAW_Network!$F$2:$F$21,RAW_Network!$B$2:$B$21,"4",RAW_Network!$C$2:$C$21,"Facebook"),"-") | E6: =SUMIFS(RAW_Network!$F$2:$F$21,RAW_Network!$B$2:$B$21,"4",RAW_Network!$C$2:$C$21,"Facebook") | F6: =SUMIFS(RAW_Network!$D$2:$D$21,RAW_Network!$B$2:$B$21,"4",RAW_Network!$C$2:$C$21,"Instagram") | G6: =IFERROR(SUMIFS(RAW_Network!$D$2:$D$21,RAW_Network!$B$2:$B$21,"4",RAW_Network!$C$2:$C$21,"Instagram")/SUMIFS(RAW_Network!$E$2:$E$21,RAW_Network!$B$2:$B$21,"4",RAW_Network!$C$2:$C$21,"Instagram"),"-") | H6: =IFERROR(SUMIFS(RAW_Network!$D$2:$D$21,RAW_Network!$B$2:$B$21,"4",RAW_Network!$C$2:$C$21,"Instagram")/SUMIFS(RAW_Network!$F$2:$F$21,RAW_Network!$B$2:$B$21,"4",RAW_Network!$C$2:$C$21,"Instagram"),"-") | I6: =SUMIFS(RAW_Network!$F$2:$F$21,RAW_Network!$B$2:$B$21,"4",RAW_Network!$C$2:$C$21,"Instagram")
A7: Oct 5 | B7: =SUMIFS(RAW_Network!$D$2:$D$21,RAW_Network!$B$2:$B$21,"5",RAW_Network!$C$2:$C$21,"Facebook") | C7: =IFERROR(SUMIFS(RAW_Network!$D$2:$D$21,RAW_Network!$B$2:$B$21,"5",RAW_Network!$C$2:$C$21,"Facebook")/SUMIFS(RAW_Network!$E$2:$E$21,RAW_Network!$B$2:$B$21,"5",RAW_Network!$C$2:$C$21,"Facebook"),"-") | D7: =IFERROR(SUMIFS(RAW_Network!$D$2:$D$21,RAW_Network!$B$2:$B$21,"5",RAW_Network!$C$2:$C$21,"Facebook")/SUMIFS(RAW_Network!$F$2:$F$21,RAW_Network!$B$2:$B$21,"5",RAW_Network!$C$2:$C$21,"Facebook"),"-") | E7: =SUMIFS(RAW_Network!$F$2:$F$21,RAW_Network!$B$2:$B$21,"5",RAW_Network!$C$2:$C$21,"Facebook") | F7: =SUMIFS(RAW_Network!$D$2:$D$21,RAW_Network!$B$2:$B$21,"5",RAW_Network!$C$2:$C$21,"Instagram") | G7: =IFERROR(SUMIFS(RAW_Network!$D$2:$D$21,RAW_Network!$B$2:$B$21,"5",RAW_Network!$C$2:$C$21,"Instagram")/SUMIFS(RAW_Network!$E$2:$E$21,RAW_Network!$B$2:$B$21,"5",RAW_Network!$C$2:$C$21,"Instagram"),"-") | H7: =IFERROR(SUMIFS(RAW_Network!$D$2:$D$21,RAW_Network!$B$2:$B$21,"5",RAW_Network!$C$2:$C$21,"Instagram")/SUMIFS(RAW_Network!$F$2:$F$21,RAW_Network!$B$2:$B$21,"5",RAW_Network!$C$2:$C$21,"Instagram"),"-") | I7: =SUMIFS(RAW_Network!$F$2:$F$21,RAW_Network!$B$2:$B$21,"5",RAW_Network!$C$2:$C$21,"Instagram")

Sheet Age Split
A1: AGE SPLIT - share of spend + CPI + Trial CAC, per window. Check whether CAC rises uniformly across age bands (systemic) or in one band (mix shift).
A2: Window | B2: Segment | C2: Spend (Rs) | D2: Spend % | E2: Installs | F2: CPI | G2: Trials | H2: Trial CAC | I2: Inflation
A3: Before Oct 1-2 | B3: 18-24 | C3: =SUMIFS(RAW_Age!$D$2:$D$31,RAW_Age!$B$2:$B$31,">=1",RAW_Age!$B$2:$B$31,"<=2",RAW_Age!$C$2:$C$31,"18-24") | D3: =IFERROR(SUMIFS(RAW_Age!$D$2:$D$31,RAW_Age!$B$2:$B$31,">=1",RAW_Age!$B$2:$B$31,"<=2",RAW_Age!$C$2:$C$31,"18-24")/SUMIFS(RAW_Age!$D$2:$D$31,RAW_Age!$B$2:$B$31,">=1",RAW_Age!$B$2:$B$31,"<=2")*100,"-") | E3: =SUMIFS(RAW_Age!$E$2:$E$31,RAW_Age!$B$2:$B$31,">=1",RAW_Age!$B$2:$B$31,"<=2",RAW_Age!$C$2:$C$31,"18-24") | F3: =IFERROR(SUMIFS(RAW_Age!$D$2:$D$31,RAW_Age!$B$2:$B$31,">=1",RAW_Age!$B$2:$B$31,"<=2",RAW_Age!$C$2:$C$31,"18-24")/SUMIFS(RAW_Age!$E$2:$E$31,RAW_Age!$B$2:$B$31,">=1",RAW_Age!$B$2:$B$31,"<=2",RAW_Age!$C$2:$C$31,"18-24"),"-") | G3: =SUMIFS(RAW_Age!$F$2:$F$31,RAW_Age!$B$2:$B$31,">=1",RAW_Age!$B$2:$B$31,"<=2",RAW_Age!$C$2:$C$31,"18-24") | H3: =IFERROR(SUMIFS(RAW_Age!$D$2:$D$31,RAW_Age!$B$2:$B$31,">=1",RAW_Age!$B$2:$B$31,"<=2",RAW_Age!$C$2:$C$31,"18-24")/SUMIFS(RAW_Age!$F$2:$F$31,RAW_Age!$B$2:$B$31,">=1",RAW_Age!$B$2:$B$31,"<=2",RAW_Age!$C$2:$C$31,"18-24"),"-")
B4: 25-34 | C4: =SUMIFS(RAW_Age!$D$2:$D$31,RAW_Age!$B$2:$B$31,">=1",RAW_Age!$B$2:$B$31,"<=2",RAW_Age!$C$2:$C$31,"25-34") | D4: =IFERROR(SUMIFS(RAW_Age!$D$2:$D$31,RAW_Age!$B$2:$B$31,">=1",RAW_Age!$B$2:$B$31,"<=2",RAW_Age!$C$2:$C$31,"25-34")/SUMIFS(RAW_Age!$D$2:$D$31,RAW_Age!$B$2:$B$31,">=1",RAW_Age!$B$2:$B$31,"<=2")*100,"-") | E4: =SUMIFS(RAW_Age!$E$2:$E$31,RAW_Age!$B$2:$B$31,">=1",RAW_Age!$B$2:$B$31,"<=2",RAW_Age!$C$2:$C$31,"25-34") | F4: =IFERROR(SUMIFS(RAW_Age!$D$2:$D$31,RAW_Age!$B$2:$B$31,">=1",RAW_Age!$B$2:$B$31,"<=2",RAW_Age!$C$2:$C$31,"25-34")/SUMIFS(RAW_Age!$E$2:$E$31,RAW_Age!$B$2:$B$31,">=1",RAW_Age!$B$2:$B$31,"<=2",RAW_Age!$C$2:$C$31,"25-34"),"-") | G4: =SUMIFS(RAW_Age!$F$2:$F$31,RAW_Age!$B$2:$B$31,">=1",RAW_Age!$B$2:$B$31,"<=2",RAW_Age!$C$2:$C$31,"25-34") | H4: =IFERROR(SUMIFS(RAW_Age!$D$2:$D$31,RAW_Age!$B$2:$B$31,">=1",RAW_Age!$B$2:$B$31,"<=2",RAW_Age!$C$2:$C$31,"25-34")/SUMIFS(RAW_Age!$F$2:$F$31,RAW_Age!$B$2:$B$31,">=1",RAW_Age!$B$2:$B$31,"<=2",RAW_Age!$C$2:$C$31,"25-34"),"-")
B5: 35-44 | C5: =SUMIFS(RAW_Age!$D$2:$D$31,RAW_Age!$B$2:$B$31,">=1",RAW_Age!$B$2:$B$31,"<=2",RAW_Age!$C$2:$C$31,"35-44") | D5: =IFERROR(SUMIFS(RAW_Age!$D$2:$D$31,RAW_Age!$B$2:$B$31,">=1",RAW_Age!$B$2:$B$31,"<=2",RAW_Age!$C$2:$C$31,"35-44")/SUMIFS(RAW_Age!$D$2:$D$31,RAW_Age!$B$2:$B$31,">=1",RAW_Age!$B$2:$B$31,"<=2")*100,"-") | E5: =SUMIFS(RAW_Age!$E$2:$E$31,RAW_Age!$B$2:$B$31,">=1",RAW_Age!$B$2:$B$31,"<=2",RAW_Age!$C$2:$C$31,"35-44") | F5: =IFERROR(SUMIFS(RAW_Age!$D$2:$D$31,RAW_Age!$B$2:$B$31,">=1",RAW_Age!$B$2:$B$31,"<=2",RAW_Age!$C$2:$C$31,"35-44")/SUMIFS(RAW_Age!$E$2:$E$31,RAW_Age!$B$2:$B$31,">=1",RAW_Age!$B$2:$B$31,"<=2",RAW_Age!$C$2:$C$31,"35-44"),"-") | G5: =SUMIFS(RAW_Age!$F$2:$F$31,RAW_Age!$B$2:$B$31,">=1",RAW_Age!$B$2:$B$31,"<=2",RAW_Age!$C$2:$C$31,"35-44") | H5: =IFERROR(SUMIFS(RAW_Age!$D$2:$D$31,RAW_Age!$B$2:$B$31,">=1",RAW_Age!$B$2:$B$31,"<=2",RAW_Age!$C$2:$C$31,"35-44")/SUMIFS(RAW_Age!$F$2:$F$31,RAW_Age!$B$2:$B$31,">=1",RAW_Age!$B$2:$B$31,"<=2",RAW_Age!$C$2:$C$31,"35-44"),"-")
B6: 45-54 | C6: =SUMIFS(RAW_Age!$D$2:$D$31,RAW_Age!$B$2:$B$31,">=1",RAW_Age!$B$2:$B$31,"<=2",RAW_Age!$C$2:$C$31,"45-54") | D6: =IFERROR(SUMIFS(RAW_Age!$D$2:$D$31,RAW_Age!$B$2:$B$31,">=1",RAW_Age!$B$2:$B$31,"<=2",RAW_Age!$C$2:$C$31,"45-54")/SUMIFS(RAW_Age!$D$2:$D$31,RAW_Age!$B$2:$B$31,">=1",RAW_Age!$B$2:$B$31,"<=2")*100,"-") | E6: =SUMIFS(RAW_Age!$E$2:$E$31,RAW_Age!$B$2:$B$31,">=1",RAW_Age!$B$2:$B$31,"<=2",RAW_Age!$C$2:$C$31,"45-54") | F6: =IFERROR(SUMIFS(RAW_Age!$D$2:$D$31,RAW_Age!$B$2:$B$31,">=1",RAW_Age!$B$2:$B$31,"<=2",RAW_Age!$C$2:$C$31,"45-54")/SUMIFS(RAW_Age!$E$2:$E$31,RAW_Age!$B$2:$B$31,">=1",RAW_Age!$B$2:$B$31,"<=2",RAW_Age!$C$2:$C$31,"45-54"),"-") | G6: =SUMIFS(RAW_Age!$F$2:$F$31,RAW_Age!$B$2:$B$31,">=1",RAW_Age!$B$2:$B$31,"<=2",RAW_Age!$C$2:$C$31,"45-54") | H6: =IFERROR(SUMIFS(RAW_Age!$D$2:$D$31,RAW_Age!$B$2:$B$31,">=1",RAW_Age!$B$2:$B$31,"<=2",RAW_Age!$C$2:$C$31,"45-54")/SUMIFS(RAW_Age!$F$2:$F$31,RAW_Age!$B$2:$B$31,">=1",RAW_Age!$B$2:$B$31,"<=2",RAW_Age!$C$2:$C$31,"45-54"),"-")
B7: 55-64 | C7: =SUMIFS(RAW_Age!$D$2:$D$31,RAW_Age!$B$2:$B$31,">=1",RAW_Age!$B$2:$B$31,"<=2",RAW_Age!$C$2:$C$31,"55-64") | D7: =IFERROR(SUMIFS(RAW_Age!$D$2:$D$31,RAW_Age!$B$2:$B$31,">=1",RAW_Age!$B$2:$B$31,"<=2",RAW_Age!$C$2:$C$31,"55-64")/SUMIFS(RAW_Age!$D$2:$D$31,RAW_Age!$B$2:$B$31,">=1",RAW_Age!$B$2:$B$31,"<=2")*100,"-") | E7: =SUMIFS(RAW_Age!$E$2:$E$31,RAW_Age!$B$2:$B$31,">=1",RAW_Age!$B$2:$B$31,"<=2",RAW_Age!$C$2:$C$31,"55-64") | F7: =IFERROR(SUMIFS(RAW_Age!$D$2:$D$31,RAW_Age!$B$2:$B$31,">=1",RAW_Age!$B$2:$B$31,"<=2",RAW_Age!$C$2:$C$31,"55-64")/SUMIFS(RAW_Age!$E$2:$E$31,RAW_Age!$B$2:$B$31,">=1",RAW_Age!$B$2:$B$31,"<=2",RAW_Age!$C$2:$C$31,"55-64"),"-") | G7: =SUMIFS(RAW_Age!$F$2:$F$31,RAW_Age!$B$2:$B$31,">=1",RAW_Age!$B$2:$B$31,"<=2",RAW_Age!$C$2:$C$31,"55-64") | H7: =IFERROR(SUMIFS(RAW_Age!$D$2:$D$31,RAW_Age!$B$2:$B$31,">=1",RAW_Age!$B$2:$B$31,"<=2",RAW_Age!$C$2:$C$31,"55-64")/SUMIFS(RAW_Age!$F$2:$F$31,RAW_Age!$B$2:$B$31,">=1",RAW_Age!$B$2:$B$31,"<=2",RAW_Age!$C$2:$C$31,"55-64"),"-")
B8: 65+ | C8: =SUMIFS(RAW_Age!$D$2:$D$31,RAW_Age!$B$2:$B$31,">=1",RAW_Age!$B$2:$B$31,"<=2",RAW_Age!$C$2:$C$31,"65+") | D8: =IFERROR(SUMIFS(RAW_Age!$D$2:$D$31,RAW_Age!$B$2:$B$31,">=1",RAW_Age!$B$2:$B$31,"<=2",RAW_Age!$C$2:$C$31,"65+")/SUMIFS(RAW_Age!$D$2:$D$31,RAW_Age!$B$2:$B$31,">=1",RAW_Age!$B$2:$B$31,"<=2")*100,"-") | E8: =SUMIFS(RAW_Age!$E$2:$E$31,RAW_Age!$B$2:$B$31,">=1",RAW_Age!$B$2:$B$31,"<=2",RAW_Age!$C$2:$C$31,"65+") | F8: =IFERROR(SUMIFS(RAW_Age!$D$2:$D$31,RAW_Age!$B$2:$B$31,">=1",RAW_Age!$B$2:$B$31,"<=2",RAW_Age!$C$2:$C$31,"65+")/SUMIFS(RAW_Age!$E$2:$E$31,RAW_Age!$B$2:$B$31,">=1",RAW_Age!$B$2:$B$31,"<=2",RAW_Age!$C$2:$C$31,"65+"),"-") | G8: =SUMIFS(RAW_Age!$F$2:$F$31,RAW_Age!$B$2:$B$31,">=1",RAW_Age!$B$2:$B$31,"<=2",RAW_Age!$C$2:$C$31,"65+") | H8: =IFERROR(SUMIFS(RAW_Age!$D$2:$D$31,RAW_Age!$B$2:$B$31,">=1",RAW_Age!$B$2:$B$31,"<=2",RAW_Age!$C$2:$C$31,"65+")/SUMIFS(RAW_Age!$F$2:$F$31,RAW_Age!$B$2:$B$31,">=1",RAW_Age!$B$2:$B$31,"<=2",RAW_Age!$C$2:$C$31,"65+"),"-")
A9: After Oct 3-4 | B9: 18-24 | C9: =SUMIFS(RAW_Age!$D$2:$D$31,RAW_Age!$B$2:$B$31,">=3",RAW_Age!$B$2:$B$31,"<=4",RAW_Age!$C$2:$C$31,"18-24") | D9: =IFERROR(SUMIFS(RAW_Age!$D$2:$D$31,RAW_Age!$B$2:$B$31,">=3",RAW_Age!$B$2:$B$31,"<=4",RAW_Age!$C$2:$C$31,"18-24")/SUMIFS(RAW_Age!$D$2:$D$31,RAW_Age!$B$2:$B$31,">=3",RAW_Age!$B$2:$B$31,"<=4")*100,"-") | E9: =SUMIFS(RAW_Age!$E$2:$E$31,RAW_Age!$B$2:$B$31,">=3",RAW_Age!$B$2:$B$31,"<=4",RAW_Age!$C$2:$C$31,"18-24") | F9: =IFERROR(SUMIFS(RAW_Age!$D$2:$D$31,RAW_Age!$B$2:$B$31,">=3",RAW_Age!$B$2:$B$31,"<=4",RAW_Age!$C$2:$C$31,"18-24")/SUMIFS(RAW_Age!$E$2:$E$31,RAW_Age!$B$2:$B$31,">=3",RAW_Age!$B$2:$B$31,"<=4",RAW_Age!$C$2:$C$31,"18-24"),"-") | G9: =SUMIFS(RAW_Age!$F$2:$F$31,RAW_Age!$B$2:$B$31,">=3",RAW_Age!$B$2:$B$31,"<=4",RAW_Age!$C$2:$C$31,"18-24") | H9: =IFERROR(SUMIFS(RAW_Age!$D$2:$D$31,RAW_Age!$B$2:$B$31,">=3",RAW_Age!$B$2:$B$31,"<=4",RAW_Age!$C$2:$C$31,"18-24")/SUMIFS(RAW_Age!$F$2:$F$31,RAW_Age!$B$2:$B$31,">=3",RAW_Age!$B$2:$B$31,"<=4",RAW_Age!$C$2:$C$31,"18-24"),"-") | I9: =IFERROR(F9/F3,"-")
B10: 25-34 | C10: =SUMIFS(RAW_Age!$D$2:$D$31,RAW_Age!$B$2:$B$31,">=3",RAW_Age!$B$2:$B$31,"<=4",RAW_Age!$C$2:$C$31,"25-34") | D10: =IFERROR(SUMIFS(RAW_Age!$D$2:$D$31,RAW_Age!$B$2:$B$31,">=3",RAW_Age!$B$2:$B$31,"<=4",RAW_Age!$C$2:$C$31,"25-34")/SUMIFS(RAW_Age!$D$2:$D$31,RAW_Age!$B$2:$B$31,">=3",RAW_Age!$B$2:$B$31,"<=4")*100,"-") | E10: =SUMIFS(RAW_Age!$E$2:$E$31,RAW_Age!$B$2:$B$31,">=3",RAW_Age!$B$2:$B$31,"<=4",RAW_Age!$C$2:$C$31,"25-34") | F10: =IFERROR(SUMIFS(RAW_Age!$D$2:$D$31,RAW_Age!$B$2:$B$31,">=3",RAW_Age!$B$2:$B$31,"<=4",RAW_Age!$C$2:$C$31,"25-34")/SUMIFS(RAW_Age!$E$2:$E$31,RAW_Age!$B$2:$B$31,">=3",RAW_Age!$B$2:$B$31,"<=4",RAW_Age!$C$2:$C$31,"25-34"),"-") | G10: =SUMIFS(RAW_Age!$F$2:$F$31,RAW_Age!$B$2:$B$31,">=3",RAW_Age!$B$2:$B$31,"<=4",RAW_Age!$C$2:$C$31,"25-34") | H10: =IFERROR(SUMIFS(RAW_Age!$D$2:$D$31,RAW_Age!$B$2:$B$31,">=3",RAW_Age!$B$2:$B$31,"<=4",RAW_Age!$C$2:$C$31,"25-34")/SUMIFS(RAW_Age!$F$2:$F$31,RAW_Age!$B$2:$B$31,">=3",RAW_Age!$B$2:$B$31,"<=4",RAW_Age!$C$2:$C$31,"25-34"),"-") | I10: =IFERROR(F10/F4,"-")
B11: 35-44 | C11: =SUMIFS(RAW_Age!$D$2:$D$31,RAW_Age!$B$2:$B$31,">=3",RAW_Age!$B$2:$B$31,"<=4",RAW_Age!$C$2:$C$31,"35-44") | D11: =IFERROR(SUMIFS(RAW_Age!$D$2:$D$31,RAW_Age!$B$2:$B$31,">=3",RAW_Age!$B$2:$B$31,"<=4",RAW_Age!$C$2:$C$31,"35-44")/SUMIFS(RAW_Age!$D$2:$D$31,RAW_Age!$B$2:$B$31,">=3",RAW_Age!$B$2:$B$31,"<=4")*100,"-") | E11: =SUMIFS(RAW_Age!$E$2:$E$31,RAW_Age!$B$2:$B$31,">=3",RAW_Age!$B$2:$B$31,"<=4",RAW_Age!$C$2:$C$31,"35-44") | F11: =IFERROR(SUMIFS(RAW_Age!$D$2:$D$31,RAW_Age!$B$2:$B$31,">=3",RAW_Age!$B$2:$B$31,"<=4",RAW_Age!$C$2:$C$31,"35-44")/SUMIFS(RAW_Age!$E$2:$E$31,RAW_Age!$B$2:$B$31,">=3",RAW_Age!$B$2:$B$31,"<=4",RAW_Age!$C$2:$C$31,"35-44"),"-") | G11: =SUMIFS(RAW_Age!$F$2:$F$31,RAW_Age!$B$2:$B$31,">=3",RAW_Age!$B$2:$B$31,"<=4",RAW_Age!$C$2:$C$31,"35-44") | H11: =IFERROR(SUMIFS(RAW_Age!$D$2:$D$31,RAW_Age!$B$2:$B$31,">=3",RAW_Age!$B$2:$B$31,"<=4",RAW_Age!$C$2:$C$31,"35-44")/SUMIFS(RAW_Age!$F$2:$F$31,RAW_Age!$B$2:$B$31,">=3",RAW_Age!$B$2:$B$31,"<=4",RAW_Age!$C$2:$C$31,"35-44"),"-") | I11: =IFERROR(F11/F5,"-")
B12: 45-54 | C12: =SUMIFS(RAW_Age!$D$2:$D$31,RAW_Age!$B$2:$B$31,">=3",RAW_Age!$B$2:$B$31,"<=4",RAW_Age!$C$2:$C$31,"45-54") | D12: =IFERROR(SUMIFS(RAW_Age!$D$2:$D$31,RAW_Age!$B$2:$B$31,">=3",RAW_Age!$B$2:$B$31,"<=4",RAW_Age!$C$2:$C$31,"45-54")/SUMIFS(RAW_Age!$D$2:$D$31,RAW_Age!$B$2:$B$31,">=3",RAW_Age!$B$2:$B$31,"<=4")*100,"-") | E12: =SUMIFS(RAW_Age!$E$2:$E$31,RAW_Age!$B$2:$B$31,">=3",RAW_Age!$B$2:$B$31,"<=4",RAW_Age!$C$2:$C$31,"45-54") | F12: =IFERROR(SUMIFS(RAW_Age!$D$2:$D$31,RAW_Age!$B$2:$B$31,">=3",RAW_Age!$B$2:$B$31,"<=4",RAW_Age!$C$2:$C$31,"45-54")/SUMIFS(RAW_Age!$E$2:$E$31,RAW_Age!$B$2:$B$31,">=3",RAW_Age!$B$2:$B$31,"<=4",RAW_Age!$C$2:$C$31,"45-54"),"-") | G12: =SUMIFS(RAW_Age!$F$2:$F$31,RAW_Age!$B$2:$B$31,">=3",RAW_Age!$B$2:$B$31,"<=4",RAW_Age!$C$2:$C$31,"45-54") | H12: =IFERROR(SUMIFS(RAW_Age!$D$2:$D$31,RAW_Age!$B$2:$B$31,">=3",RAW_Age!$B$2:$B$31,"<=4",RAW_Age!$C$2:$C$31,"45-54")/SUMIFS(RAW_Age!$F$2:$F$31,RAW_Age!$B$2:$B$31,">=3",RAW_Age!$B$2:$B$31,"<=4",RAW_Age!$C$2:$C$31,"45-54"),"-") | I12: =IFERROR(F12/F6,"-")
B13: 55-64 | C13: =SUMIFS(RAW_Age!$D$2:$D$31,RAW_Age!$B$2:$B$31,">=3",RAW_Age!$B$2:$B$31,"<=4",RAW_Age!$C$2:$C$31,"55-64") | D13: =IFERROR(SUMIFS(RAW_Age!$D$2:$D$31,RAW_Age!$B$2:$B$31,">=3",RAW_Age!$B$2:$B$31,"<=4",RAW_Age!$C$2:$C$31,"55-64")/SUMIFS(RAW_Age!$D$2:$D$31,RAW_Age!$B$2:$B$31,">=3",RAW_Age!$B$2:$B$31,"<=4")*100,"-") | E13: =SUMIFS(RAW_Age!$E$2:$E$31,RAW_Age!$B$2:$B$31,">=3",RAW_Age!$B$2:$B$31,"<=4",RAW_Age!$C$2:$C$31,"55-64") | F13: =IFERROR(SUMIFS(RAW_Age!$D$2:$D$31,RAW_Age!$B$2:$B$31,">=3",RAW_Age!$B$2:$B$31,"<=4",RAW_Age!$C$2:$C$31,"55-64")/SUMIFS(RAW_Age!$E$2:$E$31,RAW_Age!$B$2:$B$31,">=3",RAW_Age!$B$2:$B$31,"<=4",RAW_Age!$C$2:$C$31,"55-64"),"-") | G13: =SUMIFS(RAW_Age!$F$2:$F$31,RAW_Age!$B$2:$B$31,">=3",RAW_Age!$B$2:$B$31,"<=4",RAW_Age!$C$2:$C$31,"55-64") | H13: =IFERROR(SUMIFS(RAW_Age!$D$2:$D$31,RAW_Age!$B$2:$B$31,">=3",RAW_Age!$B$2:$B$31,"<=4",RAW_Age!$C$2:$C$31,"55-64")/SUMIFS(RAW_Age!$F$2:$F$31,RAW_Age!$B$2:$B$31,">=3",RAW_Age!$B$2:$B$31,"<=4",RAW_Age!$C$2:$C$31,"55-64"),"-") | I13: =IFERROR(F13/F7,"-")
B14: 65+ | C14: =SUMIFS(RAW_Age!$D$2:$D$31,RAW_Age!$B$2:$B$31,">=3",RAW_Age!$B$2:$B$31,"<=4",RAW_Age!$C$2:$C$31,"65+") | D14: =IFERROR(SUMIFS(RAW_Age!$D$2:$D$31,RAW_Age!$B$2:$B$31,">=3",RAW_Age!$B$2:$B$31,"<=4",RAW_Age!$C$2:$C$31,"65+")/SUMIFS(RAW_Age!$D$2:$D$31,RAW_Age!$B$2:$B$31,">=3",RAW_Age!$B$2:$B$31,"<=4")*100,"-") | E14: =SUMIFS(RAW_Age!$E$2:$E$31,RAW_Age!$B$2:$B$31,">=3",RAW_Age!$B$2:$B$31,"<=4",RAW_Age!$C$2:$C$31,"65+") | F14: =IFERROR(SUMIFS(RAW_Age!$D$2:$D$31,RAW_Age!$B$2:$B$31,">=3",RAW_Age!$B$2:$B$31,"<=4",RAW_Age!$C$2:$C$31,"65+")/SUMIFS(RAW_Age!$E$2:$E$31,RAW_Age!$B$2:$B$31,">=3",RAW_Age!$B$2:$B$31,"<=4",RAW_Age!$C$2:$C$31,"65+"),"-") | G14: =SUMIFS(RAW_Age!$F$2:$F$31,RAW_Age!$B$2:$B$31,">=3",RAW_Age!$B$2:$B$31,"<=4",RAW_Age!$C$2:$C$31,"65+") | H14: =IFERROR(SUMIFS(RAW_Age!$D$2:$D$31,RAW_Age!$B$2:$B$31,">=3",RAW_Age!$B$2:$B$31,"<=4",RAW_Age!$C$2:$C$31,"65+")/SUMIFS(RAW_Age!$F$2:$F$31,RAW_Age!$B$2:$B$31,">=3",RAW_Age!$B$2:$B$31,"<=4",RAW_Age!$C$2:$C$31,"65+"),"-") | I14: =IFERROR(F14/F8,"-")

Sheet Gender Split
A1: GENDER SPLIT - share of spend + CPI + Trial CAC, per window. Mix is stable (~80% male); check both degrade together.
A2: Window | B2: Segment | C2: Spend (Rs) | D2: Spend % | E2: Installs | F2: CPI | G2: Trials | H2: Trial CAC | I2: Inflation
A3: Before Oct 1-2 | B3: Male | C3: =SUMIFS(RAW_Gender!$D$2:$D$11,RAW_Gender!$B$2:$B$11,">=1",RAW_Gender!$B$2:$B$11,"<=2",RAW_Gender!$C$2:$C$11,"Male") | D3: =IFERROR(SUMIFS(RAW_Gender!$D$2:$D$11,RAW_Gender!$B$2:$B$11,">=1",RAW_Gender!$B$2:$B$11,"<=2",RAW_Gender!$C$2:$C$11,"Male")/SUMIFS(RAW_Gender!$D$2:$D$11,RAW_Gender!$B$2:$B$11,">=1",RAW_Gender!$B$2:$B$11,"<=2")*100,"-") | E3: =SUMIFS(RAW_Gender!$E$2:$E$11,RAW_Gender!$B$2:$B$11,">=1",RAW_Gender!$B$2:$B$11,"<=2",RAW_Gender!$C$2:$C$11,"Male") | F3: =IFERROR(SUMIFS(RAW_Gender!$D$2:$D$11,RAW_Gender!$B$2:$B$11,">=1",RAW_Gender!$B$2:$B$11,"<=2",RAW_Gender!$C$2:$C$11,"Male")/SUMIFS(RAW_Gender!$E$2:$E$11,RAW_Gender!$B$2:$B$11,">=1",RAW_Gender!$B$2:$B$11,"<=2",RAW_Gender!$C$2:$C$11,"Male"),"-") | G3: =SUMIFS(RAW_Gender!$F$2:$F$11,RAW_Gender!$B$2:$B$11,">=1",RAW_Gender!$B$2:$B$11,"<=2",RAW_Gender!$C$2:$C$11,"Male") | H3: =IFERROR(SUMIFS(RAW_Gender!$D$2:$D$11,RAW_Gender!$B$2:$B$11,">=1",RAW_Gender!$B$2:$B$11,"<=2",RAW_Gender!$C$2:$C$11,"Male")/SUMIFS(RAW_Gender!$F$2:$F$11,RAW_Gender!$B$2:$B$11,">=1",RAW_Gender!$B$2:$B$11,"<=2",RAW_Gender!$C$2:$C$11,"Male"),"-")
B4: Female | C4: =SUMIFS(RAW_Gender!$D$2:$D$11,RAW_Gender!$B$2:$B$11,">=1",RAW_Gender!$B$2:$B$11,"<=2",RAW_Gender!$C$2:$C$11,"Female") | D4: =IFERROR(SUMIFS(RAW_Gender!$D$2:$D$11,RAW_Gender!$B$2:$B$11,">=1",RAW_Gender!$B$2:$B$11,"<=2",RAW_Gender!$C$2:$C$11,"Female")/SUMIFS(RAW_Gender!$D$2:$D$11,RAW_Gender!$B$2:$B$11,">=1",RAW_Gender!$B$2:$B$11,"<=2")*100,"-") | E4: =SUMIFS(RAW_Gender!$E$2:$E$11,RAW_Gender!$B$2:$B$11,">=1",RAW_Gender!$B$2:$B$11,"<=2",RAW_Gender!$C$2:$C$11,"Female") | F4: =IFERROR(SUMIFS(RAW_Gender!$D$2:$D$11,RAW_Gender!$B$2:$B$11,">=1",RAW_Gender!$B$2:$B$11,"<=2",RAW_Gender!$C$2:$C$11,"Female")/SUMIFS(RAW_Gender!$E$2:$E$11,RAW_Gender!$B$2:$B$11,">=1",RAW_Gender!$B$2:$B$11,"<=2",RAW_Gender!$C$2:$C$11,"Female"),"-") | G4: =SUMIFS(RAW_Gender!$F$2:$F$11,RAW_Gender!$B$2:$B$11,">=1",RAW_Gender!$B$2:$B$11,"<=2",RAW_Gender!$C$2:$C$11,"Female") | H4: =IFERROR(SUMIFS(RAW_Gender!$D$2:$D$11,RAW_Gender!$B$2:$B$11,">=1",RAW_Gender!$B$2:$B$11,"<=2",RAW_Gender!$C$2:$C$11,"Female")/SUMIFS(RAW_Gender!$F$2:$F$11,RAW_Gender!$B$2:$B$11,">=1",RAW_Gender!$B$2:$B$11,"<=2",RAW_Gender!$C$2:$C$11,"Female"),"-")
A5: After Oct 3-4 | B5: Male | C5: =SUMIFS(RAW_Gender!$D$2:$D$11,RAW_Gender!$B$2:$B$11,">=3",RAW_Gender!$B$2:$B$11,"<=4",RAW_Gender!$C$2:$C$11,"Male") | D5: =IFERROR(SUMIFS(RAW_Gender!$D$2:$D$11,RAW_Gender!$B$2:$B$11,">=3",RAW_Gender!$B$2:$B$11,"<=4",RAW_Gender!$C$2:$C$11,"Male")/SUMIFS(RAW_Gender!$D$2:$D$11,RAW_Gender!$B$2:$B$11,">=3",RAW_Gender!$B$2:$B$11,"<=4")*100,"-") | E5: =SUMIFS(RAW_Gender!$E$2:$E$11,RAW_Gender!$B$2:$B$11,">=3",RAW_Gender!$B$2:$B$11,"<=4",RAW_Gender!$C$2:$C$11,"Male") | F5: =IFERROR(SUMIFS(RAW_Gender!$D$2:$D$11,RAW_Gender!$B$2:$B$11,">=3",RAW_Gender!$B$2:$B$11,"<=4",RAW_Gender!$C$2:$C$11,"Male")/SUMIFS(RAW_Gender!$E$2:$E$11,RAW_Gender!$B$2:$B$11,">=3",RAW_Gender!$B$2:$B$11,"<=4",RAW_Gender!$C$2:$C$11,"Male"),"-") | G5: =SUMIFS(RAW_Gender!$F$2:$F$11,RAW_Gender!$B$2:$B$11,">=3",RAW_Gender!$B$2:$B$11,"<=4",RAW_Gender!$C$2:$C$11,"Male") | H5: =IFERROR(SUMIFS(RAW_Gender!$D$2:$D$11,RAW_Gender!$B$2:$B$11,">=3",RAW_Gender!$B$2:$B$11,"<=4",RAW_Gender!$C$2:$C$11,"Male")/SUMIFS(RAW_Gender!$F$2:$F$11,RAW_Gender!$B$2:$B$11,">=3",RAW_Gender!$B$2:$B$11,"<=4",RAW_Gender!$C$2:$C$11,"Male"),"-") | I5: =IFERROR(F5/F3,"-")
B6: Female | C6: =SUMIFS(RAW_Gender!$D$2:$D$11,RAW_Gender!$B$2:$B$11,">=3",RAW_Gender!$B$2:$B$11,"<=4",RAW_Gender!$C$2:$C$11,"Female") | D6: =IFERROR(SUMIFS(RAW_Gender!$D$2:$D$11,RAW_Gender!$B$2:$B$11,">=3",RAW_Gender!$B$2:$B$11,"<=4",RAW_Gender!$C$2:$C$11,"Female")/SUMIFS(RAW_Gender!$D$2:$D$11,RAW_Gender!$B$2:$B$11,">=3",RAW_Gender!$B$2:$B$11,"<=4")*100,"-") | E6: =SUMIFS(RAW_Gender!$E$2:$E$11,RAW_Gender!$B$2:$B$11,">=3",RAW_Gender!$B$2:$B$11,"<=4",RAW_Gender!$C$2:$C$11,"Female") | F6: =IFERROR(SUMIFS(RAW_Gender!$D$2:$D$11,RAW_Gender!$B$2:$B$11,">=3",RAW_Gender!$B$2:$B$11,"<=4",RAW_Gender!$C$2:$C$11,"Female")/SUMIFS(RAW_Gender!$E$2:$E$11,RAW_Gender!$B$2:$B$11,">=3",RAW_Gender!$B$2:$B$11,"<=4",RAW_Gender!$C$2:$C$11,"Female"),"-") | G6: =SUMIFS(RAW_Gender!$F$2:$F$11,RAW_Gender!$B$2:$B$11,">=3",RAW_Gender!$B$2:$B$11,"<=4",RAW_Gender!$C$2:$C$11,"Female") | H6: =IFERROR(SUMIFS(RAW_Gender!$D$2:$D$11,RAW_Gender!$B$2:$B$11,">=3",RAW_Gender!$B$2:$B$11,"<=4",RAW_Gender!$C$2:$C$11,"Female")/SUMIFS(RAW_Gender!$F$2:$F$11,RAW_Gender!$B$2:$B$11,">=3",RAW_Gender!$B$2:$B$11,"<=4",RAW_Gender!$C$2:$C$11,"Female"),"-") | I6: =IFERROR(F6/F4,"-")

Sheet Placement Split
A1: PLACEMENT SPLIT - top placements, share of spend + CPI + Trial CAC. Inflation = After CPI / Before CPI. Broad rise = systemic.
A2: Window | B2: Segment | C2: Spend (Rs) | D2: Spend % | E2: Installs | F2: CPI | G2: Trials | H2: Trial CAC | I2: Inflation
A3: Before Oct 1-2 | B3: Facebook Reels | C3: =SUMIFS(RAW_Placement!$D$2:$D$36,RAW_Placement!$B$2:$B$36,">=1",RAW_Placement!$B$2:$B$36,"<=2",RAW_Placement!$C$2:$C$36,"Facebook Reels") | D3: =IFERROR(SUMIFS(RAW_Placement!$D$2:$D$36,RAW_Placement!$B$2:$B$36,">=1",RAW_Placement!$B$2:$B$36,"<=2",RAW_Placement!$C$2:$C$36,"Facebook Reels")/SUMIFS(RAW_Placement!$D$2:$D$36,RAW_Placement!$B$2:$B$36,">=1",RAW_Placement!$B$2:$B$36,"<=2")*100,"-") | E3: =SUMIFS(RAW_Placement!$E$2:$E$36,RAW_Placement!$B$2:$B$36,">=1",RAW_Placement!$B$2:$B$36,"<=2",RAW_Placement!$C$2:$C$36,"Facebook Reels") | F3: =IFERROR(SUMIFS(RAW_Placement!$D$2:$D$36,RAW_Placement!$B$2:$B$36,">=1",RAW_Placement!$B$2:$B$36,"<=2",RAW_Placement!$C$2:$C$36,"Facebook Reels")/SUMIFS(RAW_Placement!$E$2:$E$36,RAW_Placement!$B$2:$B$36,">=1",RAW_Placement!$B$2:$B$36,"<=2",RAW_Placement!$C$2:$C$36,"Facebook Reels"),"-") | G3: =SUMIFS(RAW_Placement!$F$2:$F$36,RAW_Placement!$B$2:$B$36,">=1",RAW_Placement!$B$2:$B$36,"<=2",RAW_Placement!$C$2:$C$36,"Facebook Reels") | H3: =IFERROR(SUMIFS(RAW_Placement!$D$2:$D$36,RAW_Placement!$B$2:$B$36,">=1",RAW_Placement!$B$2:$B$36,"<=2",RAW_Placement!$C$2:$C$36,"Facebook Reels")/SUMIFS(RAW_Placement!$F$2:$F$36,RAW_Placement!$B$2:$B$36,">=1",RAW_Placement!$B$2:$B$36,"<=2",RAW_Placement!$C$2:$C$36,"Facebook Reels"),"-")
B4: Facebook Feed | C4: =SUMIFS(RAW_Placement!$D$2:$D$36,RAW_Placement!$B$2:$B$36,">=1",RAW_Placement!$B$2:$B$36,"<=2",RAW_Placement!$C$2:$C$36,"Facebook Feed") | D4: =IFERROR(SUMIFS(RAW_Placement!$D$2:$D$36,RAW_Placement!$B$2:$B$36,">=1",RAW_Placement!$B$2:$B$36,"<=2",RAW_Placement!$C$2:$C$36,"Facebook Feed")/SUMIFS(RAW_Placement!$D$2:$D$36,RAW_Placement!$B$2:$B$36,">=1",RAW_Placement!$B$2:$B$36,"<=2")*100,"-") | E4: =SUMIFS(RAW_Placement!$E$2:$E$36,RAW_Placement!$B$2:$B$36,">=1",RAW_Placement!$B$2:$B$36,"<=2",RAW_Placement!$C$2:$C$36,"Facebook Feed") | F4: =IFERROR(SUMIFS(RAW_Placement!$D$2:$D$36,RAW_Placement!$B$2:$B$36,">=1",RAW_Placement!$B$2:$B$36,"<=2",RAW_Placement!$C$2:$C$36,"Facebook Feed")/SUMIFS(RAW_Placement!$E$2:$E$36,RAW_Placement!$B$2:$B$36,">=1",RAW_Placement!$B$2:$B$36,"<=2",RAW_Placement!$C$2:$C$36,"Facebook Feed"),"-") | G4: =SUMIFS(RAW_Placement!$F$2:$F$36,RAW_Placement!$B$2:$B$36,">=1",RAW_Placement!$B$2:$B$36,"<=2",RAW_Placement!$C$2:$C$36,"Facebook Feed") | H4: =IFERROR(SUMIFS(RAW_Placement!$D$2:$D$36,RAW_Placement!$B$2:$B$36,">=1",RAW_Placement!$B$2:$B$36,"<=2",RAW_Placement!$C$2:$C$36,"Facebook Feed")/SUMIFS(RAW_Placement!$F$2:$F$36,RAW_Placement!$B$2:$B$36,">=1",RAW_Placement!$B$2:$B$36,"<=2",RAW_Placement!$C$2:$C$36,"Facebook Feed"),"-")
B5: Instagram Reels | C5: =SUMIFS(RAW_Placement!$D$2:$D$36,RAW_Placement!$B$2:$B$36,">=1",RAW_Placement!$B$2:$B$36,"<=2",RAW_Placement!$C$2:$C$36,"Instagram Reels") | D5: =IFERROR(SUMIFS(RAW_Placement!$D$2:$D$36,RAW_Placement!$B$2:$B$36,">=1",RAW_Placement!$B$2:$B$36,"<=2",RAW_Placement!$C$2:$C$36,"Instagram Reels")/SUMIFS(RAW_Placement!$D$2:$D$36,RAW_Placement!$B$2:$B$36,">=1",RAW_Placement!$B$2:$B$36,"<=2")*100,"-") | E5: =SUMIFS(RAW_Placement!$E$2:$E$36,RAW_Placement!$B$2:$B$36,">=1",RAW_Placement!$B$2:$B$36,"<=2",RAW_Placement!$C$2:$C$36,"Instagram Reels") | F5: =IFERROR(SUMIFS(RAW_Placement!$D$2:$D$36,RAW_Placement!$B$2:$B$36,">=1",RAW_Placement!$B$2:$B$36,"<=2",RAW_Placement!$C$2:$C$36,"Instagram Reels")/SUMIFS(RAW_Placement!$E$2:$E$36,RAW_Placement!$B$2:$B$36,">=1",RAW_Placement!$B$2:$B$36,"<=2",RAW_Placement!$C$2:$C$36,"Instagram Reels"),"-") | G5: =SUMIFS(RAW_Placement!$F$2:$F$36,RAW_Placement!$B$2:$B$36,">=1",RAW_Placement!$B$2:$B$36,"<=2",RAW_Placement!$C$2:$C$36,"Instagram Reels") | H5: =IFERROR(SUMIFS(RAW_Placement!$D$2:$D$36,RAW_Placement!$B$2:$B$36,">=1",RAW_Placement!$B$2:$B$36,"<=2",RAW_Placement!$C$2:$C$36,"Instagram Reels")/SUMIFS(RAW_Placement!$F$2:$F$36,RAW_Placement!$B$2:$B$36,">=1",RAW_Placement!$B$2:$B$36,"<=2",RAW_Placement!$C$2:$C$36,"Instagram Reels"),"-")
B6: Instagram Feed | C6: =SUMIFS(RAW_Placement!$D$2:$D$36,RAW_Placement!$B$2:$B$36,">=1",RAW_Placement!$B$2:$B$36,"<=2",RAW_Placement!$C$2:$C$36,"Instagram Feed") | D6: =IFERROR(SUMIFS(RAW_Placement!$D$2:$D$36,RAW_Placement!$B$2:$B$36,">=1",RAW_Placement!$B$2:$B$36,"<=2",RAW_Placement!$C$2:$C$36,"Instagram Feed")/SUMIFS(RAW_Placement!$D$2:$D$36,RAW_Placement!$B$2:$B$36,">=1",RAW_Placement!$B$2:$B$36,"<=2")*100,"-") | E6: =SUMIFS(RAW_Placement!$E$2:$E$36,RAW_Placement!$B$2:$B$36,">=1",RAW_Placement!$B$2:$B$36,"<=2",RAW_Placement!$C$2:$C$36,"Instagram Feed") | F6: =IFERROR(SUMIFS(RAW_Placement!$D$2:$D$36,RAW_Placement!$B$2:$B$36,">=1",RAW_Placement!$B$2:$B$36,"<=2",RAW_Placement!$C$2:$C$36,"Instagram Feed")/SUMIFS(RAW_Placement!$E$2:$E$36,RAW_Placement!$B$2:$B$36,">=1",RAW_Placement!$B$2:$B$36,"<=2",RAW_Placement!$C$2:$C$36,"Instagram Feed"),"-") | G6: =SUMIFS(RAW_Placement!$F$2:$F$36,RAW_Placement!$B$2:$B$36,">=1",RAW_Placement!$B$2:$B$36,"<=2",RAW_Placement!$C$2:$C$36,"Instagram Feed") | H6: =IFERROR(SUMIFS(RAW_Placement!$D$2:$D$36,RAW_Placement!$B$2:$B$36,">=1",RAW_Placement!$B$2:$B$36,"<=2",RAW_Placement!$C$2:$C$36,"Instagram Feed")/SUMIFS(RAW_Placement!$F$2:$F$36,RAW_Placement!$B$2:$B$36,">=1",RAW_Placement!$B$2:$B$36,"<=2",RAW_Placement!$C$2:$C$36,"Instagram Feed"),"-")
B7: Facebook Stories | C7: =SUMIFS(RAW_Placement!$D$2:$D$36,RAW_Placement!$B$2:$B$36,">=1",RAW_Placement!$B$2:$B$36,"<=2",RAW_Placement!$C$2:$C$36,"Facebook Stories") | D7: =IFERROR(SUMIFS(RAW_Placement!$D$2:$D$36,RAW_Placement!$B$2:$B$36,">=1",RAW_Placement!$B$2:$B$36,"<=2",RAW_Placement!$C$2:$C$36,"Facebook Stories")/SUMIFS(RAW_Placement!$D$2:$D$36,RAW_Placement!$B$2:$B$36,">=1",RAW_Placement!$B$2:$B$36,"<=2")*100,"-") | E7: =SUMIFS(RAW_Placement!$E$2:$E$36,RAW_Placement!$B$2:$B$36,">=1",RAW_Placement!$B$2:$B$36,"<=2",RAW_Placement!$C$2:$C$36,"Facebook Stories") | F7: =IFERROR(SUMIFS(RAW_Placement!$D$2:$D$36,RAW_Placement!$B$2:$B$36,">=1",RAW_Placement!$B$2:$B$36,"<=2",RAW_Placement!$C$2:$C$36,"Facebook Stories")/SUMIFS(RAW_Placement!$E$2:$E$36,RAW_Placement!$B$2:$B$36,">=1",RAW_Placement!$B$2:$B$36,"<=2",RAW_Placement!$C$2:$C$36,"Facebook Stories"),"-") | G7: =SUMIFS(RAW_Placement!$F$2:$F$36,RAW_Placement!$B$2:$B$36,">=1",RAW_Placement!$B$2:$B$36,"<=2",RAW_Placement!$C$2:$C$36,"Facebook Stories") | H7: =IFERROR(SUMIFS(RAW_Placement!$D$2:$D$36,RAW_Placement!$B$2:$B$36,">=1",RAW_Placement!$B$2:$B$36,"<=2",RAW_Placement!$C$2:$C$36,"Facebook Stories")/SUMIFS(RAW_Placement!$F$2:$F$36,RAW_Placement!$B$2:$B$36,">=1",RAW_Placement!$B$2:$B$36,"<=2",RAW_Placement!$C$2:$C$36,"Facebook Stories"),"-")
B8: Instream Video | C8: =SUMIFS(RAW_Placement!$D$2:$D$36,RAW_Placement!$B$2:$B$36,">=1",RAW_Placement!$B$2:$B$36,"<=2",RAW_Placement!$C$2:$C$36,"Instream Video") | D8: =IFERROR(SUMIFS(RAW_Placement!$D$2:$D$36,RAW_Placement!$B$2:$B$36,">=1",RAW_Placement!$B$2:$B$36,"<=2",RAW_Placement!$C$2:$C$36,"Instream Video")/SUMIFS(RAW_Placement!$D$2:$D$36,RAW_Placement!$B$2:$B$36,">=1",RAW_Placement!$B$2:$B$36,"<=2")*100,"-") | E8: =SUMIFS(RAW_Placement!$E$2:$E$36,RAW_Placement!$B$2:$B$36,">=1",RAW_Placement!$B$2:$B$36,"<=2",RAW_Placement!$C$2:$C$36,"Instream Video") | F8: =IFERROR(SUMIFS(RAW_Placement!$D$2:$D$36,RAW_Placement!$B$2:$B$36,">=1",RAW_Placement!$B$2:$B$36,"<=2",RAW_Placement!$C$2:$C$36,"Instream Video")/SUMIFS(RAW_Placement!$E$2:$E$36,RAW_Placement!$B$2:$B$36,">=1",RAW_Placement!$B$2:$B$36,"<=2",RAW_Placement!$C$2:$C$36,"Instream Video"),"-") | G8: =SUMIFS(RAW_Placement!$F$2:$F$36,RAW_Placement!$B$2:$B$36,">=1",RAW_Placement!$B$2:$B$36,"<=2",RAW_Placement!$C$2:$C$36,"Instream Video") | H8: =IFERROR(SUMIFS(RAW_Placement!$D$2:$D$36,RAW_Placement!$B$2:$B$36,">=1",RAW_Placement!$B$2:$B$36,"<=2",RAW_Placement!$C$2:$C$36,"Instream Video")/SUMIFS(RAW_Placement!$F$2:$F$36,RAW_Placement!$B$2:$B$36,">=1",RAW_Placement!$B$2:$B$36,"<=2",RAW_Placement!$C$2:$C$36,"Instream Video"),"-")
B9: Instagram Stories | C9: =SUMIFS(RAW_Placement!$D$2:$D$36,RAW_Placement!$B$2:$B$36,">=1",RAW_Placement!$B$2:$B$36,"<=2",RAW_Placement!$C$2:$C$36,"Instagram Stories") | D9: =IFERROR(SUMIFS(RAW_Placement!$D$2:$D$36,RAW_Placement!$B$2:$B$36,">=1",RAW_Placement!$B$2:$B$36,"<=2",RAW_Placement!$C$2:$C$36,"Instagram Stories")/SUMIFS(RAW_Placement!$D$2:$D$36,RAW_Placement!$B$2:$B$36,">=1",RAW_Placement!$B$2:$B$36,"<=2")*100,"-") | E9: =SUMIFS(RAW_Placement!$E$2:$E$36,RAW_Placement!$B$2:$B$36,">=1",RAW_Placement!$B$2:$B$36,"<=2",RAW_Placement!$C$2:$C$36,"Instagram Stories") | F9: =IFERROR(SUMIFS(RAW_Placement!$D$2:$D$36,RAW_Placement!$B$2:$B$36,">=1",RAW_Placement!$B$2:$B$36,"<=2",RAW_Placement!$C$2:$C$36,"Instagram Stories")/SUMIFS(RAW_Placement!$E$2:$E$36,RAW_Placement!$B$2:$B$36,">=1",RAW_Placement!$B$2:$B$36,"<=2",RAW_Placement!$C$2:$C$36,"Instagram Stories"),"-") | G9: =SUMIFS(RAW_Placement!$F$2:$F$36,RAW_Placement!$B$2:$B$36,">=1",RAW_Placement!$B$2:$B$36,"<=2",RAW_Placement!$C$2:$C$36,"Instagram Stories") | H9: =IFERROR(SUMIFS(RAW_Placement!$D$2:$D$36,RAW_Placement!$B$2:$B$36,">=1",RAW_Placement!$B$2:$B$36,"<=2",RAW_Placement!$C$2:$C$36,"Instagram Stories")/SUMIFS(RAW_Placement!$F$2:$F$36,RAW_Placement!$B$2:$B$36,">=1",RAW_Placement!$B$2:$B$36,"<=2",RAW_Placement!$C$2:$C$36,"Instagram Stories"),"-")
A10: After Oct 3-4 | B10: Facebook Reels | C10: =SUMIFS(RAW_Placement!$D$2:$D$36,RAW_Placement!$B$2:$B$36,">=3",RAW_Placement!$B$2:$B$36,"<=4",RAW_Placement!$C$2:$C$36,"Facebook Reels") | D10: =IFERROR(SUMIFS(RAW_Placement!$D$2:$D$36,RAW_Placement!$B$2:$B$36,">=3",RAW_Placement!$B$2:$B$36,"<=4",RAW_Placement!$C$2:$C$36,"Facebook Reels")/SUMIFS(RAW_Placement!$D$2:$D$36,RAW_Placement!$B$2:$B$36,">=3",RAW_Placement!$B$2:$B$36,"<=4")*100,"-") | E10: =SUMIFS(RAW_Placement!$E$2:$E$36,RAW_Placement!$B$2:$B$36,">=3",RAW_Placement!$B$2:$B$36,"<=4",RAW_Placement!$C$2:$C$36,"Facebook Reels") | F10: =IFERROR(SUMIFS(RAW_Placement!$D$2:$D$36,RAW_Placement!$B$2:$B$36,">=3",RAW_Placement!$B$2:$B$36,"<=4",RAW_Placement!$C$2:$C$36,"Facebook Reels")/SUMIFS(RAW_Placement!$E$2:$E$36,RAW_Placement!$B$2:$B$36,">=3",RAW_Placement!$B$2:$B$36,"<=4",RAW_Placement!$C$2:$C$36,"Facebook Reels"),"-") | G10: =SUMIFS(RAW_Placement!$F$2:$F$36,RAW_Placement!$B$2:$B$36,">=3",RAW_Placement!$B$2:$B$36,"<=4",RAW_Placement!$C$2:$C$36,"Facebook Reels") | H10: =IFERROR(SUMIFS(RAW_Placement!$D$2:$D$36,RAW_Placement!$B$2:$B$36,">=3",RAW_Placement!$B$2:$B$36,"<=4",RAW_Placement!$C$2:$C$36,"Facebook Reels")/SUMIFS(RAW_Placement!$F$2:$F$36,RAW_Placement!$B$2:$B$36,">=3",RAW_Placement!$B$2:$B$36,"<=4",RAW_Placement!$C$2:$C$36,"Facebook Reels"),"-") | I10: =IFERROR(F10/F3,"-")
B11: Facebook Feed | C11: =SUMIFS(RAW_Placement!$D$2:$D$36,RAW_Placement!$B$2:$B$36,">=3",RAW_Placement!$B$2:$B$36,"<=4",RAW_Placement!$C$2:$C$36,"Facebook Feed") | D11: =IFERROR(SUMIFS(RAW_Placement!$D$2:$D$36,RAW_Placement!$B$2:$B$36,">=3",RAW_Placement!$B$2:$B$36,"<=4",RAW_Placement!$C$2:$C$36,"Facebook Feed")/SUMIFS(RAW_Placement!$D$2:$D$36,RAW_Placement!$B$2:$B$36,">=3",RAW_Placement!$B$2:$B$36,"<=4")*100,"-") | E11: =SUMIFS(RAW_Placement!$E$2:$E$36,RAW_Placement!$B$2:$B$36,">=3",RAW_Placement!$B$2:$B$36,"<=4",RAW_Placement!$C$2:$C$36,"Facebook Feed") | F11: =IFERROR(SUMIFS(RAW_Placement!$D$2:$D$36,RAW_Placement!$B$2:$B$36,">=3",RAW_Placement!$B$2:$B$36,"<=4",RAW_Placement!$C$2:$C$36,"Facebook Feed")/SUMIFS(RAW_Placement!$E$2:$E$36,RAW_Placement!$B$2:$B$36,">=3",RAW_Placement!$B$2:$B$36,"<=4",RAW_Placement!$C$2:$C$36,"Facebook Feed"),"-") | G11: =SUMIFS(RAW_Placement!$F$2:$F$36,RAW_Placement!$B$2:$B$36,">=3",RAW_Placement!$B$2:$B$36,"<=4",RAW_Placement!$C$2:$C$36,"Facebook Feed") | H11: =IFERROR(SUMIFS(RAW_Placement!$D$2:$D$36,RAW_Placement!$B$2:$B$36,">=3",RAW_Placement!$B$2:$B$36,"<=4",RAW_Placement!$C$2:$C$36,"Facebook Feed")/SUMIFS(RAW_Placement!$F$2:$F$36,RAW_Placement!$B$2:$B$36,">=3",RAW_Placement!$B$2:$B$36,"<=4",RAW_Placement!$C$2:$C$36,"Facebook Feed"),"-") | I11: =IFERROR(F11/F4,"-")
B12: Instagram Reels | C12: =SUMIFS(RAW_Placement!$D$2:$D$36,RAW_Placement!$B$2:$B$36,">=3",RAW_Placement!$B$2:$B$36,"<=4",RAW_Placement!$C$2:$C$36,"Instagram Reels") | D12: =IFERROR(SUMIFS(RAW_Placement!$D$2:$D$36,RAW_Placement!$B$2:$B$36,">=3",RAW_Placement!$B$2:$B$36,"<=4",RAW_Placement!$C$2:$C$36,"Instagram Reels")/SUMIFS(RAW_Placement!$D$2:$D$36,RAW_Placement!$B$2:$B$36,">=3",RAW_Placement!$B$2:$B$36,"<=4")*100,"-") | E12: =SUMIFS(RAW_Placement!$E$2:$E$36,RAW_Placement!$B$2:$B$36,">=3",RAW_Placement!$B$2:$B$36,"<=4",RAW_Placement!$C$2:$C$36,"Instagram Reels") | F12: =IFERROR(SUMIFS(RAW_Placement!$D$2:$D$36,RAW_Placement!$B$2:$B$36,">=3",RAW_Placement!$B$2:$B$36,"<=4",RAW_Placement!$C$2:$C$36,"Instagram Reels")/SUMIFS(RAW_Placement!$E$2:$E$36,RAW_Placement!$B$2:$B$36,">=3",RAW_Placement!$B$2:$B$36,"<=4",RAW_Placement!$C$2:$C$36,"Instagram Reels"),"-") | G12: =SUMIFS(RAW_Placement!$F$2:$F$36,RAW_Placement!$B$2:$B$36,">=3",RAW_Placement!$B$2:$B$36,"<=4",RAW_Placement!$C$2:$C$36,"Instagram Reels") | H12: =IFERROR(SUMIFS(RAW_Placement!$D$2:$D$36,RAW_Placement!$B$2:$B$36,">=3",RAW_Placement!$B$2:$B$36,"<=4",RAW_Placement!$C$2:$C$36,"Instagram Reels")/SUMIFS(RAW_Placement!$F$2:$F$36,RAW_Placement!$B$2:$B$36,">=3",RAW_Placement!$B$2:$B$36,"<=4",RAW_Placement!$C$2:$C$36,"Instagram Reels"),"-") | I12: =IFERROR(F12/F5,"-")
B13: Instagram Feed | C13: =SUMIFS(RAW_Placement!$D$2:$D$36,RAW_Placement!$B$2:$B$36,">=3",RAW_Placement!$B$2:$B$36,"<=4",RAW_Placement!$C$2:$C$36,"Instagram Feed") | D13: =IFERROR(SUMIFS(RAW_Placement!$D$2:$D$36,RAW_Placement!$B$2:$B$36,">=3",RAW_Placement!$B$2:$B$36,"<=4",RAW_Placement!$C$2:$C$36,"Instagram Feed")/SUMIFS(RAW_Placement!$D$2:$D$36,RAW_Placement!$B$2:$B$36,">=3",RAW_Placement!$B$2:$B$36,"<=4")*100,"-") | E13: =SUMIFS(RAW_Placement!$E$2:$E$36,RAW_Placement!$B$2:$B$36,">=3",RAW_Placement!$B$2:$B$36,"<=4",RAW_Placement!$C$2:$C$36,"Instagram Feed") | F13: =IFERROR(SUMIFS(RAW_Placement!$D$2:$D$36,RAW_Placement!$B$2:$B$36,">=3",RAW_Placement!$B$2:$B$36,"<=4",RAW_Placement!$C$2:$C$36,"Instagram Feed")/SUMIFS(RAW_Placement!$E$2:$E$36,RAW_Placement!$B$2:$B$36,">=3",RAW_Placement!$B$2:$B$36,"<=4",RAW_Placement!$C$2:$C$36,"Instagram Feed"),"-") | G13: =SUMIFS(RAW_Placement!$F$2:$F$36,RAW_Placement!$B$2:$B$36,">=3",RAW_Placement!$B$2:$B$36,"<=4",RAW_Placement!$C$2:$C$36,"Instagram Feed") | H13: =IFERROR(SUMIFS(RAW_Placement!$D$2:$D$36,RAW_Placement!$B$2:$B$36,">=3",RAW_Placement!$B$2:$B$36,"<=4",RAW_Placement!$C$2:$C$36,"Instagram Feed")/SUMIFS(RAW_Placement!$F$2:$F$36,RAW_Placement!$B$2:$B$36,">=3",RAW_Placement!$B$2:$B$36,"<=4",RAW_Placement!$C$2:$C$36,"Instagram Feed"),"-") | I13: =IFERROR(F13/F6,"-")
B14: Facebook Stories | C14: =SUMIFS(RAW_Placement!$D$2:$D$36,RAW_Placement!$B$2:$B$36,">=3",RAW_Placement!$B$2:$B$36,"<=4",RAW_Placement!$C$2:$C$36,"Facebook Stories") | D14: =IFERROR(SUMIFS(RAW_Placement!$D$2:$D$36,RAW_Placement!$B$2:$B$36,">=3",RAW_Placement!$B$2:$B$36,"<=4",RAW_Placement!$C$2:$C$36,"Facebook Stories")/SUMIFS(RAW_Placement!$D$2:$D$36,RAW_Placement!$B$2:$B$36,">=3",RAW_Placement!$B$2:$B$36,"<=4")*100,"-") | E14: =SUMIFS(RAW_Placement!$E$2:$E$36,RAW_Placement!$B$2:$B$36,">=3",RAW_Placement!$B$2:$B$36,"<=4",RAW_Placement!$C$2:$C$36,"Facebook Stories") | F14: =IFERROR(SUMIFS(RAW_Placement!$D$2:$D$36,RAW_Placement!$B$2:$B$36,">=3",RAW_Placement!$B$2:$B$36,"<=4",RAW_Placement!$C$2:$C$36,"Facebook Stories")/SUMIFS(RAW_Placement!$E$2:$E$36,RAW_Placement!$B$2:$B$36,">=3",RAW_Placement!$B$2:$B$36,"<=4",RAW_Placement!$C$2:$C$36,"Facebook Stories"),"-") | G14: =SUMIFS(RAW_Placement!$F$2:$F$36,RAW_Placement!$B$2:$B$36,">=3",RAW_Placement!$B$2:$B$36,"<=4",RAW_Placement!$C$2:$C$36,"Facebook Stories") | H14: =IFERROR(SUMIFS(RAW_Placement!$D$2:$D$36,RAW_Placement!$B$2:$B$36,">=3",RAW_Placement!$B$2:$B$36,"<=4",RAW_Placement!$C$2:$C$36,"Facebook Stories")/SUMIFS(RAW_Placement!$F$2:$F$36,RAW_Placement!$B$2:$B$36,">=3",RAW_Placement!$B$2:$B$36,"<=4",RAW_Placement!$C$2:$C$36,"Facebook Stories"),"-") | I14: =IFERROR(F14/F7,"-")
B15: Instream Video | C15: =SUMIFS(RAW_Placement!$D$2:$D$36,RAW_Placement!$B$2:$B$36,">=3",RAW_Placement!$B$2:$B$36,"<=4",RAW_Placement!$C$2:$C$36,"Instream Video") | D15: =IFERROR(SUMIFS(RAW_Placement!$D$2:$D$36,RAW_Placement!$B$2:$B$36,">=3",RAW_Placement!$B$2:$B$36,"<=4",RAW_Placement!$C$2:$C$36,"Instream Video")/SUMIFS(RAW_Placement!$D$2:$D$36,RAW_Placement!$B$2:$B$36,">=3",RAW_Placement!$B$2:$B$36,"<=4")*100,"-") | E15: =SUMIFS(RAW_Placement!$E$2:$E$36,RAW_Placement!$B$2:$B$36,">=3",RAW_Placement!$B$2:$B$36,"<=4",RAW_Placement!$C$2:$C$36,"Instream Video") | F15: =IFERROR(SUMIFS(RAW_Placement!$D$2:$D$36,RAW_Placement!$B$2:$B$36,">=3",RAW_Placement!$B$2:$B$36,"<=4",RAW_Placement!$C$2:$C$36,"Instream Video")/SUMIFS(RAW_Placement!$E$2:$E$36,RAW_Placement!$B$2:$B$36,">=3",RAW_Placement!$B$2:$B$36,"<=4",RAW_Placement!$C$2:$C$36,"Instream Video"),"-") | G15: =SUMIFS(RAW_Placement!$F$2:$F$36,RAW_Placement!$B$2:$B$36,">=3",RAW_Placement!$B$2:$B$36,"<=4",RAW_Placement!$C$2:$C$36,"Instream Video") | H15: =IFERROR(SUMIFS(RAW_Placement!$D$2:$D$36,RAW_Placement!$B$2:$B$36,">=3",RAW_Placement!$B$2:$B$36,"<=4",RAW_Placement!$C$2:$C$36,"Instream Video")/SUMIFS(RAW_Placement!$F$2:$F$36,RAW_Placement!$B$2:$B$36,">=3",RAW_Placement!$B$2:$B$36,"<=4",RAW_Placement!$C$2:$C$36,"Instream Video"),"-") | I15: =IFERROR(F15/F8,"-")
B16: Instagram Stories | C16: =SUMIFS(RAW_Placement!$D$2:$D$36,RAW_Placement!$B$2:$B$36,">=3",RAW_Placement!$B$2:$B$36,"<=4",RAW_Placement!$C$2:$C$36,"Instagram Stories") | D16: =IFERROR(SUMIFS(RAW_Placement!$D$2:$D$36,RAW_Placement!$B$2:$B$36,">=3",RAW_Placement!$B$2:$B$36,"<=4",RAW_Placement!$C$2:$C$36,"Instagram Stories")/SUMIFS(RAW_Placement!$D$2:$D$36,RAW_Placement!$B$2:$B$36,">=3",RAW_Placement!$B$2:$B$36,"<=4")*100,"-") | E16: =SUMIFS(RAW_Placement!$E$2:$E$36,RAW_Placement!$B$2:$B$36,">=3",RAW_Placement!$B$2:$B$36,"<=4",RAW_Placement!$C$2:$C$36,"Instagram Stories") | F16: =IFERROR(SUMIFS(RAW_Placement!$D$2:$D$36,RAW_Placement!$B$2:$B$36,">=3",RAW_Placement!$B$2:$B$36,"<=4",RAW_Placement!$C$2:$C$36,"Instagram Stories")/SUMIFS(RAW_Placement!$E$2:$E$36,RAW_Placement!$B$2:$B$36,">=3",RAW_Placement!$B$2:$B$36,"<=4",RAW_Placement!$C$2:$C$36,"Instagram Stories"),"-") | G16: =SUMIFS(RAW_Placement!$F$2:$F$36,RAW_Placement!$B$2:$B$36,">=3",RAW_Placement!$B$2:$B$36,"<=4",RAW_Placement!$C$2:$C$36,"Instagram Stories") | H16: =IFERROR(SUMIFS(RAW_Placement!$D$2:$D$36,RAW_Placement!$B$2:$B$36,">=3",RAW_Placement!$B$2:$B$36,"<=4",RAW_Placement!$C$2:$C$36,"Instagram Stories")/SUMIFS(RAW_Placement!$F$2:$F$36,RAW_Placement!$B$2:$B$36,">=3",RAW_Placement!$B$2:$B$36,"<=4",RAW_Placement!$C$2:$C$36,"Instagram Stories"),"-") | I16: =IFERROR(F16/F9,"-")

Sheet Device Split
A1: DEVICE SPLIT - effectively single-platform (Android smartphone ~99.9%). Not a factor.
A2: Window | B2: Segment | C2: Spend (Rs) | D2: Spend % | E2: Installs | F2: CPI | G2: Trials | H2: Trial CAC | I2: Inflation
A3: Before Oct 1-2 | B3: Android smartphone | C3: =SUMIFS(RAW_Device!$D$2:$D$11,RAW_Device!$B$2:$B$11,">=1",RAW_Device!$B$2:$B$11,"<=2",RAW_Device!$C$2:$C$11,"Android smartphone") | D3: =IFERROR(SUMIFS(RAW_Device!$D$2:$D$11,RAW_Device!$B$2:$B$11,">=1",RAW_Device!$B$2:$B$11,"<=2",RAW_Device!$C$2:$C$11,"Android smartphone")/SUMIFS(RAW_Device!$D$2:$D$11,RAW_Device!$B$2:$B$11,">=1",RAW_Device!$B$2:$B$11,"<=2")*100,"-") | E3: =SUMIFS(RAW_Device!$E$2:$E$11,RAW_Device!$B$2:$B$11,">=1",RAW_Device!$B$2:$B$11,"<=2",RAW_Device!$C$2:$C$11,"Android smartphone") | F3: =IFERROR(SUMIFS(RAW_Device!$D$2:$D$11,RAW_Device!$B$2:$B$11,">=1",RAW_Device!$B$2:$B$11,"<=2",RAW_Device!$C$2:$C$11,"Android smartphone")/SUMIFS(RAW_Device!$E$2:$E$11,RAW_Device!$B$2:$B$11,">=1",RAW_Device!$B$2:$B$11,"<=2",RAW_Device!$C$2:$C$11,"Android smartphone"),"-") | G3: =SUMIFS(RAW_Device!$F$2:$F$11,RAW_Device!$B$2:$B$11,">=1",RAW_Device!$B$2:$B$11,"<=2",RAW_Device!$C$2:$C$11,"Android smartphone") | H3: =IFERROR(SUMIFS(RAW_Device!$D$2:$D$11,RAW_Device!$B$2:$B$11,">=1",RAW_Device!$B$2:$B$11,"<=2",RAW_Device!$C$2:$C$11,"Android smartphone")/SUMIFS(RAW_Device!$F$2:$F$11,RAW_Device!$B$2:$B$11,">=1",RAW_Device!$B$2:$B$11,"<=2",RAW_Device!$C$2:$C$11,"Android smartphone"),"-")
B4: Android tablet | C4: =SUMIFS(RAW_Device!$D$2:$D$11,RAW_Device!$B$2:$B$11,">=1",RAW_Device!$B$2:$B$11,"<=2",RAW_Device!$C$2:$C$11,"Android tablet") | D4: =IFERROR(SUMIFS(RAW_Device!$D$2:$D$11,RAW_Device!$B$2:$B$11,">=1",RAW_Device!$B$2:$B$11,"<=2",RAW_Device!$C$2:$C$11,"Android tablet")/SUMIFS(RAW_Device!$D$2:$D$11,RAW_Device!$B$2:$B$11,">=1",RAW_Device!$B$2:$B$11,"<=2")*100,"-") | E4: =SUMIFS(RAW_Device!$E$2:$E$11,RAW_Device!$B$2:$B$11,">=1",RAW_Device!$B$2:$B$11,"<=2",RAW_Device!$C$2:$C$11,"Android tablet") | F4: =IFERROR(SUMIFS(RAW_Device!$D$2:$D$11,RAW_Device!$B$2:$B$11,">=1",RAW_Device!$B$2:$B$11,"<=2",RAW_Device!$C$2:$C$11,"Android tablet")/SUMIFS(RAW_Device!$E$2:$E$11,RAW_Device!$B$2:$B$11,">=1",RAW_Device!$B$2:$B$11,"<=2",RAW_Device!$C$2:$C$11,"Android tablet"),"-") | G4: =SUMIFS(RAW_Device!$F$2:$F$11,RAW_Device!$B$2:$B$11,">=1",RAW_Device!$B$2:$B$11,"<=2",RAW_Device!$C$2:$C$11,"Android tablet") | H4: =IFERROR(SUMIFS(RAW_Device!$D$2:$D$11,RAW_Device!$B$2:$B$11,">=1",RAW_Device!$B$2:$B$11,"<=2",RAW_Device!$C$2:$C$11,"Android tablet")/SUMIFS(RAW_Device!$F$2:$F$11,RAW_Device!$B$2:$B$11,">=1",RAW_Device!$B$2:$B$11,"<=2",RAW_Device!$C$2:$C$11,"Android tablet"),"-")
A5: After Oct 3-4 | B5: Android smartphone | C5: =SUMIFS(RAW_Device!$D$2:$D$11,RAW_Device!$B$2:$B$11,">=3",RAW_Device!$B$2:$B$11,"<=4",RAW_Device!$C$2:$C$11,"Android smartphone") | D5: =IFERROR(SUMIFS(RAW_Device!$D$2:$D$11,RAW_Device!$B$2:$B$11,">=3",RAW_Device!$B$2:$B$11,"<=4",RAW_Device!$C$2:$C$11,"Android smartphone")/SUMIFS(RAW_Device!$D$2:$D$11,RAW_Device!$B$2:$B$11,">=3",RAW_Device!$B$2:$B$11,"<=4")*100,"-") | E5: =SUMIFS(RAW_Device!$E$2:$E$11,RAW_Device!$B$2:$B$11,">=3",RAW_Device!$B$2:$B$11,"<=4",RAW_Device!$C$2:$C$11,"Android smartphone") | F5: =IFERROR(SUMIFS(RAW_Device!$D$2:$D$11,RAW_Device!$B$2:$B$11,">=3",RAW_Device!$B$2:$B$11,"<=4",RAW_Device!$C$2:$C$11,"Android smartphone")/SUMIFS(RAW_Device!$E$2:$E$11,RAW_Device!$B$2:$B$11,">=3",RAW_Device!$B$2:$B$11,"<=4",RAW_Device!$C$2:$C$11,"Android smartphone"),"-") | G5: =SUMIFS(RAW_Device!$F$2:$F$11,RAW_Device!$B$2:$B$11,">=3",RAW_Device!$B$2:$B$11,"<=4",RAW_Device!$C$2:$C$11,"Android smartphone") | H5: =IFERROR(SUMIFS(RAW_Device!$D$2:$D$11,RAW_Device!$B$2:$B$11,">=3",RAW_Device!$B$2:$B$11,"<=4",RAW_Device!$C$2:$C$11,"Android smartphone")/SUMIFS(RAW_Device!$F$2:$F$11,RAW_Device!$B$2:$B$11,">=3",RAW_Device!$B$2:$B$11,"<=4",RAW_Device!$C$2:$C$11,"Android smartphone"),"-") | I5: =IFERROR(F5/F3,"-")
B6: Android tablet | C6: =SUMIFS(RAW_Device!$D$2:$D$11,RAW_Device!$B$2:$B$11,">=3",RAW_Device!$B$2:$B$11,"<=4",RAW_Device!$C$2:$C$11,"Android tablet") | D6: =IFERROR(SUMIFS(RAW_Device!$D$2:$D$11,RAW_Device!$B$2:$B$11,">=3",RAW_Device!$B$2:$B$11,"<=4",RAW_Device!$C$2:$C$11,"Android tablet")/SUMIFS(RAW_Device!$D$2:$D$11,RAW_Device!$B$2:$B$11,">=3",RAW_Device!$B$2:$B$11,"<=4")*100,"-") | E6: =SUMIFS(RAW_Device!$E$2:$E$11,RAW_Device!$B$2:$B$11,">=3",RAW_Device!$B$2:$B$11,"<=4",RAW_Device!$C$2:$C$11,"Android tablet") | F6: =IFERROR(SUMIFS(RAW_Device!$D$2:$D$11,RAW_Device!$B$2:$B$11,">=3",RAW_Device!$B$2:$B$11,"<=4",RAW_Device!$C$2:$C$11,"Android tablet")/SUMIFS(RAW_Device!$E$2:$E$11,RAW_Device!$B$2:$B$11,">=3",RAW_Device!$B$2:$B$11,"<=4",RAW_Device!$C$2:$C$11,"Android tablet"),"-") | G6: =SUMIFS(RAW_Device!$F$2:$F$11,RAW_Device!$B$2:$B$11,">=3",RAW_Device!$B$2:$B$11,"<=4",RAW_Device!$C$2:$C$11,"Android tablet") | H6: =IFERROR(SUMIFS(RAW_Device!$D$2:$D$11,RAW_Device!$B$2:$B$11,">=3",RAW_Device!$B$2:$B$11,"<=4",RAW_Device!$C$2:$C$11,"Android tablet")/SUMIFS(RAW_Device!$F$2:$F$11,RAW_Device!$B$2:$B$11,">=3",RAW_Device!$B$2:$B$11,"<=4",RAW_Device!$C$2:$C$11,"Android tablet"),"-") | I6: =IFERROR(F6/F4,"-")

Sheet Campaign Level
A1: CAMPAIGN LEVEL - spend, CPI, Trial CAC per window. Inflation = After CPI / Before CPI.
A2: Window | B2: Segment | C2: Spend (Rs) | D2: Spend % | E2: Installs | F2: CPI | G2: Trials | H2: Trial CAC | I2: Inflation
A3: Before Oct 1-2 | B3: HI_005_MIX_Purchase_ABO | C3: =SUMIFS(RAW_Campaign!$D$2:$D$55,RAW_Campaign!$B$2:$B$55,">=1",RAW_Campaign!$B$2:$B$55,"<=2",RAW_Campaign!$C$2:$C$55,"HI_005_MIX_Purchase_ABO") | D3: =IFERROR(SUMIFS(RAW_Campaign!$D$2:$D$55,RAW_Campaign!$B$2:$B$55,">=1",RAW_Campaign!$B$2:$B$55,"<=2",RAW_Campaign!$C$2:$C$55,"HI_005_MIX_Purchase_ABO")/SUMIFS(RAW_Campaign!$D$2:$D$55,RAW_Campaign!$B$2:$B$55,">=1",RAW_Campaign!$B$2:$B$55,"<=2")*100,"-") | E3: =SUMIFS(RAW_Campaign!$E$2:$E$55,RAW_Campaign!$B$2:$B$55,">=1",RAW_Campaign!$B$2:$B$55,"<=2",RAW_Campaign!$C$2:$C$55,"HI_005_MIX_Purchase_ABO") | F3: =IFERROR(SUMIFS(RAW_Campaign!$D$2:$D$55,RAW_Campaign!$B$2:$B$55,">=1",RAW_Campaign!$B$2:$B$55,"<=2",RAW_Campaign!$C$2:$C$55,"HI_005_MIX_Purchase_ABO")/SUMIFS(RAW_Campaign!$E$2:$E$55,RAW_Campaign!$B$2:$B$55,">=1",RAW_Campaign!$B$2:$B$55,"<=2",RAW_Campaign!$C$2:$C$55,"HI_005_MIX_Purchase_ABO"),"-") | G3: =SUMIFS(RAW_Campaign!$F$2:$F$55,RAW_Campaign!$B$2:$B$55,">=1",RAW_Campaign!$B$2:$B$55,"<=2",RAW_Campaign!$C$2:$C$55,"HI_005_MIX_Purchase_ABO") | H3: =IFERROR(SUMIFS(RAW_Campaign!$D$2:$D$55,RAW_Campaign!$B$2:$B$55,">=1",RAW_Campaign!$B$2:$B$55,"<=2",RAW_Campaign!$C$2:$C$55,"HI_005_MIX_Purchase_ABO")/SUMIFS(RAW_Campaign!$F$2:$F$55,RAW_Campaign!$B$2:$B$55,">=1",RAW_Campaign!$B$2:$B$55,"<=2",RAW_Campaign!$C$2:$C$55,"HI_005_MIX_Purchase_ABO"),"-")
B4: HI_005_MIX_All_India_CBO | C4: =SUMIFS(RAW_Campaign!$D$2:$D$55,RAW_Campaign!$B$2:$B$55,">=1",RAW_Campaign!$B$2:$B$55,"<=2",RAW_Campaign!$C$2:$C$55,"HI_005_MIX_All_India_CBO") | D4: =IFERROR(SUMIFS(RAW_Campaign!$D$2:$D$55,RAW_Campaign!$B$2:$B$55,">=1",RAW_Campaign!$B$2:$B$55,"<=2",RAW_Campaign!$C$2:$C$55,"HI_005_MIX_All_India_CBO")/SUMIFS(RAW_Campaign!$D$2:$D$55,RAW_Campaign!$B$2:$B$55,">=1",RAW_Campaign!$B$2:$B$55,"<=2")*100,"-") | E4: =SUMIFS(RAW_Campaign!$E$2:$E$55,RAW_Campaign!$B$2:$B$55,">=1",RAW_Campaign!$B$2:$B$55,"<=2",RAW_Campaign!$C$2:$C$55,"HI_005_MIX_All_India_CBO") | F4: =IFERROR(SUMIFS(RAW_Campaign!$D$2:$D$55,RAW_Campaign!$B$2:$B$55,">=1",RAW_Campaign!$B$2:$B$55,"<=2",RAW_Campaign!$C$2:$C$55,"HI_005_MIX_All_India_CBO")/SUMIFS(RAW_Campaign!$E$2:$E$55,RAW_Campaign!$B$2:$B$55,">=1",RAW_Campaign!$B$2:$B$55,"<=2",RAW_Campaign!$C$2:$C$55,"HI_005_MIX_All_India_CBO"),"-") | G4: =SUMIFS(RAW_Campaign!$F$2:$F$55,RAW_Campaign!$B$2:$B$55,">=1",RAW_Campaign!$B$2:$B$55,"<=2",RAW_Campaign!$C$2:$C$55,"HI_005_MIX_All_India_CBO") | H4: =IFERROR(SUMIFS(RAW_Campaign!$D$2:$D$55,RAW_Campaign!$B$2:$B$55,">=1",RAW_Campaign!$B$2:$B$55,"<=2",RAW_Campaign!$C$2:$C$55,"HI_005_MIX_All_India_CBO")/SUMIFS(RAW_Campaign!$F$2:$F$55,RAW_Campaign!$B$2:$B$55,">=1",RAW_Campaign!$B$2:$B$55,"<=2",RAW_Campaign!$C$2:$C$55,"HI_005_MIX_All_India_CBO"),"-")
B5: HI_005_Political_Purchase_ABO | C5: =SUMIFS(RAW_Campaign!$D$2:$D$55,RAW_Campaign!$B$2:$B$55,">=1",RAW_Campaign!$B$2:$B$55,"<=2",RAW_Campaign!$C$2:$C$55,"HI_005_Political_Purchase_ABO") | D5: =IFERROR(SUMIFS(RAW_Campaign!$D$2:$D$55,RAW_Campaign!$B$2:$B$55,">=1",RAW_Campaign!$B$2:$B$55,"<=2",RAW_Campaign!$C$2:$C$55,"HI_005_Political_Purchase_ABO")/SUMIFS(RAW_Campaign!$D$2:$D$55,RAW_Campaign!$B$2:$B$55,">=1",RAW_Campaign!$B$2:$B$55,"<=2")*100,"-") | E5: =SUMIFS(RAW_Campaign!$E$2:$E$55,RAW_Campaign!$B$2:$B$55,">=1",RAW_Campaign!$B$2:$B$55,"<=2",RAW_Campaign!$C$2:$C$55,"HI_005_Political_Purchase_ABO") | F5: =IFERROR(SUMIFS(RAW_Campaign!$D$2:$D$55,RAW_Campaign!$B$2:$B$55,">=1",RAW_Campaign!$B$2:$B$55,"<=2",RAW_Campaign!$C$2:$C$55,"HI_005_Political_Purchase_ABO")/SUMIFS(RAW_Campaign!$E$2:$E$55,RAW_Campaign!$B$2:$B$55,">=1",RAW_Campaign!$B$2:$B$55,"<=2",RAW_Campaign!$C$2:$C$55,"HI_005_Political_Purchase_ABO"),"-") | G5: =SUMIFS(RAW_Campaign!$F$2:$F$55,RAW_Campaign!$B$2:$B$55,">=1",RAW_Campaign!$B$2:$B$55,"<=2",RAW_Campaign!$C$2:$C$55,"HI_005_Political_Purchase_ABO") | H5: =IFERROR(SUMIFS(RAW_Campaign!$D$2:$D$55,RAW_Campaign!$B$2:$B$55,">=1",RAW_Campaign!$B$2:$B$55,"<=2",RAW_Campaign!$C$2:$C$55,"HI_005_Political_Purchase_ABO")/SUMIFS(RAW_Campaign!$F$2:$F$55,RAW_Campaign!$B$2:$B$55,">=1",RAW_Campaign!$B$2:$B$55,"<=2",RAW_Campaign!$C$2:$C$55,"HI_005_Political_Purchase_ABO"),"-")
B6: HI_005_EVNT_Purchase_ABO | C6: =SUMIFS(RAW_Campaign!$D$2:$D$55,RAW_Campaign!$B$2:$B$55,">=1",RAW_Campaign!$B$2:$B$55,"<=2",RAW_Campaign!$C$2:$C$55,"HI_005_EVNT_Purchase_ABO") | D6: =IFERROR(SUMIFS(RAW_Campaign!$D$2:$D$55,RAW_Campaign!$B$2:$B$55,">=1",RAW_Campaign!$B$2:$B$55,"<=2",RAW_Campaign!$C$2:$C$55,"HI_005_EVNT_Purchase_ABO")/SUMIFS(RAW_Campaign!$D$2:$D$55,RAW_Campaign!$B$2:$B$55,">=1",RAW_Campaign!$B$2:$B$55,"<=2")*100,"-") | E6: =SUMIFS(RAW_Campaign!$E$2:$E$55,RAW_Campaign!$B$2:$B$55,">=1",RAW_Campaign!$B$2:$B$55,"<=2",RAW_Campaign!$C$2:$C$55,"HI_005_EVNT_Purchase_ABO") | F6: =IFERROR(SUMIFS(RAW_Campaign!$D$2:$D$55,RAW_Campaign!$B$2:$B$55,">=1",RAW_Campaign!$B$2:$B$55,"<=2",RAW_Campaign!$C$2:$C$55,"HI_005_EVNT_Purchase_ABO")/SUMIFS(RAW_Campaign!$E$2:$E$55,RAW_Campaign!$B$2:$B$55,">=1",RAW_Campaign!$B$2:$B$55,"<=2",RAW_Campaign!$C$2:$C$55,"HI_005_EVNT_Purchase_ABO"),"-") | G6: =SUMIFS(RAW_Campaign!$F$2:$F$55,RAW_Campaign!$B$2:$B$55,">=1",RAW_Campaign!$B$2:$B$55,"<=2",RAW_Campaign!$C$2:$C$55,"HI_005_EVNT_Purchase_ABO") | H6: =IFERROR(SUMIFS(RAW_Campaign!$D$2:$D$55,RAW_Campaign!$B$2:$B$55,">=1",RAW_Campaign!$B$2:$B$55,"<=2",RAW_Campaign!$C$2:$C$55,"HI_005_EVNT_Purchase_ABO")/SUMIFS(RAW_Campaign!$F$2:$F$55,RAW_Campaign!$B$2:$B$55,">=1",RAW_Campaign!$B$2:$B$55,"<=2",RAW_Campaign!$C$2:$C$55,"HI_005_EVNT_Purchase_ABO"),"-")
B7: TE_001_MIX_Purchase_ABO | C7: =SUMIFS(RAW_Campaign!$D$2:$D$55,RAW_Campaign!$B$2:$B$55,">=1",RAW_Campaign!$B$2:$B$55,"<=2",RAW_Campaign!$C$2:$C$55,"TE_001_MIX_Purchase_ABO") | D7: =IFERROR(SUMIFS(RAW_Campaign!$D$2:$D$55,RAW_Campaign!$B$2:$B$55,">=1",RAW_Campaign!$B$2:$B$55,"<=2",RAW_Campaign!$C$2:$C$55,"TE_001_MIX_Purchase_ABO")/SUMIFS(RAW_Campaign!$D$2:$D$55,RAW_Campaign!$B$2:$B$55,">=1",RAW_Campaign!$B$2:$B$55,"<=2")*100,"-") | E7: =SUMIFS(RAW_Campaign!$E$2:$E$55,RAW_Campaign!$B$2:$B$55,">=1",RAW_Campaign!$B$2:$B$55,"<=2",RAW_Campaign!$C$2:$C$55,"TE_001_MIX_Purchase_ABO") | F7: =IFERROR(SUMIFS(RAW_Campaign!$D$2:$D$55,RAW_Campaign!$B$2:$B$55,">=1",RAW_Campaign!$B$2:$B$55,"<=2",RAW_Campaign!$C$2:$C$55,"TE_001_MIX_Purchase_ABO")/SUMIFS(RAW_Campaign!$E$2:$E$55,RAW_Campaign!$B$2:$B$55,">=1",RAW_Campaign!$B$2:$B$55,"<=2",RAW_Campaign!$C$2:$C$55,"TE_001_MIX_Purchase_ABO"),"-") | G7: =SUMIFS(RAW_Campaign!$F$2:$F$55,RAW_Campaign!$B$2:$B$55,">=1",RAW_Campaign!$B$2:$B$55,"<=2",RAW_Campaign!$C$2:$C$55,"TE_001_MIX_Purchase_ABO") | H7: =IFERROR(SUMIFS(RAW_Campaign!$D$2:$D$55,RAW_Campaign!$B$2:$B$55,">=1",RAW_Campaign!$B$2:$B$55,"<=2",RAW_Campaign!$C$2:$C$55,"TE_001_MIX_Purchase_ABO")/SUMIFS(RAW_Campaign!$F$2:$F$55,RAW_Campaign!$B$2:$B$55,">=1",RAW_Campaign!$B$2:$B$55,"<=2",RAW_Campaign!$C$2:$C$55,"TE_001_MIX_Purchase_ABO"),"-")
B8: KA_004_MIX_Purchase_ABO | C8: =SUMIFS(RAW_Campaign!$D$2:$D$55,RAW_Campaign!$B$2:$B$55,">=1",RAW_Campaign!$B$2:$B$55,"<=2",RAW_Campaign!$C$2:$C$55,"KA_004_MIX_Purchase_ABO") | D8: =IFERROR(SUMIFS(RAW_Campaign!$D$2:$D$55,RAW_Campaign!$B$2:$B$55,">=1",RAW_Campaign!$B$2:$B$55,"<=2",RAW_Campaign!$C$2:$C$55,"KA_004_MIX_Purchase_ABO")/SUMIFS(RAW_Campaign!$D$2:$D$55,RAW_Campaign!$B$2:$B$55,">=1",RAW_Campaign!$B$2:$B$55,"<=2")*100,"-") | E8: =SUMIFS(RAW_Campaign!$E$2:$E$55,RAW_Campaign!$B$2:$B$55,">=1",RAW_Campaign!$B$2:$B$55,"<=2",RAW_Campaign!$C$2:$C$55,"KA_004_MIX_Purchase_ABO") | F8: =IFERROR(SUMIFS(RAW_Campaign!$D$2:$D$55,RAW_Campaign!$B$2:$B$55,">=1",RAW_Campaign!$B$2:$B$55,"<=2",RAW_Campaign!$C$2:$C$55,"KA_004_MIX_Purchase_ABO")/SUMIFS(RAW_Campaign!$E$2:$E$55,RAW_Campaign!$B$2:$B$55,">=1",RAW_Campaign!$B$2:$B$55,"<=2",RAW_Campaign!$C$2:$C$55,"KA_004_MIX_Purchase_ABO"),"-") | G8: =SUMIFS(RAW_Campaign!$F$2:$F$55,RAW_Campaign!$B$2:$B$55,">=1",RAW_Campaign!$B$2:$B$55,"<=2",RAW_Campaign!$C$2:$C$55,"KA_004_MIX_Purchase_ABO") | H8: =IFERROR(SUMIFS(RAW_Campaign!$D$2:$D$55,RAW_Campaign!$B$2:$B$55,">=1",RAW_Campaign!$B$2:$B$55,"<=2",RAW_Campaign!$C$2:$C$55,"KA_004_MIX_Purchase_ABO")/SUMIFS(RAW_Campaign!$F$2:$F$55,RAW_Campaign!$B$2:$B$55,">=1",RAW_Campaign!$B$2:$B$55,"<=2",RAW_Campaign!$C$2:$C$55,"KA_004_MIX_Purchase_ABO"),"-")
B9: TN_002_MIX_Purchase_ABO | C9: =SUMIFS(RAW_Campaign!$D$2:$D$55,RAW_Campaign!$B$2:$B$55,">=1",RAW_Campaign!$B$2:$B$55,"<=2",RAW_Campaign!$C$2:$C$55,"TN_002_MIX_Purchase_ABO") | D9: =IFERROR(SUMIFS(RAW_Campaign!$D$2:$D$55,RAW_Campaign!$B$2:$B$55,">=1",RAW_Campaign!$B$2:$B$55,"<=2",RAW_Campaign!$C$2:$C$55,"TN_002_MIX_Purchase_ABO")/SUMIFS(RAW_Campaign!$D$2:$D$55,RAW_Campaign!$B$2:$B$55,">=1",RAW_Campaign!$B$2:$B$55,"<=2")*100,"-") | E9: =SUMIFS(RAW_Campaign!$E$2:$E$55,RAW_Campaign!$B$2:$B$55,">=1",RAW_Campaign!$B$2:$B$55,"<=2",RAW_Campaign!$C$2:$C$55,"TN_002_MIX_Purchase_ABO") | F9: =IFERROR(SUMIFS(RAW_Campaign!$D$2:$D$55,RAW_Campaign!$B$2:$B$55,">=1",RAW_Campaign!$B$2:$B$55,"<=2",RAW_Campaign!$C$2:$C$55,"TN_002_MIX_Purchase_ABO")/SUMIFS(RAW_Campaign!$E$2:$E$55,RAW_Campaign!$B$2:$B$55,">=1",RAW_Campaign!$B$2:$B$55,"<=2",RAW_Campaign!$C$2:$C$55,"TN_002_MIX_Purchase_ABO"),"-") | G9: =SUMIFS(RAW_Campaign!$F$2:$F$55,RAW_Campaign!$B$2:$B$55,">=1",RAW_Campaign!$B$2:$B$55,"<=2",RAW_Campaign!$C$2:$C$55,"TN_002_MIX_Purchase_ABO") | H9: =IFERROR(SUMIFS(RAW_Campaign!$D$2:$D$55,RAW_Campaign!$B$2:$B$55,">=1",RAW_Campaign!$B$2:$B$55,"<=2",RAW_Campaign!$C$2:$C$55,"TN_002_MIX_Purchase_ABO")/SUMIFS(RAW_Campaign!$F$2:$F$55,RAW_Campaign!$B$2:$B$55,">=1",RAW_Campaign!$B$2:$B$55,"<=2",RAW_Campaign!$C$2:$C$55,"TN_002_MIX_Purchase_ABO"),"-")
B10: TN_002_MIX_Purchase_CBO | C10: =SUMIFS(RAW_Campaign!$D$2:$D$55,RAW_Campaign!$B$2:$B$55,">=1",RAW_Campaign!$B$2:$B$55,"<=2",RAW_Campaign!$C$2:$C$55,"TN_002_MIX_Purchase_CBO") | D10: =IFERROR(SUMIFS(RAW_Campaign!$D$2:$D$55,RAW_Campaign!$B$2:$B$55,">=1",RAW_Campaign!$B$2:$B$55,"<=2",RAW_Campaign!$C$2:$C$55,"TN_002_MIX_Purchase_CBO")/SUMIFS(RAW_Campaign!$D$2:$D$55,RAW_Campaign!$B$2:$B$55,">=1",RAW_Campaign!$B$2:$B$55,"<=2")*100,"-") | E10: =SUMIFS(RAW_Campaign!$E$2:$E$55,RAW_Campaign!$B$2:$B$55,">=1",RAW_Campaign!$B$2:$B$55,"<=2",RAW_Campaign!$C$2:$C$55,"TN_002_MIX_Purchase_CBO") | F10: =IFERROR(SUMIFS(RAW_Campaign!$D$2:$D$55,RAW_Campaign!$B$2:$B$55,">=1",RAW_Campaign!$B$2:$B$55,"<=2",RAW_Campaign!$C$2:$C$55,"TN_002_MIX_Purchase_CBO")/SUMIFS(RAW_Campaign!$E$2:$E$55,RAW_Campaign!$B$2:$B$55,">=1",RAW_Campaign!$B$2:$B$55,"<=2",RAW_Campaign!$C$2:$C$55,"TN_002_MIX_Purchase_CBO"),"-") | G10: =SUMIFS(RAW_Campaign!$F$2:$F$55,RAW_Campaign!$B$2:$B$55,">=1",RAW_Campaign!$B$2:$B$55,"<=2",RAW_Campaign!$C$2:$C$55,"TN_002_MIX_Purchase_CBO") | H10: =IFERROR(SUMIFS(RAW_Campaign!$D$2:$D$55,RAW_Campaign!$B$2:$B$55,">=1",RAW_Campaign!$B$2:$B$55,"<=2",RAW_Campaign!$C$2:$C$55,"TN_002_MIX_Purchase_CBO")/SUMIFS(RAW_Campaign!$F$2:$F$55,RAW_Campaign!$B$2:$B$55,">=1",RAW_Campaign!$B$2:$B$55,"<=2",RAW_Campaign!$C$2:$C$55,"TN_002_MIX_Purchase_CBO"),"-")
B11: MH_003_MIX_Purchase_ABO | C11: =SUMIFS(RAW_Campaign!$D$2:$D$55,RAW_Campaign!$B$2:$B$55,">=1",RAW_Campaign!$B$2:$B$55,"<=2",RAW_Campaign!$C$2:$C$55,"MH_003_MIX_Purchase_ABO") | D11: =IFERROR(SUMIFS(RAW_Campaign!$D$2:$D$55,RAW_Campaign!$B$2:$B$55,">=1",RAW_Campaign!$B$2:$B$55,"<=2",RAW_Campaign!$C$2:$C$55,"MH_003_MIX_Purchase_ABO")/SUMIFS(RAW_Campaign!$D$2:$D$55,RAW_Campaign!$B$2:$B$55,">=1",RAW_Campaign!$B$2:$B$55,"<=2")*100,"-") | E11: =SUMIFS(RAW_Campaign!$E$2:$E$55,RAW_Campaign!$B$2:$B$55,">=1",RAW_Campaign!$B$2:$B$55,"<=2",RAW_Campaign!$C$2:$C$55,"MH_003_MIX_Purchase_ABO") | F11: =IFERROR(SUMIFS(RAW_Campaign!$D$2:$D$55,RAW_Campaign!$B$2:$B$55,">=1",RAW_Campaign!$B$2:$B$55,"<=2",RAW_Campaign!$C$2:$C$55,"MH_003_MIX_Purchase_ABO")/SUMIFS(RAW_Campaign!$E$2:$E$55,RAW_Campaign!$B$2:$B$55,">=1",RAW_Campaign!$B$2:$B$55,"<=2",RAW_Campaign!$C$2:$C$55,"MH_003_MIX_Purchase_ABO"),"-") | G11: =SUMIFS(RAW_Campaign!$F$2:$F$55,RAW_Campaign!$B$2:$B$55,">=1",RAW_Campaign!$B$2:$B$55,"<=2",RAW_Campaign!$C$2:$C$55,"MH_003_MIX_Purchase_ABO") | H11: =IFERROR(SUMIFS(RAW_Campaign!$D$2:$D$55,RAW_Campaign!$B$2:$B$55,">=1",RAW_Campaign!$B$2:$B$55,"<=2",RAW_Campaign!$C$2:$C$55,"MH_003_MIX_Purchase_ABO")/SUMIFS(RAW_Campaign!$F$2:$F$55,RAW_Campaign!$B$2:$B$55,">=1",RAW_Campaign!$B$2:$B$55,"<=2",RAW_Campaign!$C$2:$C$55,"MH_003_MIX_Purchase_ABO"),"-")
B12: KA_004_Political_Purchase_ABO | C12: =SUMIFS(RAW_Campaign!$D$2:$D$55,RAW_Campaign!$B$2:$B$55,">=1",RAW_Campaign!$B$2:$B$55,"<=2",RAW_Campaign!$C$2:$C$55,"KA_004_Political_Purchase_ABO") | D12: =IFERROR(SUMIFS(RAW_Campaign!$D$2:$D$55,RAW_Campaign!$B$2:$B$55,">=1",RAW_Campaign!$B$2:$B$55,"<=2",RAW_Campaign!$C$2:$C$55,"KA_004_Political_Purchase_ABO")/SUMIFS(RAW_Campaign!$D$2:$D$55,RAW_Campaign!$B$2:$B$55,">=1",RAW_Campaign!$B$2:$B$55,"<=2")*100,"-") | E12: =SUMIFS(RAW_Campaign!$E$2:$E$55,RAW_Campaign!$B$2:$B$55,">=1",RAW_Campaign!$B$2:$B$55,"<=2",RAW_Campaign!$C$2:$C$55,"KA_004_Political_Purchase_ABO") | F12: =IFERROR(SUMIFS(RAW_Campaign!$D$2:$D$55,RAW_Campaign!$B$2:$B$55,">=1",RAW_Campaign!$B$2:$B$55,"<=2",RAW_Campaign!$C$2:$C$55,"KA_004_Political_Purchase_ABO")/SUMIFS(RAW_Campaign!$E$2:$E$55,RAW_Campaign!$B$2:$B$55,">=1",RAW_Campaign!$B$2:$B$55,"<=2",RAW_Campaign!$C$2:$C$55,"KA_004_Political_Purchase_ABO"),"-") | G12: =SUMIFS(RAW_Campaign!$F$2:$F$55,RAW_Campaign!$B$2:$B$55,">=1",RAW_Campaign!$B$2:$B$55,"<=2",RAW_Campaign!$C$2:$C$55,"KA_004_Political_Purchase_ABO") | H12: =IFERROR(SUMIFS(RAW_Campaign!$D$2:$D$55,RAW_Campaign!$B$2:$B$55,">=1",RAW_Campaign!$B$2:$B$55,"<=2",RAW_Campaign!$C$2:$C$55,"KA_004_Political_Purchase_ABO")/SUMIFS(RAW_Campaign!$F$2:$F$55,RAW_Campaign!$B$2:$B$55,">=1",RAW_Campaign!$B$2:$B$55,"<=2",RAW_Campaign!$C$2:$C$55,"KA_004_Political_Purchase_ABO"),"-")
B13: TN_002_EVNT_Purchase_ABO | C13: =SUMIFS(RAW_Campaign!$D$2:$D$55,RAW_Campaign!$B$2:$B$55,">=1",RAW_Campaign!$B$2:$B$55,"<=2",RAW_Campaign!$C$2:$C$55,"TN_002_EVNT_Purchase_ABO") | D13: =IFERROR(SUMIFS(RAW_Campaign!$D$2:$D$55,RAW_Campaign!$B$2:$B$55,">=1",RAW_Campaign!$B$2:$B$55,"<=2",RAW_Campaign!$C$2:$C$55,"TN_002_EVNT_Purchase_ABO")/SUMIFS(RAW_Campaign!$D$2:$D$55,RAW_Campaign!$B$2:$B$55,">=1",RAW_Campaign!$B$2:$B$55,"<=2")*100,"-") | E13: =SUMIFS(RAW_Campaign!$E$2:$E$55,RAW_Campaign!$B$2:$B$55,">=1",RAW_Campaign!$B$2:$B$55,"<=2",RAW_Campaign!$C$2:$C$55,"TN_002_EVNT_Purchase_ABO") | F13: =IFERROR(SUMIFS(RAW_Campaign!$D$2:$D$55,RAW_Campaign!$B$2:$B$55,">=1",RAW_Campaign!$B$2:$B$55,"<=2",RAW_Campaign!$C$2:$C$55,"TN_002_EVNT_Purchase_ABO")/SUMIFS(RAW_Campaign!$E$2:$E$55,RAW_Campaign!$B$2:$B$55,">=1",RAW_Campaign!$B$2:$B$55,"<=2",RAW_Campaign!$C$2:$C$55,"TN_002_EVNT_Purchase_ABO"),"-") | G13: =SUMIFS(RAW_Campaign!$F$2:$F$55,RAW_Campaign!$B$2:$B$55,">=1",RAW_Campaign!$B$2:$B$55,"<=2",RAW_Campaign!$C$2:$C$55,"TN_002_EVNT_Purchase_ABO") | H13: =IFERROR(SUMIFS(RAW_Campaign!$D$2:$D$55,RAW_Campaign!$B$2:$B$55,">=1",RAW_Campaign!$B$2:$B$55,"<=2",RAW_Campaign!$C$2:$C$55,"TN_002_EVNT_Purchase_ABO")/SUMIFS(RAW_Campaign!$F$2:$F$55,RAW_Campaign!$B$2:$B$55,">=1",RAW_Campaign!$B$2:$B$55,"<=2",RAW_Campaign!$C$2:$C$55,"TN_002_EVNT_Purchase_ABO"),"-")
A14: After Oct 3-4 | B14: HI_005_MIX_Purchase_ABO | C14: =SUMIFS(RAW_Campaign!$D$2:$D$55,RAW_Campaign!$B$2:$B$55,">=3",RAW_Campaign!$B$2:$B$55,"<=4",RAW_Campaign!$C$2:$C$55,"HI_005_MIX_Purchase_ABO") | D14: =IFERROR(SUMIFS(RAW_Campaign!$D$2:$D$55,RAW_Campaign!$B$2:$B$55,">=3",RAW_Campaign!$B$2:$B$55,"<=4",RAW_Campaign!$C$2:$C$55,"HI_005_MIX_Purchase_ABO")/SUMIFS(RAW_Campaign!$D$2:$D$55,RAW_Campaign!$B$2:$B$55,">=3",RAW_Campaign!$B$2:$B$55,"<=4")*100,"-") | E14: =SUMIFS(RAW_Campaign!$E$2:$E$55,RAW_Campaign!$B$2:$B$55,">=3",RAW_Campaign!$B$2:$B$55,"<=4",RAW_Campaign!$C$2:$C$55,"HI_005_MIX_Purchase_ABO") | F14: =IFERROR(SUMIFS(RAW_Campaign!$D$2:$D$55,RAW_Campaign!$B$2:$B$55,">=3",RAW_Campaign!$B$2:$B$55,"<=4",RAW_Campaign!$C$2:$C$55,"HI_005_MIX_Purchase_ABO")/SUMIFS(RAW_Campaign!$E$2:$E$55,RAW_Campaign!$B$2:$B$55,">=3",RAW_Campaign!$B$2:$B$55,"<=4",RAW_Campaign!$C$2:$C$55,"HI_005_MIX_Purchase_ABO"),"-") | G14: =SUMIFS(RAW_Campaign!$F$2:$F$55,RAW_Campaign!$B$2:$B$55,">=3",RAW_Campaign!$B$2:$B$55,"<=4",RAW_Campaign!$C$2:$C$55,"HI_005_MIX_Purchase_ABO") | H14: =IFERROR(SUMIFS(RAW_Campaign!$D$2:$D$55,RAW_Campaign!$B$2:$B$55,">=3",RAW_Campaign!$B$2:$B$55,"<=4",RAW_Campaign!$C$2:$C$55,"HI_005_MIX_Purchase_ABO")/SUMIFS(RAW_Campaign!$F$2:$F$55,RAW_Campaign!$B$2:$B$55,">=3",RAW_Campaign!$B$2:$B$55,"<=4",RAW_Campaign!$C$2:$C$55,"HI_005_MIX_Purchase_ABO"),"-") | I14: =IFERROR(F14/F3,"-")
B15: HI_005_MIX_All_India_CBO | C15: =SUMIFS(RAW_Campaign!$D$2:$D$55,RAW_Campaign!$B$2:$B$55,">=3",RAW_Campaign!$B$2:$B$55,"<=4",RAW_Campaign!$C$2:$C$55,"HI_005_MIX_All_India_CBO") | D15: =IFERROR(SUMIFS(RAW_Campaign!$D$2:$D$55,RAW_Campaign!$B$2:$B$55,">=3",RAW_Campaign!$B$2:$B$55,"<=4",RAW_Campaign!$C$2:$C$55,"HI_005_MIX_All_India_CBO")/SUMIFS(RAW_Campaign!$D$2:$D$55,RAW_Campaign!$B$2:$B$55,">=3",RAW_Campaign!$B$2:$B$55,"<=4")*100,"-") | E15: =SUMIFS(RAW_Campaign!$E$2:$E$55,RAW_Campaign!$B$2:$B$55,">=3",RAW_Campaign!$B$2:$B$55,"<=4",RAW_Campaign!$C$2:$C$55,"HI_005_MIX_All_India_CBO") | F15: =IFERROR(SUMIFS(RAW_Campaign!$D$2:$D$55,RAW_Campaign!$B$2:$B$55,">=3",RAW_Campaign!$B$2:$B$55,"<=4",RAW_Campaign!$C$2:$C$55,"HI_005_MIX_All_India_CBO")/SUMIFS(RAW_Campaign!$E$2:$E$55,RAW_Campaign!$B$2:$B$55,">=3",RAW_Campaign!$B$2:$B$55,"<=4",RAW_Campaign!$C$2:$C$55,"HI_005_MIX_All_India_CBO"),"-") | G15: =SUMIFS(RAW_Campaign!$F$2:$F$55,RAW_Campaign!$B$2:$B$55,">=3",RAW_Campaign!$B$2:$B$55,"<=4",RAW_Campaign!$C$2:$C$55,"HI_005_MIX_All_India_CBO") | H15: =IFERROR(SUMIFS(RAW_Campaign!$D$2:$D$55,RAW_Campaign!$B$2:$B$55,">=3",RAW_Campaign!$B$2:$B$55,"<=4",RAW_Campaign!$C$2:$C$55,"HI_005_MIX_All_India_CBO")/SUMIFS(RAW_Campaign!$F$2:$F$55,RAW_Campaign!$B$2:$B$55,">=3",RAW_Campaign!$B$2:$B$55,"<=4",RAW_Campaign!$C$2:$C$55,"HI_005_MIX_All_India_CBO"),"-") | I15: =IFERROR(F15/F4,"-")
B16: HI_005_Political_Purchase_ABO | C16: =SUMIFS(RAW_Campaign!$D$2:$D$55,RAW_Campaign!$B$2:$B$55,">=3",RAW_Campaign!$B$2:$B$55,"<=4",RAW_Campaign!$C$2:$C$55,"HI_005_Political_Purchase_ABO") | D16: =IFERROR(SUMIFS(RAW_Campaign!$D$2:$D$55,RAW_Campaign!$B$2:$B$55,">=3",RAW_Campaign!$B$2:$B$55,"<=4",RAW_Campaign!$C$2:$C$55,"HI_005_Political_Purchase_ABO")/SUMIFS(RAW_Campaign!$D$2:$D$55,RAW_Campaign!$B$2:$B$55,">=3",RAW_Campaign!$B$2:$B$55,"<=4")*100,"-") | E16: =SUMIFS(RAW_Campaign!$E$2:$E$55,RAW_Campaign!$B$2:$B$55,">=3",RAW_Campaign!$B$2:$B$55,"<=4",RAW_Campaign!$C$2:$C$55,"HI_005_Political_Purchase_ABO") | F16: =IFERROR(SUMIFS(RAW_Campaign!$D$2:$D$55,RAW_Campaign!$B$2:$B$55,">=3",RAW_Campaign!$B$2:$B$55,"<=4",RAW_Campaign!$C$2:$C$55,"HI_005_Political_Purchase_ABO")/SUMIFS(RAW_Campaign!$E$2:$E$55,RAW_Campaign!$B$2:$B$55,">=3",RAW_Campaign!$B$2:$B$55,"<=4",RAW_Campaign!$C$2:$C$55,"HI_005_Political_Purchase_ABO"),"-") | G16: =SUMIFS(RAW_Campaign!$F$2:$F$55,RAW_Campaign!$B$2:$B$55,">=3",RAW_Campaign!$B$2:$B$55,"<=4",RAW_Campaign!$C$2:$C$55,"HI_005_Political_Purchase_ABO") | H16: =IFERROR(SUMIFS(RAW_Campaign!$D$2:$D$55,RAW_Campaign!$B$2:$B$55,">=3",RAW_Campaign!$B$2:$B$55,"<=4",RAW_Campaign!$C$2:$C$55,"HI_005_Political_Purchase_ABO")/SUMIFS(RAW_Campaign!$F$2:$F$55,RAW_Campaign!$B$2:$B$55,">=3",RAW_Campaign!$B$2:$B$55,"<=4",RAW_Campaign!$C$2:$C$55,"HI_005_Political_Purchase_ABO"),"-") | I16: =IFERROR(F16/F5,"-")
B17: HI_005_EVNT_Purchase_ABO | C17: =SUMIFS(RAW_Campaign!$D$2:$D$55,RAW_Campaign!$B$2:$B$55,">=3",RAW_Campaign!$B$2:$B$55,"<=4",RAW_Campaign!$C$2:$C$55,"HI_005_EVNT_Purchase_ABO") | D17: =IFERROR(SUMIFS(RAW_Campaign!$D$2:$D$55,RAW_Campaign!$B$2:$B$55,">=3",RAW_Campaign!$B$2:$B$55,"<=4",RAW_Campaign!$C$2:$C$55,"HI_005_EVNT_Purchase_ABO")/SUMIFS(RAW_Campaign!$D$2:$D$55,RAW_Campaign!$B$2:$B$55,">=3",RAW_Campaign!$B$2:$B$55,"<=4")*100,"-") | E17: =SUMIFS(RAW_Campaign!$E$2:$E$55,RAW_Campaign!$B$2:$B$55,">=3",RAW_Campaign!$B$2:$B$55,"<=4",RAW_Campaign!$C$2:$C$55,"HI_005_EVNT_Purchase_ABO") | F17: =IFERROR(SUMIFS(RAW_Campaign!$D$2:$D$55,RAW_Campaign!$B$2:$B$55,">=3",RAW_Campaign!$B$2:$B$55,"<=4",RAW_Campaign!$C$2:$C$55,"HI_005_EVNT_Purchase_ABO")/SUMIFS(RAW_Campaign!$E$2:$E$55,RAW_Campaign!$B$2:$B$55,">=3",RAW_Campaign!$B$2:$B$55,"<=4",RAW_Campaign!$C$2:$C$55,"HI_005_EVNT_Purchase_ABO"),"-") | G17: =SUMIFS(RAW_Campaign!$F$2:$F$55,RAW_Campaign!$B$2:$B$55,">=3",RAW_Campaign!$B$2:$B$55,"<=4",RAW_Campaign!$C$2:$C$55,"HI_005_EVNT_Purchase_ABO") | H17: =IFERROR(SUMIFS(RAW_Campaign!$D$2:$D$55,RAW_Campaign!$B$2:$B$55,">=3",RAW_Campaign!$B$2:$B$55,"<=4",RAW_Campaign!$C$2:$C$55,"HI_005_EVNT_Purchase_ABO")/SUMIFS(RAW_Campaign!$F$2:$F$55,RAW_Campaign!$B$2:$B$55,">=3",RAW_Campaign!$B$2:$B$55,"<=4",RAW_Campaign!$C$2:$C$55,"HI_005_EVNT_Purchase_ABO"),"-") | I17: =IFERROR(F17/F6,"-")
B18: TE_001_MIX_Purchase_ABO | C18: =SUMIFS(RAW_Campaign!$D$2:$D$55,RAW_Campaign!$B$2:$B$55,">=3",RAW_Campaign!$B$2:$B$55,"<=4",RAW_Campaign!$C$2:$C$55,"TE_001_MIX_Purchase_ABO") | D18: =IFERROR(SUMIFS(RAW_Campaign!$D$2:$D$55,RAW_Campaign!$B$2:$B$55,">=3",RAW_Campaign!$B$2:$B$55,"<=4",RAW_Campaign!$C$2:$C$55,"TE_001_MIX_Purchase_ABO")/SUMIFS(RAW_Campaign!$D$2:$D$55,RAW_Campaign!$B$2:$B$55,">=3",RAW_Campaign!$B$2:$B$55,"<=4")*100,"-") | E18: =SUMIFS(RAW_Campaign!$E$2:$E$55,RAW_Campaign!$B$2:$B$55,">=3",RAW_Campaign!$B$2:$B$55,"<=4",RAW_Campaign!$C$2:$C$55,"TE_001_MIX_Purchase_ABO") | F18: =IFERROR(SUMIFS(RAW_Campaign!$D$2:$D$55,RAW_Campaign!$B$2:$B$55,">=3",RAW_Campaign!$B$2:$B$55,"<=4",RAW_Campaign!$C$2:$C$55,"TE_001_MIX_Purchase_ABO")/SUMIFS(RAW_Campaign!$E$2:$E$55,RAW_Campaign!$B$2:$B$55,">=3",RAW_Campaign!$B$2:$B$55,"<=4",RAW_Campaign!$C$2:$C$55,"TE_001_MIX_Purchase_ABO"),"-") | G18: =SUMIFS(RAW_Campaign!$F$2:$F$55,RAW_Campaign!$B$2:$B$55,">=3",RAW_Campaign!$B$2:$B$55,"<=4",RAW_Campaign!$C$2:$C$55,"TE_001_MIX_Purchase_ABO") | H18: =IFERROR(SUMIFS(RAW_Campaign!$D$2:$D$55,RAW_Campaign!$B$2:$B$55,">=3",RAW_Campaign!$B$2:$B$55,"<=4",RAW_Campaign!$C$2:$C$55,"TE_001_MIX_Purchase_ABO")/SUMIFS(RAW_Campaign!$F$2:$F$55,RAW_Campaign!$B$2:$B$55,">=3",RAW_Campaign!$B$2:$B$55,"<=4",RAW_Campaign!$C$2:$C$55,"TE_001_MIX_Purchase_ABO"),"-") | I18: =IFERROR(F18/F7,"-")
B19: KA_004_MIX_Purchase_ABO | C19: =SUMIFS(RAW_Campaign!$D$2:$D$55,RAW_Campaign!$B$2:$B$55,">=3",RAW_Campaign!$B$2:$B$55,"<=4",RAW_Campaign!$C$2:$C$55,"KA_004_MIX_Purchase_ABO") | D19: =IFERROR(SUMIFS(RAW_Campaign!$D$2:$D$55,RAW_Campaign!$B$2:$B$55,">=3",RAW_Campaign!$B$2:$B$55,"<=4",RAW_Campaign!$C$2:$C$55,"KA_004_MIX_Purchase_ABO")/SUMIFS(RAW_Campaign!$D$2:$D$55,RAW_Campaign!$B$2:$B$55,">=3",RAW_Campaign!$B$2:$B$55,"<=4")*100,"-") | E19: =SUMIFS(RAW_Campaign!$E$2:$E$55,RAW_Campaign!$B$2:$B$55,">=3",RAW_Campaign!$B$2:$B$55,"<=4",RAW_Campaign!$C$2:$C$55,"KA_004_MIX_Purchase_ABO") | F19: =IFERROR(SUMIFS(RAW_Campaign!$D$2:$D$55,RAW_Campaign!$B$2:$B$55,">=3",RAW_Campaign!$B$2:$B$55,"<=4",RAW_Campaign!$C$2:$C$55,"KA_004_MIX_Purchase_ABO")/SUMIFS(RAW_Campaign!$E$2:$E$55,RAW_Campaign!$B$2:$B$55,">=3",RAW_Campaign!$B$2:$B$55,"<=4",RAW_Campaign!$C$2:$C$55,"KA_004_MIX_Purchase_ABO"),"-") | G19: =SUMIFS(RAW_Campaign!$F$2:$F$55,RAW_Campaign!$B$2:$B$55,">=3",RAW_Campaign!$B$2:$B$55,"<=4",RAW_Campaign!$C$2:$C$55,"KA_004_MIX_Purchase_ABO") | H19: =IFERROR(SUMIFS(RAW_Campaign!$D$2:$D$55,RAW_Campaign!$B$2:$B$55,">=3",RAW_Campaign!$B$2:$B$55,"<=4",RAW_Campaign!$C$2:$C$55,"KA_004_MIX_Purchase_ABO")/SUMIFS(RAW_Campaign!$F$2:$F$55,RAW_Campaign!$B$2:$B$55,">=3",RAW_Campaign!$B$2:$B$55,"<=4",RAW_Campaign!$C$2:$C$55,"KA_004_MIX_Purchase_ABO"),"-") | I19: =IFERROR(F19/F8,"-")
B20: TN_002_MIX_Purchase_ABO | C20: =SUMIFS(RAW_Campaign!$D$2:$D$55,RAW_Campaign!$B$2:$B$55,">=3",RAW_Campaign!$B$2:$B$55,"<=4",RAW_Campaign!$C$2:$C$55,"TN_002_MIX_Purchase_ABO") | D20: =IFERROR(SUMIFS(RAW_Campaign!$D$2:$D$55,RAW_Campaign!$B$2:$B$55,">=3",RAW_Campaign!$B$2:$B$55,"<=4",RAW_Campaign!$C$2:$C$55,"TN_002_MIX_Purchase_ABO")/SUMIFS(RAW_Campaign!$D$2:$D$55,RAW_Campaign!$B$2:$B$55,">=3",RAW_Campaign!$B$2:$B$55,"<=4")*100,"-") | E20: =SUMIFS(RAW_Campaign!$E$2:$E$55,RAW_Campaign!$B$2:$B$55,">=3",RAW_Campaign!$B$2:$B$55,"<=4",RAW_Campaign!$C$2:$C$55,"TN_002_MIX_Purchase_ABO") | F20: =IFERROR(SUMIFS(RAW_Campaign!$D$2:$D$55,RAW_Campaign!$B$2:$B$55,">=3",RAW_Campaign!$B$2:$B$55,"<=4",RAW_Campaign!$C$2:$C$55,"TN_002_MIX_Purchase_ABO")/SUMIFS(RAW_Campaign!$E$2:$E$55,RAW_Campaign!$B$2:$B$55,">=3",RAW_Campaign!$B$2:$B$55,"<=4",RAW_Campaign!$C$2:$C$55,"TN_002_MIX_Purchase_ABO"),"-") | G20: =SUMIFS(RAW_Campaign!$F$2:$F$55,RAW_Campaign!$B$2:$B$55,">=3",RAW_Campaign!$B$2:$B$55,"<=4",RAW_Campaign!$C$2:$C$55,"TN_002_MIX_Purchase_ABO") | H20: =IFERROR(SUMIFS(RAW_Campaign!$D$2:$D$55,RAW_Campaign!$B$2:$B$55,">=3",RAW_Campaign!$B$2:$B$55,"<=4",RAW_Campaign!$C$2:$C$55,"TN_002_MIX_Purchase_ABO")/SUMIFS(RAW_Campaign!$F$2:$F$55,RAW_Campaign!$B$2:$B$55,">=3",RAW_Campaign!$B$2:$B$55,"<=4",RAW_Campaign!$C$2:$C$55,"TN_002_MIX_Purchase_ABO"),"-") | I20: =IFERROR(F20/F9,"-")
B21: TN_002_MIX_Purchase_CBO | C21: =SUMIFS(RAW_Campaign!$D$2:$D$55,RAW_Campaign!$B$2:$B$55,">=3",RAW_Campaign!$B$2:$B$55,"<=4",RAW_Campaign!$C$2:$C$55,"TN_002_MIX_Purchase_CBO") | D21: =IFERROR(SUMIFS(RAW_Campaign!$D$2:$D$55,RAW_Campaign!$B$2:$B$55,">=3",RAW_Campaign!$B$2:$B$55,"<=4",RAW_Campaign!$C$2:$C$55,"TN_002_MIX_Purchase_CBO")/SUMIFS(RAW_Campaign!$D$2:$D$55,RAW_Campaign!$B$2:$B$55,">=3",RAW_Campaign!$B$2:$B$55,"<=4")*100,"-") | E21: =SUMIFS(RAW_Campaign!$E$2:$E$55,RAW_Campaign!$B$2:$B$55,">=3",RAW_Campaign!$B$2:$B$55,"<=4",RAW_Campaign!$C$2:$C$55,"TN_002_MIX_Purchase_CBO") | F21: =IFERROR(SUMIFS(RAW_Campaign!$D$2:$D$55,RAW_Campaign!$B$2:$B$55,">=3",RAW_Campaign!$B$2:$B$55,"<=4",RAW_Campaign!$C$2:$C$55,"TN_002_MIX_Purchase_CBO")/SUMIFS(RAW_Campaign!$E$2:$E$55,RAW_Campaign!$B$2:$B$55,">=3",RAW_Campaign!$B$2:$B$55,"<=4",RAW_Campaign!$C$2:$C$55,"TN_002_MIX_Purchase_CBO"),"-") | G21: =SUMIFS(RAW_Campaign!$F$2:$F$55,RAW_Campaign!$B$2:$B$55,">=3",RAW_Campaign!$B$2:$B$55,"<=4",RAW_Campaign!$C$2:$C$55,"TN_002_MIX_Purchase_CBO") | H21: =IFERROR(SUMIFS(RAW_Campaign!$D$2:$D$55,RAW_Campaign!$B$2:$B$55,">=3",RAW_Campaign!$B$2:$B$55,"<=4",RAW_Campaign!$C$2:$C$55,"TN_002_MIX_Purchase_CBO")/SUMIFS(RAW_Campaign!$F$2:$F$55,RAW_Campaign!$B$2:$B$55,">=3",RAW_Campaign!$B$2:$B$55,"<=4",RAW_Campaign!$C$2:$C$55,"TN_002_MIX_Purchase_CBO"),"-") | I21: =IFERROR(F21/F10,"-")
B22: MH_003_MIX_Purchase_ABO | C22: =SUMIFS(RAW_Campaign!$D$2:$D$55,RAW_Campaign!$B$2:$B$55,">=3",RAW_Campaign!$B$2:$B$55,"<=4",RAW_Campaign!$C$2:$C$55,"MH_003_MIX_Purchase_ABO") | D22: =IFERROR(SUMIFS(RAW_Campaign!$D$2:$D$55,RAW_Campaign!$B$2:$B$55,">=3",RAW_Campaign!$B$2:$B$55,"<=4",RAW_Campaign!$C$2:$C$55,"MH_003_MIX_Purchase_ABO")/SUMIFS(RAW_Campaign!$D$2:$D$55,RAW_Campaign!$B$2:$B$55,">=3",RAW_Campaign!$B$2:$B$55,"<=4")*100,"-") | E22: =SUMIFS(RAW_Campaign!$E$2:$E$55,RAW_Campaign!$B$2:$B$55,">=3",RAW_Campaign!$B$2:$B$55,"<=4",RAW_Campaign!$C$2:$C$55,"MH_003_MIX_Purchase_ABO") | F22: =IFERROR(SUMIFS(RAW_Campaign!$D$2:$D$55,RAW_Campaign!$B$2:$B$55,">=3",RAW_Campaign!$B$2:$B$55,"<=4",RAW_Campaign!$C$2:$C$55,"MH_003_MIX_Purchase_ABO")/SUMIFS(RAW_Campaign!$E$2:$E$55,RAW_Campaign!$B$2:$B$55,">=3",RAW_Campaign!$B$2:$B$55,"<=4",RAW_Campaign!$C$2:$C$55,"MH_003_MIX_Purchase_ABO"),"-") | G22: =SUMIFS(RAW_Campaign!$F$2:$F$55,RAW_Campaign!$B$2:$B$55,">=3",RAW_Campaign!$B$2:$B$55,"<=4",RAW_Campaign!$C$2:$C$55,"MH_003_MIX_Purchase_ABO") | H22: =IFERROR(SUMIFS(RAW_Campaign!$D$2:$D$55,RAW_Campaign!$B$2:$B$55,">=3",RAW_Campaign!$B$2:$B$55,"<=4",RAW_Campaign!$C$2:$C$55,"MH_003_MIX_Purchase_ABO")/SUMIFS(RAW_Campaign!$F$2:$F$55,RAW_Campaign!$B$2:$B$55,">=3",RAW_Campaign!$B$2:$B$55,"<=4",RAW_Campaign!$C$2:$C$55,"MH_003_MIX_Purchase_ABO"),"-") | I22: =IFERROR(F22/F11,"-")
B23: KA_004_Political_Purchase_ABO | C23: =SUMIFS(RAW_Campaign!$D$2:$D$55,RAW_Campaign!$B$2:$B$55,">=3",RAW_Campaign!$B$2:$B$55,"<=4",RAW_Campaign!$C$2:$C$55,"KA_004_Political_Purchase_ABO") | D23: =IFERROR(SUMIFS(RAW_Campaign!$D$2:$D$55,RAW_Campaign!$B$2:$B$55,">=3",RAW_Campaign!$B$2:$B$55,"<=4",RAW_Campaign!$C$2:$C$55,"KA_004_Political_Purchase_ABO")/SUMIFS(RAW_Campaign!$D$2:$D$55,RAW_Campaign!$B$2:$B$55,">=3",RAW_Campaign!$B$2:$B$55,"<=4")*100,"-") | E23: =SUMIFS(RAW_Campaign!$E$2:$E$55,RAW_Campaign!$B$2:$B$55,">=3",RAW_Campaign!$B$2:$B$55,"<=4",RAW_Campaign!$C$2:$C$55,"KA_004_Political_Purchase_ABO") | F23: =IFERROR(SUMIFS(RAW_Campaign!$D$2:$D$55,RAW_Campaign!$B$2:$B$55,">=3",RAW_Campaign!$B$2:$B$55,"<=4",RAW_Campaign!$C$2:$C$55,"KA_004_Political_Purchase_ABO")/SUMIFS(RAW_Campaign!$E$2:$E$55,RAW_Campaign!$B$2:$B$55,">=3",RAW_Campaign!$B$2:$B$55,"<=4",RAW_Campaign!$C$2:$C$55,"KA_004_Political_Purchase_ABO"),"-") | G23: =SUMIFS(RAW_Campaign!$F$2:$F$55,RAW_Campaign!$B$2:$B$55,">=3",RAW_Campaign!$B$2:$B$55,"<=4",RAW_Campaign!$C$2:$C$55,"KA_004_Political_Purchase_ABO") | H23: =IFERROR(SUMIFS(RAW_Campaign!$D$2:$D$55,RAW_Campaign!$B$2:$B$55,">=3",RAW_Campaign!$B$2:$B$55,"<=4",RAW_Campaign!$C$2:$C$55,"KA_004_Political_Purchase_ABO")/SUMIFS(RAW_Campaign!$F$2:$F$55,RAW_Campaign!$B$2:$B$55,">=3",RAW_Campaign!$B$2:$B$55,"<=4",RAW_Campaign!$C$2:$C$55,"KA_004_Political_Purchase_ABO"),"-") | I23: =IFERROR(F23/F12,"-")
B24: TN_002_EVNT_Purchase_ABO | C24: =SUMIFS(RAW_Campaign!$D$2:$D$55,RAW_Campaign!$B$2:$B$55,">=3",RAW_Campaign!$B$2:$B$55,"<=4",RAW_Campaign!$C$2:$C$55,"TN_002_EVNT_Purchase_ABO") | D24: =IFERROR(SUMIFS(RAW_Campaign!$D$2:$D$55,RAW_Campaign!$B$2:$B$55,">=3",RAW_Campaign!$B$2:$B$55,"<=4",RAW_Campaign!$C$2:$C$55,"TN_002_EVNT_Purchase_ABO")/SUMIFS(RAW_Campaign!$D$2:$D$55,RAW_Campaign!$B$2:$B$55,">=3",RAW_Campaign!$B$2:$B$55,"<=4")*100,"-") | E24: =SUMIFS(RAW_Campaign!$E$2:$E$55,RAW_Campaign!$B$2:$B$55,">=3",RAW_Campaign!$B$2:$B$55,"<=4",RAW_Campaign!$C$2:$C$55,"TN_002_EVNT_Purchase_ABO") | F24: =IFERROR(SUMIFS(RAW_Campaign!$D$2:$D$55,RAW_Campaign!$B$2:$B$55,">=3",RAW_Campaign!$B$2:$B$55,"<=4",RAW_Campaign!$C$2:$C$55,"TN_002_EVNT_Purchase_ABO")/SUMIFS(RAW_Campaign!$E$2:$E$55,RAW_Campaign!$B$2:$B$55,">=3",RAW_Campaign!$B$2:$B$55,"<=4",RAW_Campaign!$C$2:$C$55,"TN_002_EVNT_Purchase_ABO"),"-") | G24: =SUMIFS(RAW_Campaign!$F$2:$F$55,RAW_Campaign!$B$2:$B$55,">=3",RAW_Campaign!$B$2:$B$55,"<=4",RAW_Campaign!$C$2:$C$55,"TN_002_EVNT_Purchase_ABO") | H24: =IFERROR(SUMIFS(RAW_Campaign!$D$2:$D$55,RAW_Campaign!$B$2:$B$55,">=3",RAW_Campaign!$B$2:$B$55,"<=4",RAW_Campaign!$C$2:$C$55,"TN_002_EVNT_Purchase_ABO")/SUMIFS(RAW_Campaign!$F$2:$F$55,RAW_Campaign!$B$2:$B$55,">=3",RAW_Campaign!$B$2:$B$55,"<=4",RAW_Campaign!$C$2:$C$55,"TN_002_EVNT_Purchase_ABO"),"-") | I24: =IFERROR(F24/F13,"-")

Sheet Adset Jump Check
A1: ADSET JUMP CHECK - for every adset that spent > Rs 1,000 on Oct 2, its Trial CAC on Oct 2 (before) vs Oct 3 (after the Sat jump). If the rise were a uniform account-wide shock, almost every row would be red (up). Scaled = budget was raised on Oct 3 in this session.
A2: Adset | B2: Oct 2 Spend | C2: Oct 2 CAC | D2: Oct 3 Spend | E2: Oct 3 CAC | F2: CAC change % | G2: Scaled on Oct 3
A3: HI_005_POL_DL_BAU_VID_05Aug26_LS | B3: =SUMIFS(RAW_Adset!$D$2:$D$401,RAW_Adset!$A$2:$A$401,"HI_005_POL_DL_BAU_VID_05Aug26_LS",RAW_Adset!$B$2:$B$401,"2") | C3: =IFERROR(SUMIFS(RAW_Adset!$D$2:$D$401,RAW_Adset!$A$2:$A$401,"HI_005_POL_DL_BAU_VID_05Aug26_LS",RAW_Adset!$B$2:$B$401,"2")/SUMIFS(RAW_Adset!$E$2:$E$401,RAW_Adset!$A$2:$A$401,"HI_005_POL_DL_BAU_VID_05Aug26_LS",RAW_Adset!$B$2:$B$401,"2"),"-") | D3: =SUMIFS(RAW_Adset!$D$2:$D$401,RAW_Adset!$A$2:$A$401,"HI_005_POL_DL_BAU_VID_05Aug26_LS",RAW_Adset!$B$2:$B$401,"3") | E3: =IFERROR(SUMIFS(RAW_Adset!$D$2:$D$401,RAW_Adset!$A$2:$A$401,"HI_005_POL_DL_BAU_VID_05Aug26_LS",RAW_Adset!$B$2:$B$401,"3")/SUMIFS(RAW_Adset!$E$2:$E$401,RAW_Adset!$A$2:$A$401,"HI_005_POL_DL_BAU_VID_05Aug26_LS",RAW_Adset!$B$2:$B$401,"3"),"-") | F3: =IFERROR((SUMIFS(RAW_Adset!$D$2:$D$401,RAW_Adset!$A$2:$A$401,"HI_005_POL_DL_BAU_VID_05Aug26_LS",RAW_Adset!$B$2:$B$401,"3")/SUMIFS(RAW_Adset!$E$2:$E$401,RAW_Adset!$A$2:$A$401,"HI_005_POL_DL_BAU_VID_05Aug26_LS",RAW_Adset!$B$2:$B$401,"3"))/(SUMIFS(RAW_Adset!$D$2:$D$401,RAW_Adset!$A$2:$A$401,"HI_005_POL_DL_BAU_VID_05Aug26_LS",RAW_Adset!$B$2:$B$401,"2")/SUMIFS(RAW_Adset!$E$2:$E$401,RAW_Adset!$A$2:$A$401,"HI_005_POL_DL_BAU_VID_05Aug26_LS",RAW_Adset!$B$2:$B$401,"2"))-1,"-")
A4: HI_005_OVR_DL_Old_Song_FB_Post_VID_LS_24Sep26 | B4: =SUMIFS(RAW_Adset!$D$2:$D$401,RAW_Adset!$A$2:$A$401,"HI_005_OVR_DL_Old_Song_FB_Post_VID_LS_24Sep26",RAW_Adset!$B$2:$B$401,"2") | C4: =IFERROR(SUMIFS(RAW_Adset!$D$2:$D$401,RAW_Adset!$A$2:$A$401,"HI_005_OVR_DL_Old_Song_FB_Post_VID_LS_24Sep26",RAW_Adset!$B$2:$B$401,"2")/SUMIFS(RAW_Adset!$E$2:$E$401,RAW_Adset!$A$2:$A$401,"HI_005_OVR_DL_Old_Song_FB_Post_VID_LS_24Sep26",RAW_Adset!$B$2:$B$401,"2"),"-") | D4: =SUMIFS(RAW_Adset!$D$2:$D$401,RAW_Adset!$A$2:$A$401,"HI_005_OVR_DL_Old_Song_FB_Post_VID_LS_24Sep26",RAW_Adset!$B$2:$B$401,"3") | E4: =IFERROR(SUMIFS(RAW_Adset!$D$2:$D$401,RAW_Adset!$A$2:$A$401,"HI_005_OVR_DL_Old_Song_FB_Post_VID_LS_24Sep26",RAW_Adset!$B$2:$B$401,"3")/SUMIFS(RAW_Adset!$E$2:$E$401,RAW_Adset!$A$2:$A$401,"HI_005_OVR_DL_Old_Song_FB_Post_VID_LS_24Sep26",RAW_Adset!$B$2:$B$401,"3"),"-") | F4: =IFERROR((SUMIFS(RAW_Adset!$D$2:$D$401,RAW_Adset!$A$2:$A$401,"HI_005_OVR_DL_Old_Song_FB_Post_VID_LS_24Sep26",RAW_Adset!$B$2:$B$401,"3")/SUMIFS(RAW_Adset!$E$2:$E$401,RAW_Adset!$A$2:$A$401,"HI_005_OVR_DL_Old_Song_FB_Post_VID_LS_24Sep26",RAW_Adset!$B$2:$B$401,"3"))/(SUMIFS(RAW_Adset!$D$2:$D$401,RAW_Adset!$A$2:$A$401,"HI_005_OVR_DL_Old_Song_FB_Post_VID_LS_24Sep26",RAW_Adset!$B$2:$B$401,"2")/SUMIFS(RAW_Adset!$E$2:$E$401,RAW_Adset!$A$2:$A$401,"HI_005_OVR_DL_Old_Song_FB_Post_VID_LS_24Sep26",RAW_Adset!$B$2:$B$401,"2"))-1,"-")
A5: HI_005_EVNT_DL_BAU_Navratri_VID_28Sep26_4_LS | B5: =SUMIFS(RAW_Adset!$D$2:$D$401,RAW_Adset!$A$2:$A$401,"HI_005_EVNT_DL_BAU_Navratri_VID_28Sep26_4_LS",RAW_Adset!$B$2:$B$401,"2") | C5: =IFERROR(SUMIFS(RAW_Adset!$D$2:$D$401,RAW_Adset!$A$2:$A$401,"HI_005_EVNT_DL_BAU_Navratri_VID_28Sep26_4_LS",RAW_Adset!$B$2:$B$401,"2")/SUMIFS(RAW_Adset!$E$2:$E$401,RAW_Adset!$A$2:$A$401,"HI_005_EVNT_DL_BAU_Navratri_VID_28Sep26_4_LS",RAW_Adset!$B$2:$B$401,"2"),"-") | D5: =SUMIFS(RAW_Adset!$D$2:$D$401,RAW_Adset!$A$2:$A$401,"HI_005_EVNT_DL_BAU_Navratri_VID_28Sep26_4_LS",RAW_Adset!$B$2:$B$401,"3") | E5: =IFERROR(SUMIFS(RAW_Adset!$D$2:$D$401,RAW_Adset!$A$2:$A$401,"HI_005_EVNT_DL_BAU_Navratri_VID_28Sep26_4_LS",RAW_Adset!$B$2:$B$401,"3")/SUMIFS(RAW_Adset!$E$2:$E$401,RAW_Adset!$A$2:$A$401,"HI_005_EVNT_DL_BAU_Navratri_VID_28Sep26_4_LS",RAW_Adset!$B$2:$B$401,"3"),"-") | F5: =IFERROR((SUMIFS(RAW_Adset!$D$2:$D$401,RAW_Adset!$A$2:$A$401,"HI_005_EVNT_DL_BAU_Navratri_VID_28Sep26_4_LS",RAW_Adset!$B$2:$B$401,"3")/SUMIFS(RAW_Adset!$E$2:$E$401,RAW_Adset!$A$2:$A$401,"HI_005_EVNT_DL_BAU_Navratri_VID_28Sep26_4_LS",RAW_Adset!$B$2:$B$401,"3"))/(SUMIFS(RAW_Adset!$D$2:$D$401,RAW_Adset!$A$2:$A$401,"HI_005_EVNT_DL_BAU_Navratri_VID_28Sep26_4_LS",RAW_Adset!$B$2:$B$401,"2")/SUMIFS(RAW_Adset!$E$2:$E$401,RAW_Adset!$A$2:$A$401,"HI_005_EVNT_DL_BAU_Navratri_VID_28Sep26_4_LS",RAW_Adset!$B$2:$B$401,"2"))-1,"-")
A6: HI_005_OVR_DL_GetFamous_VID_LS_15Sep26 | B6: =SUMIFS(RAW_Adset!$D$2:$D$401,RAW_Adset!$A$2:$A$401,"HI_005_OVR_DL_GetFamous_VID_LS_15Sep26",RAW_Adset!$B$2:$B$401,"2") | C6: =IFERROR(SUMIFS(RAW_Adset!$D$2:$D$401,RAW_Adset!$A$2:$A$401,"HI_005_OVR_DL_GetFamous_VID_LS_15Sep26",RAW_Adset!$B$2:$B$401,"2")/SUMIFS(RAW_Adset!$E$2:$E$401,RAW_Adset!$A$2:$A$401,"HI_005_OVR_DL_GetFamous_VID_LS_15Sep26",RAW_Adset!$B$2:$B$401,"2"),"-") | D6: =SUMIFS(RAW_Adset!$D$2:$D$401,RAW_Adset!$A$2:$A$401,"HI_005_OVR_DL_GetFamous_VID_LS_15Sep26",RAW_Adset!$B$2:$B$401,"3") | E6: =IFERROR(SUMIFS(RAW_Adset!$D$2:$D$401,RAW_Adset!$A$2:$A$401,"HI_005_OVR_DL_GetFamous_VID_LS_15Sep26",RAW_Adset!$B$2:$B$401,"3")/SUMIFS(RAW_Adset!$E$2:$E$401,RAW_Adset!$A$2:$A$401,"HI_005_OVR_DL_GetFamous_VID_LS_15Sep26",RAW_Adset!$B$2:$B$401,"3"),"-") | F6: =IFERROR((SUMIFS(RAW_Adset!$D$2:$D$401,RAW_Adset!$A$2:$A$401,"HI_005_OVR_DL_GetFamous_VID_LS_15Sep26",RAW_Adset!$B$2:$B$401,"3")/SUMIFS(RAW_Adset!$E$2:$E$401,RAW_Adset!$A$2:$A$401,"HI_005_OVR_DL_GetFamous_VID_LS_15Sep26",RAW_Adset!$B$2:$B$401,"3"))/(SUMIFS(RAW_Adset!$D$2:$D$401,RAW_Adset!$A$2:$A$401,"HI_005_OVR_DL_GetFamous_VID_LS_15Sep26",RAW_Adset!$B$2:$B$401,"2")/SUMIFS(RAW_Adset!$E$2:$E$401,RAW_Adset!$A$2:$A$401,"HI_005_OVR_DL_GetFamous_VID_LS_15Sep26",RAW_Adset!$B$2:$B$401,"2"))-1,"-") | G6: Yes
A7: HI_005_BHKT_Hanuman_ID_Card_EXT_DL_BAU_Income_VID_11Sep26_LS | B7: =SUMIFS(RAW_Adset!$D$2:$D$401,RAW_Adset!$A$2:$A$401,"HI_005_BHKT_Hanuman_ID_Card_EXT_DL_BAU_Income_VID_11Sep26_LS",RAW_Adset!$B$2:$B$401,"2") | C7: =IFERROR(SUMIFS(RAW_Adset!$D$2:$D$401,RAW_Adset!$A$2:$A$401,"HI_005_BHKT_Hanuman_ID_Card_EXT_DL_BAU_Income_VID_11Sep26_LS",RAW_Adset!$B$2:$B$401,"2")/SUMIFS(RAW_Adset!$E$2:$E$401,RAW_Adset!$A$2:$A$401,"HI_005_BHKT_Hanuman_ID_Card_EXT_DL_BAU_Income_VID_11Sep26_LS",RAW_Adset!$B$2:$B$401,"2"),"-") | D7: =SUMIFS(RAW_Adset!$D$2:$D$401,RAW_Adset!$A$2:$A$401,"HI_005_BHKT_Hanuman_ID_Card_EXT_DL_BAU_Income_VID_11Sep26_LS",RAW_Adset!$B$2:$B$401,"3") | E7: =IFERROR(SUMIFS(RAW_Adset!$D$2:$D$401,RAW_Adset!$A$2:$A$401,"HI_005_BHKT_Hanuman_ID_Card_EXT_DL_BAU_Income_VID_11Sep26_LS",RAW_Adset!$B$2:$B$401,"3")/SUMIFS(RAW_Adset!$E$2:$E$401,RAW_Adset!$A$2:$A$401,"HI_005_BHKT_Hanuman_ID_Card_EXT_DL_BAU_Income_VID_11Sep26_LS",RAW_Adset!$B$2:$B$401,"3"),"-") | F7: =IFERROR((SUMIFS(RAW_Adset!$D$2:$D$401,RAW_Adset!$A$2:$A$401,"HI_005_BHKT_Hanuman_ID_Card_EXT_DL_BAU_Income_VID_11Sep26_LS",RAW_Adset!$B$2:$B$401,"3")/SUMIFS(RAW_Adset!$E$2:$E$401,RAW_Adset!$A$2:$A$401,"HI_005_BHKT_Hanuman_ID_Card_EXT_DL_BAU_Income_VID_11Sep26_LS",RAW_Adset!$B$2:$B$401,"3"))/(SUMIFS(RAW_Adset!$D$2:$D$401,RAW_Adset!$A$2:$A$401,"HI_005_BHKT_Hanuman_ID_Card_EXT_DL_BAU_Income_VID_11Sep26_LS",RAW_Adset!$B$2:$B$401,"2")/SUMIFS(RAW_Adset!$E$2:$E$401,RAW_Adset!$A$2:$A$401,"HI_005_BHKT_Hanuman_ID_Card_EXT_DL_BAU_Income_VID_11Sep26_LS",RAW_Adset!$B$2:$B$401,"2"))-1,"-") | G7: Yes
A8: HI_005_BHKT_Hanuman_DL_Female_Business_VOX_POP_VID_Aug25_LS | B8: =SUMIFS(RAW_Adset!$D$2:$D$401,RAW_Adset!$A$2:$A$401,"HI_005_BHKT_Hanuman_DL_Female_Business_VOX_POP_VID_Aug25_LS",RAW_Adset!$B$2:$B$401,"2") | C8: =IFERROR(SUMIFS(RAW_Adset!$D$2:$D$401,RAW_Adset!$A$2:$A$401,"HI_005_BHKT_Hanuman_DL_Female_Business_VOX_POP_VID_Aug25_LS",RAW_Adset!$B$2:$B$401,"2")/SUMIFS(RAW_Adset!$E$2:$E$401,RAW_Adset!$A$2:$A$401,"HI_005_BHKT_Hanuman_DL_Female_Business_VOX_POP_VID_Aug25_LS",RAW_Adset!$B$2:$B$401,"2"),"-") | D8: =SUMIFS(RAW_Adset!$D$2:$D$401,RAW_Adset!$A$2:$A$401,"HI_005_BHKT_Hanuman_DL_Female_Business_VOX_POP_VID_Aug25_LS",RAW_Adset!$B$2:$B$401,"3") | E8: =IFERROR(SUMIFS(RAW_Adset!$D$2:$D$401,RAW_Adset!$A$2:$A$401,"HI_005_BHKT_Hanuman_DL_Female_Business_VOX_POP_VID_Aug25_LS",RAW_Adset!$B$2:$B$401,"3")/SUMIFS(RAW_Adset!$E$2:$E$401,RAW_Adset!$A$2:$A$401,"HI_005_BHKT_Hanuman_DL_Female_Business_VOX_POP_VID_Aug25_LS",RAW_Adset!$B$2:$B$401,"3"),"-") | F8: =IFERROR((SUMIFS(RAW_Adset!$D$2:$D$401,RAW_Adset!$A$2:$A$401,"HI_005_BHKT_Hanuman_DL_Female_Business_VOX_POP_VID_Aug25_LS",RAW_Adset!$B$2:$B$401,"3")/SUMIFS(RAW_Adset!$E$2:$E$401,RAW_Adset!$A$2:$A$401,"HI_005_BHKT_Hanuman_DL_Female_Business_VOX_POP_VID_Aug25_LS",RAW_Adset!$B$2:$B$401,"3"))/(SUMIFS(RAW_Adset!$D$2:$D$401,RAW_Adset!$A$2:$A$401,"HI_005_BHKT_Hanuman_DL_Female_Business_VOX_POP_VID_Aug25_LS",RAW_Adset!$B$2:$B$401,"2")/SUMIFS(RAW_Adset!$E$2:$E$401,RAW_Adset!$A$2:$A$401,"HI_005_BHKT_Hanuman_DL_Female_Business_VOX_POP_VID_Aug25_LS",RAW_Adset!$B$2:$B$401,"2"))-1,"-")
A9: HI_005_BHKT_Hanuman_ID_Card_DL_BAU_VID_Sep14_LS | B9: =SUMIFS(RAW_Adset!$D$2:$D$401,RAW_Adset!$A$2:$A$401,"HI_005_BHKT_Hanuman_ID_Card_DL_BAU_VID_Sep14_LS",RAW_Adset!$B$2:$B$401,"2") | C9: =IFERROR(SUMIFS(RAW_Adset!$D$2:$D$401,RAW_Adset!$A$2:$A$401,"HI_005_BHKT_Hanuman_ID_Card_DL_BAU_VID_Sep14_LS",RAW_Adset!$B$2:$B$401,"2")/SUMIFS(RAW_Adset!$E$2:$E$401,RAW_Adset!$A$2:$A$401,"HI_005_BHKT_Hanuman_ID_Card_DL_BAU_VID_Sep14_LS",RAW_Adset!$B$2:$B$401,"2"),"-") | D9: =SUMIFS(RAW_Adset!$D$2:$D$401,RAW_Adset!$A$2:$A$401,"HI_005_BHKT_Hanuman_ID_Card_DL_BAU_VID_Sep14_LS",RAW_Adset!$B$2:$B$401,"3") | E9: =IFERROR(SUMIFS(RAW_Adset!$D$2:$D$401,RAW_Adset!$A$2:$A$401,"HI_005_BHKT_Hanuman_ID_Card_DL_BAU_VID_Sep14_LS",RAW_Adset!$B$2:$B$401,"3")/SUMIFS(RAW_Adset!$E$2:$E$401,RAW_Adset!$A$2:$A$401,"HI_005_BHKT_Hanuman_ID_Card_DL_BAU_VID_Sep14_LS",RAW_Adset!$B$2:$B$401,"3"),"-") | F9: =IFERROR((SUMIFS(RAW_Adset!$D$2:$D$401,RAW_Adset!$A$2:$A$401,"HI_005_BHKT_Hanuman_ID_Card_DL_BAU_VID_Sep14_LS",RAW_Adset!$B$2:$B$401,"3")/SUMIFS(RAW_Adset!$E$2:$E$401,RAW_Adset!$A$2:$A$401,"HI_005_BHKT_Hanuman_ID_Card_DL_BAU_VID_Sep14_LS",RAW_Adset!$B$2:$B$401,"3"))/(SUMIFS(RAW_Adset!$D$2:$D$401,RAW_Adset!$A$2:$A$401,"HI_005_BHKT_Hanuman_ID_Card_DL_BAU_VID_Sep14_LS",RAW_Adset!$B$2:$B$401,"2")/SUMIFS(RAW_Adset!$E$2:$E$401,RAW_Adset!$A$2:$A$401,"HI_005_BHKT_Hanuman_ID_Card_DL_BAU_VID_Sep14_LS",RAW_Adset!$B$2:$B$401,"2"))-1,"-")
A10: KA_004_BDAY_DL_BAU_B1597 - B1599_VID_LS | B10: =SUMIFS(RAW_Adset!$D$2:$D$401,RAW_Adset!$A$2:$A$401,"KA_004_BDAY_DL_BAU_B1597 - B1599_VID_LS",RAW_Adset!$B$2:$B$401,"2") | C10: =IFERROR(SUMIFS(RAW_Adset!$D$2:$D$401,RAW_Adset!$A$2:$A$401,"KA_004_BDAY_DL_BAU_B1597 - B1599_VID_LS",RAW_Adset!$B$2:$B$401,"2")/SUMIFS(RAW_Adset!$E$2:$E$401,RAW_Adset!$A$2:$A$401,"KA_004_BDAY_DL_BAU_B1597 - B1599_VID_LS",RAW_Adset!$B$2:$B$401,"2"),"-") | D10: =SUMIFS(RAW_Adset!$D$2:$D$401,RAW_Adset!$A$2:$A$401,"KA_004_BDAY_DL_BAU_B1597 - B1599_VID_LS",RAW_Adset!$B$2:$B$401,"3") | E10: =IFERROR(SUMIFS(RAW_Adset!$D$2:$D$401,RAW_Adset!$A$2:$A$401,"KA_004_BDAY_DL_BAU_B1597 - B1599_VID_LS",RAW_Adset!$B$2:$B$401,"3")/SUMIFS(RAW_Adset!$E$2:$E$401,RAW_Adset!$A$2:$A$401,"KA_004_BDAY_DL_BAU_B1597 - B1599_VID_LS",RAW_Adset!$B$2:$B$401,"3"),"-") | F10: =IFERROR((SUMIFS(RAW_Adset!$D$2:$D$401,RAW_Adset!$A$2:$A$401,"KA_004_BDAY_DL_BAU_B1597 - B1599_VID_LS",RAW_Adset!$B$2:$B$401,"3")/SUMIFS(RAW_Adset!$E$2:$E$401,RAW_Adset!$A$2:$A$401,"KA_004_BDAY_DL_BAU_B1597 - B1599_VID_LS",RAW_Adset!$B$2:$B$401,"3"))/(SUMIFS(RAW_Adset!$D$2:$D$401,RAW_Adset!$A$2:$A$401,"KA_004_BDAY_DL_BAU_B1597 - B1599_VID_LS",RAW_Adset!$B$2:$B$401,"2")/SUMIFS(RAW_Adset!$E$2:$E$401,RAW_Adset!$A$2:$A$401,"KA_004_BDAY_DL_BAU_B1597 - B1599_VID_LS",RAW_Adset!$B$2:$B$401,"2"))-1,"-") | G10: Yes
A11: HI_005_BHKT_Hanuman_DL_UGC_AI_Family_Relationships_VID_15Sep26_LS | B11: =SUMIFS(RAW_Adset!$D$2:$D$401,RAW_Adset!$A$2:$A$401,"HI_005_BHKT_Hanuman_DL_UGC_AI_Family_Relationships_VID_15Sep26_LS",RAW_Adset!$B$2:$B$401,"2") | C11: =IFERROR(SUMIFS(RAW_Adset!$D$2:$D$401,RAW_Adset!$A$2:$A$401,"HI_005_BHKT_Hanuman_DL_UGC_AI_Family_Relationships_VID_15Sep26_LS",RAW_Adset!$B$2:$B$401,"2")/SUMIFS(RAW_Adset!$E$2:$E$401,RAW_Adset!$A$2:$A$401,"HI_005_BHKT_Hanuman_DL_UGC_AI_Family_Relationships_VID_15Sep26_LS",RAW_Adset!$B$2:$B$401,"2"),"-") | D11: =SUMIFS(RAW_Adset!$D$2:$D$401,RAW_Adset!$A$2:$A$401,"HI_005_BHKT_Hanuman_DL_UGC_AI_Family_Relationships_VID_15Sep26_LS",RAW_Adset!$B$2:$B$401,"3") | E11: =IFERROR(SUMIFS(RAW_Adset!$D$2:$D$401,RAW_Adset!$A$2:$A$401,"HI_005_BHKT_Hanuman_DL_UGC_AI_Family_Relationships_VID_15Sep26_LS",RAW_Adset!$B$2:$B$401,"3")/SUMIFS(RAW_Adset!$E$2:$E$401,RAW_Adset!$A$2:$A$401,"HI_005_BHKT_Hanuman_DL_UGC_AI_Family_Relationships_VID_15Sep26_LS",RAW_Adset!$B$2:$B$401,"3"),"-") | F11: =IFERROR((SUMIFS(RAW_Adset!$D$2:$D$401,RAW_Adset!$A$2:$A$401,"HI_005_BHKT_Hanuman_DL_UGC_AI_Family_Relationships_VID_15Sep26_LS",RAW_Adset!$B$2:$B$401,"3")/SUMIFS(RAW_Adset!$E$2:$E$401,RAW_Adset!$A$2:$A$401,"HI_005_BHKT_Hanuman_DL_UGC_AI_Family_Relationships_VID_15Sep26_LS",RAW_Adset!$B$2:$B$401,"3"))/(SUMIFS(RAW_Adset!$D$2:$D$401,RAW_Adset!$A$2:$A$401,"HI_005_BHKT_Hanuman_DL_UGC_AI_Family_Relationships_VID_15Sep26_LS",RAW_Adset!$B$2:$B$401,"2")/SUMIFS(RAW_Adset!$E$2:$E$401,RAW_Adset!$A$2:$A$401,"HI_005_BHKT_Hanuman_DL_UGC_AI_Family_Relationships_VID_15Sep26_LS",RAW_Adset!$B$2:$B$401,"2"))-1,"-") | G11: Yes
A12: HI_005_BHKT_Hanuman_ID_Card_EXT_DL_BAU_VID_11Sep26_LS | B12: =SUMIFS(RAW_Adset!$D$2:$D$401,RAW_Adset!$A$2:$A$401,"HI_005_BHKT_Hanuman_ID_Card_EXT_DL_BAU_VID_11Sep26_LS",RAW_Adset!$B$2:$B$401,"2") | C12: =IFERROR(SUMIFS(RAW_Adset!$D$2:$D$401,RAW_Adset!$A$2:$A$401,"HI_005_BHKT_Hanuman_ID_Card_EXT_DL_BAU_VID_11Sep26_LS",RAW_Adset!$B$2:$B$401,"2")/SUMIFS(RAW_Adset!$E$2:$E$401,RAW_Adset!$A$2:$A$401,"HI_005_BHKT_Hanuman_ID_Card_EXT_DL_BAU_VID_11Sep26_LS",RAW_Adset!$B$2:$B$401,"2"),"-") | D12: =SUMIFS(RAW_Adset!$D$2:$D$401,RAW_Adset!$A$2:$A$401,"HI_005_BHKT_Hanuman_ID_Card_EXT_DL_BAU_VID_11Sep26_LS",RAW_Adset!$B$2:$B$401,"3") | E12: =IFERROR(SUMIFS(RAW_Adset!$D$2:$D$401,RAW_Adset!$A$2:$A$401,"HI_005_BHKT_Hanuman_ID_Card_EXT_DL_BAU_VID_11Sep26_LS",RAW_Adset!$B$2:$B$401,"3")/SUMIFS(RAW_Adset!$E$2:$E$401,RAW_Adset!$A$2:$A$401,"HI_005_BHKT_Hanuman_ID_Card_EXT_DL_BAU_VID_11Sep26_LS",RAW_Adset!$B$2:$B$401,"3"),"-") | F12: =IFERROR((SUMIFS(RAW_Adset!$D$2:$D$401,RAW_Adset!$A$2:$A$401,"HI_005_BHKT_Hanuman_ID_Card_EXT_DL_BAU_VID_11Sep26_LS",RAW_Adset!$B$2:$B$401,"3")/SUMIFS(RAW_Adset!$E$2:$E$401,RAW_Adset!$A$2:$A$401,"HI_005_BHKT_Hanuman_ID_Card_EXT_DL_BAU_VID_11Sep26_LS",RAW_Adset!$B$2:$B$401,"3"))/(SUMIFS(RAW_Adset!$D$2:$D$401,RAW_Adset!$A$2:$A$401,"HI_005_BHKT_Hanuman_ID_Card_EXT_DL_BAU_VID_11Sep26_LS",RAW_Adset!$B$2:$B$401,"2")/SUMIFS(RAW_Adset!$E$2:$E$401,RAW_Adset!$A$2:$A$401,"HI_005_BHKT_Hanuman_ID_Card_EXT_DL_BAU_VID_11Sep26_LS",RAW_Adset!$B$2:$B$401,"2"))-1,"-")
A13: HI_005_OVR_DL_GetFamous_BreakingNews_VID_LS_28Sep26 | B13: =SUMIFS(RAW_Adset!$D$2:$D$401,RAW_Adset!$A$2:$A$401,"HI_005_OVR_DL_GetFamous_BreakingNews_VID_LS_28Sep26",RAW_Adset!$B$2:$B$401,"2") | C13: =IFERROR(SUMIFS(RAW_Adset!$D$2:$D$401,RAW_Adset!$A$2:$A$401,"HI_005_OVR_DL_GetFamous_BreakingNews_VID_LS_28Sep26",RAW_Adset!$B$2:$B$401,"2")/SUMIFS(RAW_Adset!$E$2:$E$401,RAW_Adset!$A$2:$A$401,"HI_005_OVR_DL_GetFamous_BreakingNews_VID_LS_28Sep26",RAW_Adset!$B$2:$B$401,"2"),"-") | D13: =SUMIFS(RAW_Adset!$D$2:$D$401,RAW_Adset!$A$2:$A$401,"HI_005_OVR_DL_GetFamous_BreakingNews_VID_LS_28Sep26",RAW_Adset!$B$2:$B$401,"3") | E13: =IFERROR(SUMIFS(RAW_Adset!$D$2:$D$401,RAW_Adset!$A$2:$A$401,"HI_005_OVR_DL_GetFamous_BreakingNews_VID_LS_28Sep26",RAW_Adset!$B$2:$B$401,"3")/SUMIFS(RAW_Adset!$E$2:$E$401,RAW_Adset!$A$2:$A$401,"HI_005_OVR_DL_GetFamous_BreakingNews_VID_LS_28Sep26",RAW_Adset!$B$2:$B$401,"3"),"-") | F13: =IFERROR((SUMIFS(RAW_Adset!$D$2:$D$401,RAW_Adset!$A$2:$A$401,"HI_005_OVR_DL_GetFamous_BreakingNews_VID_LS_28Sep26",RAW_Adset!$B$2:$B$401,"3")/SUMIFS(RAW_Adset!$E$2:$E$401,RAW_Adset!$A$2:$A$401,"HI_005_OVR_DL_GetFamous_BreakingNews_VID_LS_28Sep26",RAW_Adset!$B$2:$B$401,"3"))/(SUMIFS(RAW_Adset!$D$2:$D$401,RAW_Adset!$A$2:$A$401,"HI_005_OVR_DL_GetFamous_BreakingNews_VID_LS_28Sep26",RAW_Adset!$B$2:$B$401,"2")/SUMIFS(RAW_Adset!$E$2:$E$401,RAW_Adset!$A$2:$A$401,"HI_005_OVR_DL_GetFamous_BreakingNews_VID_LS_28Sep26",RAW_Adset!$B$2:$B$401,"2"))-1,"-") | G13: Yes
A14: HI_005_BHKT_Hanuman_DL_BAU_VID_Sep04_1_LS | B14: =SUMIFS(RAW_Adset!$D$2:$D$401,RAW_Adset!$A$2:$A$401,"HI_005_BHKT_Hanuman_DL_BAU_VID_Sep04_1_LS",RAW_Adset!$B$2:$B$401,"2") | C14: =IFERROR(SUMIFS(RAW_Adset!$D$2:$D$401,RAW_Adset!$A$2:$A$401,"HI_005_BHKT_Hanuman_DL_BAU_VID_Sep04_1_LS",RAW_Adset!$B$2:$B$401,"2")/SUMIFS(RAW_Adset!$E$2:$E$401,RAW_Adset!$A$2:$A$401,"HI_005_BHKT_Hanuman_DL_BAU_VID_Sep04_1_LS",RAW_Adset!$B$2:$B$401,"2"),"-") | D14: =SUMIFS(RAW_Adset!$D$2:$D$401,RAW_Adset!$A$2:$A$401,"HI_005_BHKT_Hanuman_DL_BAU_VID_Sep04_1_LS",RAW_Adset!$B$2:$B$401,"3") | E14: =IFERROR(SUMIFS(RAW_Adset!$D$2:$D$401,RAW_Adset!$A$2:$A$401,"HI_005_BHKT_Hanuman_DL_BAU_VID_Sep04_1_LS",RAW_Adset!$B$2:$B$401,"3")/SUMIFS(RAW_Adset!$E$2:$E$401,RAW_Adset!$A$2:$A$401,"HI_005_BHKT_Hanuman_DL_BAU_VID_Sep04_1_LS",RAW_Adset!$B$2:$B$401,"3"),"-") | F14: =IFERROR((SUMIFS(RAW_Adset!$D$2:$D$401,RAW_Adset!$A$2:$A$401,"HI_005_BHKT_Hanuman_DL_BAU_VID_Sep04_1_LS",RAW_Adset!$B$2:$B$401,"3")/SUMIFS(RAW_Adset!$E$2:$E$401,RAW_Adset!$A$2:$A$401,"HI_005_BHKT_Hanuman_DL_BAU_VID_Sep04_1_LS",RAW_Adset!$B$2:$B$401,"3"))/(SUMIFS(RAW_Adset!$D$2:$D$401,RAW_Adset!$A$2:$A$401,"HI_005_BHKT_Hanuman_DL_BAU_VID_Sep04_1_LS",RAW_Adset!$B$2:$B$401,"2")/SUMIFS(RAW_Adset!$E$2:$E$401,RAW_Adset!$A$2:$A$401,"HI_005_BHKT_Hanuman_DL_BAU_VID_Sep04_1_LS",RAW_Adset!$B$2:$B$401,"2"))-1,"-")
A15: HI_005_OVR_NDL_Old_Song_VID_LS_15Sep26 | B15: =SUMIFS(RAW_Adset!$D$2:$D$401,RAW_Adset!$A$2:$A$401,"HI_005_OVR_NDL_Old_Song_VID_LS_15Sep26",RAW_Adset!$B$2:$B$401,"2") | C15: =IFERROR(SUMIFS(RAW_Adset!$D$2:$D$401,RAW_Adset!$A$2:$A$401,"HI_005_OVR_NDL_Old_Song_VID_LS_15Sep26",RAW_Adset!$B$2:$B$401,"2")/SUMIFS(RAW_Adset!$E$2:$E$401,RAW_Adset!$A$2:$A$401,"HI_005_OVR_NDL_Old_Song_VID_LS_15Sep26",RAW_Adset!$B$2:$B$401,"2"),"-") | D15: =SUMIFS(RAW_Adset!$D$2:$D$401,RAW_Adset!$A$2:$A$401,"HI_005_OVR_NDL_Old_Song_VID_LS_15Sep26",RAW_Adset!$B$2:$B$401,"3") | E15: =IFERROR(SUMIFS(RAW_Adset!$D$2:$D$401,RAW_Adset!$A$2:$A$401,"HI_005_OVR_NDL_Old_Song_VID_LS_15Sep26",RAW_Adset!$B$2:$B$401,"3")/SUMIFS(RAW_Adset!$E$2:$E$401,RAW_Adset!$A$2:$A$401,"HI_005_OVR_NDL_Old_Song_VID_LS_15Sep26",RAW_Adset!$B$2:$B$401,"3"),"-") | F15: =IFERROR((SUMIFS(RAW_Adset!$D$2:$D$401,RAW_Adset!$A$2:$A$401,"HI_005_OVR_NDL_Old_Song_VID_LS_15Sep26",RAW_Adset!$B$2:$B$401,"3")/SUMIFS(RAW_Adset!$E$2:$E$401,RAW_Adset!$A$2:$A$401,"HI_005_OVR_NDL_Old_Song_VID_LS_15Sep26",RAW_Adset!$B$2:$B$401,"3"))/(SUMIFS(RAW_Adset!$D$2:$D$401,RAW_Adset!$A$2:$A$401,"HI_005_OVR_NDL_Old_Song_VID_LS_15Sep26",RAW_Adset!$B$2:$B$401,"2")/SUMIFS(RAW_Adset!$E$2:$E$401,RAW_Adset!$A$2:$A$401,"HI_005_OVR_NDL_Old_Song_VID_LS_15Sep26",RAW_Adset!$B$2:$B$401,"2"))-1,"-")
A16: HI_005_POL_VID_Cat_DL_BAU_Shri_Ram_BJP_VID_18Sep_LS | B16: =SUMIFS(RAW_Adset!$D$2:$D$401,RAW_Adset!$A$2:$A$401,"HI_005_POL_VID_Cat_DL_BAU_Shri_Ram_BJP_VID_18Sep_LS",RAW_Adset!$B$2:$B$401,"2") | C16: =IFERROR(SUMIFS(RAW_Adset!$D$2:$D$401,RAW_Adset!$A$2:$A$401,"HI_005_POL_VID_Cat_DL_BAU_Shri_Ram_BJP_VID_18Sep_LS",RAW_Adset!$B$2:$B$401,"2")/SUMIFS(RAW_Adset!$E$2:$E$401,RAW_Adset!$A$2:$A$401,"HI_005_POL_VID_Cat_DL_BAU_Shri_Ram_BJP_VID_18Sep_LS",RAW_Adset!$B$2:$B$401,"2"),"-") | D16: =SUMIFS(RAW_Adset!$D$2:$D$401,RAW_Adset!$A$2:$A$401,"HI_005_POL_VID_Cat_DL_BAU_Shri_Ram_BJP_VID_18Sep_LS",RAW_Adset!$B$2:$B$401,"3") | E16: =IFERROR(SUMIFS(RAW_Adset!$D$2:$D$401,RAW_Adset!$A$2:$A$401,"HI_005_POL_VID_Cat_DL_BAU_Shri_Ram_BJP_VID_18Sep_LS",RAW_Adset!$B$2:$B$401,"3")/SUMIFS(RAW_Adset!$E$2:$E$401,RAW_Adset!$A$2:$A$401,"HI_005_POL_VID_Cat_DL_BAU_Shri_Ram_BJP_VID_18Sep_LS",RAW_Adset!$B$2:$B$401,"3"),"-") | F16: =IFERROR((SUMIFS(RAW_Adset!$D$2:$D$401,RAW_Adset!$A$2:$A$401,"HI_005_POL_VID_Cat_DL_BAU_Shri_Ram_BJP_VID_18Sep_LS",RAW_Adset!$B$2:$B$401,"3")/SUMIFS(RAW_Adset!$E$2:$E$401,RAW_Adset!$A$2:$A$401,"HI_005_POL_VID_Cat_DL_BAU_Shri_Ram_BJP_VID_18Sep_LS",RAW_Adset!$B$2:$B$401,"3"))/(SUMIFS(RAW_Adset!$D$2:$D$401,RAW_Adset!$A$2:$A$401,"HI_005_POL_VID_Cat_DL_BAU_Shri_Ram_BJP_VID_18Sep_LS",RAW_Adset!$B$2:$B$401,"2")/SUMIFS(RAW_Adset!$E$2:$E$401,RAW_Adset!$A$2:$A$401,"HI_005_POL_VID_Cat_DL_BAU_Shri_Ram_BJP_VID_18Sep_LS",RAW_Adset!$B$2:$B$401,"2"))-1,"-")
A17: HI_005_BHKT_Khatu_Shyam_DL_UGC_AI_Growth_Blessing_VID_28Sep26_LS | B17: =SUMIFS(RAW_Adset!$D$2:$D$401,RAW_Adset!$A$2:$A$401,"HI_005_BHKT_Khatu_Shyam_DL_UGC_AI_Growth_Blessing_VID_28Sep26_LS",RAW_Adset!$B$2:$B$401,"2") | C17: =IFERROR(SUMIFS(RAW_Adset!$D$2:$D$401,RAW_Adset!$A$2:$A$401,"HI_005_BHKT_Khatu_Shyam_DL_UGC_AI_Growth_Blessing_VID_28Sep26_LS",RAW_Adset!$B$2:$B$401,"2")/SUMIFS(RAW_Adset!$E$2:$E$401,RAW_Adset!$A$2:$A$401,"HI_005_BHKT_Khatu_Shyam_DL_UGC_AI_Growth_Blessing_VID_28Sep26_LS",RAW_Adset!$B$2:$B$401,"2"),"-") | D17: =SUMIFS(RAW_Adset!$D$2:$D$401,RAW_Adset!$A$2:$A$401,"HI_005_BHKT_Khatu_Shyam_DL_UGC_AI_Growth_Blessing_VID_28Sep26_LS",RAW_Adset!$B$2:$B$401,"3") | E17: =IFERROR(SUMIFS(RAW_Adset!$D$2:$D$401,RAW_Adset!$A$2:$A$401,"HI_005_BHKT_Khatu_Shyam_DL_UGC_AI_Growth_Blessing_VID_28Sep26_LS",RAW_Adset!$B$2:$B$401,"3")/SUMIFS(RAW_Adset!$E$2:$E$401,RAW_Adset!$A$2:$A$401,"HI_005_BHKT_Khatu_Shyam_DL_UGC_AI_Growth_Blessing_VID_28Sep26_LS",RAW_Adset!$B$2:$B$401,"3"),"-") | F17: =IFERROR((SUMIFS(RAW_Adset!$D$2:$D$401,RAW_Adset!$A$2:$A$401,"HI_005_BHKT_Khatu_Shyam_DL_UGC_AI_Growth_Blessing_VID_28Sep26_LS",RAW_Adset!$B$2:$B$401,"3")/SUMIFS(RAW_Adset!$E$2:$E$401,RAW_Adset!$A$2:$A$401,"HI_005_BHKT_Khatu_Shyam_DL_UGC_AI_Growth_Blessing_VID_28Sep26_LS",RAW_Adset!$B$2:$B$401,"3"))/(SUMIFS(RAW_Adset!$D$2:$D$401,RAW_Adset!$A$2:$A$401,"HI_005_BHKT_Khatu_Shyam_DL_UGC_AI_Growth_Blessing_VID_28Sep26_LS",RAW_Adset!$B$2:$B$401,"2")/SUMIFS(RAW_Adset!$E$2:$E$401,RAW_Adset!$A$2:$A$401,"HI_005_BHKT_Khatu_Shyam_DL_UGC_AI_Growth_Blessing_VID_28Sep26_LS",RAW_Adset!$B$2:$B$401,"2"))-1,"-") | G17: Yes
A18: HI_005_OVR_DL_Best_performing_MIX_VID_LS_28Sep26 | B18: =SUMIFS(RAW_Adset!$D$2:$D$401,RAW_Adset!$A$2:$A$401,"HI_005_OVR_DL_Best_performing_MIX_VID_LS_28Sep26",RAW_Adset!$B$2:$B$401,"2") | C18: =IFERROR(SUMIFS(RAW_Adset!$D$2:$D$401,RAW_Adset!$A$2:$A$401,"HI_005_OVR_DL_Best_performing_MIX_VID_LS_28Sep26",RAW_Adset!$B$2:$B$401,"2")/SUMIFS(RAW_Adset!$E$2:$E$401,RAW_Adset!$A$2:$A$401,"HI_005_OVR_DL_Best_performing_MIX_VID_LS_28Sep26",RAW_Adset!$B$2:$B$401,"2"),"-") | D18: =SUMIFS(RAW_Adset!$D$2:$D$401,RAW_Adset!$A$2:$A$401,"HI_005_OVR_DL_Best_performing_MIX_VID_LS_28Sep26",RAW_Adset!$B$2:$B$401,"3") | E18: =IFERROR(SUMIFS(RAW_Adset!$D$2:$D$401,RAW_Adset!$A$2:$A$401,"HI_005_OVR_DL_Best_performing_MIX_VID_LS_28Sep26",RAW_Adset!$B$2:$B$401,"3")/SUMIFS(RAW_Adset!$E$2:$E$401,RAW_Adset!$A$2:$A$401,"HI_005_OVR_DL_Best_performing_MIX_VID_LS_28Sep26",RAW_Adset!$B$2:$B$401,"3"),"-") | F18: =IFERROR((SUMIFS(RAW_Adset!$D$2:$D$401,RAW_Adset!$A$2:$A$401,"HI_005_OVR_DL_Best_performing_MIX_VID_LS_28Sep26",RAW_Adset!$B$2:$B$401,"3")/SUMIFS(RAW_Adset!$E$2:$E$401,RAW_Adset!$A$2:$A$401,"HI_005_OVR_DL_Best_performing_MIX_VID_LS_28Sep26",RAW_Adset!$B$2:$B$401,"3"))/(SUMIFS(RAW_Adset!$D$2:$D$401,RAW_Adset!$A$2:$A$401,"HI_005_OVR_DL_Best_performing_MIX_VID_LS_28Sep26",RAW_Adset!$B$2:$B$401,"2")/SUMIFS(RAW_Adset!$E$2:$E$401,RAW_Adset!$A$2:$A$401,"HI_005_OVR_DL_Best_performing_MIX_VID_LS_28Sep26",RAW_Adset!$B$2:$B$401,"2"))-1,"-")
A19: MH_003_BHKT_DL_BAU_ID_Card_VID_16Sep26_LS | B19: =SUMIFS(RAW_Adset!$D$2:$D$401,RAW_Adset!$A$2:$A$401,"MH_003_BHKT_DL_BAU_ID_Card_VID_16Sep26_LS",RAW_Adset!$B$2:$B$401,"2") | C19: =IFERROR(SUMIFS(RAW_Adset!$D$2:$D$401,RAW_Adset!$A$2:$A$401,"MH_003_BHKT_DL_BAU_ID_Card_VID_16Sep26_LS",RAW_Adset!$B$2:$B$401,"2")/SUMIFS(RAW_Adset!$E$2:$E$401,RAW_Adset!$A$2:$A$401,"MH_003_BHKT_DL_BAU_ID_Card_VID_16Sep26_LS",RAW_Adset!$B$2:$B$401,"2"),"-") | D19: =SUMIFS(RAW_Adset!$D$2:$D$401,RAW_Adset!$A$2:$A$401,"MH_003_BHKT_DL_BAU_ID_Card_VID_16Sep26_LS",RAW_Adset!$B$2:$B$401,"3") | E19: =IFERROR(SUMIFS(RAW_Adset!$D$2:$D$401,RAW_Adset!$A$2:$A$401,"MH_003_BHKT_DL_BAU_ID_Card_VID_16Sep26_LS",RAW_Adset!$B$2:$B$401,"3")/SUMIFS(RAW_Adset!$E$2:$E$401,RAW_Adset!$A$2:$A$401,"MH_003_BHKT_DL_BAU_ID_Card_VID_16Sep26_LS",RAW_Adset!$B$2:$B$401,"3"),"-") | F19: =IFERROR((SUMIFS(RAW_Adset!$D$2:$D$401,RAW_Adset!$A$2:$A$401,"MH_003_BHKT_DL_BAU_ID_Card_VID_16Sep26_LS",RAW_Adset!$B$2:$B$401,"3")/SUMIFS(RAW_Adset!$E$2:$E$401,RAW_Adset!$A$2:$A$401,"MH_003_BHKT_DL_BAU_ID_Card_VID_16Sep26_LS",RAW_Adset!$B$2:$B$401,"3"))/(SUMIFS(RAW_Adset!$D$2:$D$401,RAW_Adset!$A$2:$A$401,"MH_003_BHKT_DL_BAU_ID_Card_VID_16Sep26_LS",RAW_Adset!$B$2:$B$401,"2")/SUMIFS(RAW_Adset!$E$2:$E$401,RAW_Adset!$A$2:$A$401,"MH_003_BHKT_DL_BAU_ID_Card_VID_16Sep26_LS",RAW_Adset!$B$2:$B$401,"2"))-1,"-")
A20: MH_003_HI_BHKT_Hanuman_ID_Card_EXT_DL_BAU_VID_11Sep26_Parents_LS | B20: =SUMIFS(RAW_Adset!$D$2:$D$401,RAW_Adset!$A$2:$A$401,"MH_003_HI_BHKT_Hanuman_ID_Card_EXT_DL_BAU_VID_11Sep26_Parents_LS",RAW_Adset!$B$2:$B$401,"2") | C20: =IFERROR(SUMIFS(RAW_Adset!$D$2:$D$401,RAW_Adset!$A$2:$A$401,"MH_003_HI_BHKT_Hanuman_ID_Card_EXT_DL_BAU_VID_11Sep26_Parents_LS",RAW_Adset!$B$2:$B$401,"2")/SUMIFS(RAW_Adset!$E$2:$E$401,RAW_Adset!$A$2:$A$401,"MH_003_HI_BHKT_Hanuman_ID_Card_EXT_DL_BAU_VID_11Sep26_Parents_LS",RAW_Adset!$B$2:$B$401,"2"),"-") | D20: =SUMIFS(RAW_Adset!$D$2:$D$401,RAW_Adset!$A$2:$A$401,"MH_003_HI_BHKT_Hanuman_ID_Card_EXT_DL_BAU_VID_11Sep26_Parents_LS",RAW_Adset!$B$2:$B$401,"3") | E20: =IFERROR(SUMIFS(RAW_Adset!$D$2:$D$401,RAW_Adset!$A$2:$A$401,"MH_003_HI_BHKT_Hanuman_ID_Card_EXT_DL_BAU_VID_11Sep26_Parents_LS",RAW_Adset!$B$2:$B$401,"3")/SUMIFS(RAW_Adset!$E$2:$E$401,RAW_Adset!$A$2:$A$401,"MH_003_HI_BHKT_Hanuman_ID_Card_EXT_DL_BAU_VID_11Sep26_Parents_LS",RAW_Adset!$B$2:$B$401,"3"),"-") | F20: =IFERROR((SUMIFS(RAW_Adset!$D$2:$D$401,RAW_Adset!$A$2:$A$401,"MH_003_HI_BHKT_Hanuman_ID_Card_EXT_DL_BAU_VID_11Sep26_Parents_LS",RAW_Adset!$B$2:$B$401,"3")/SUMIFS(RAW_Adset!$E$2:$E$401,RAW_Adset!$A$2:$A$401,"MH_003_HI_BHKT_Hanuman_ID_Card_EXT_DL_BAU_VID_11Sep26_Parents_LS",RAW_Adset!$B$2:$B$401,"3"))/(SUMIFS(RAW_Adset!$D$2:$D$401,RAW_Adset!$A$2:$A$401,"MH_003_HI_BHKT_Hanuman_ID_Card_EXT_DL_BAU_VID_11Sep26_Parents_LS",RAW_Adset!$B$2:$B$401,"2")/SUMIFS(RAW_Adset!$E$2:$E$401,RAW_Adset!$A$2:$A$401,"MH_003_HI_BHKT_Hanuman_ID_Card_EXT_DL_BAU_VID_11Sep26_Parents_LS",RAW_Adset!$B$2:$B$401,"2"))-1,"-")
A21: TN_002_BHKT_DL_BAU_Murugan_2_VID_Aug14_LS | B21: =SUMIFS(RAW_Adset!$D$2:$D$401,RAW_Adset!$A$2:$A$401,"TN_002_BHKT_DL_BAU_Murugan_2_VID_Aug14_LS",RAW_Adset!$B$2:$B$401,"2") | C21: =IFERROR(SUMIFS(RAW_Adset!$D$2:$D$401,RAW_Adset!$A$2:$A$401,"TN_002_BHKT_DL_BAU_Murugan_2_VID_Aug14_LS",RAW_Adset!$B$2:$B$401,"2")/SUMIFS(RAW_Adset!$E$2:$E$401,RAW_Adset!$A$2:$A$401,"TN_002_BHKT_DL_BAU_Murugan_2_VID_Aug14_LS",RAW_Adset!$B$2:$B$401,"2"),"-") | D21: =SUMIFS(RAW_Adset!$D$2:$D$401,RAW_Adset!$A$2:$A$401,"TN_002_BHKT_DL_BAU_Murugan_2_VID_Aug14_LS",RAW_Adset!$B$2:$B$401,"3") | E21: =IFERROR(SUMIFS(RAW_Adset!$D$2:$D$401,RAW_Adset!$A$2:$A$401,"TN_002_BHKT_DL_BAU_Murugan_2_VID_Aug14_LS",RAW_Adset!$B$2:$B$401,"3")/SUMIFS(RAW_Adset!$E$2:$E$401,RAW_Adset!$A$2:$A$401,"TN_002_BHKT_DL_BAU_Murugan_2_VID_Aug14_LS",RAW_Adset!$B$2:$B$401,"3"),"-") | F21: =IFERROR((SUMIFS(RAW_Adset!$D$2:$D$401,RAW_Adset!$A$2:$A$401,"TN_002_BHKT_DL_BAU_Murugan_2_VID_Aug14_LS",RAW_Adset!$B$2:$B$401,"3")/SUMIFS(RAW_Adset!$E$2:$E$401,RAW_Adset!$A$2:$A$401,"TN_002_BHKT_DL_BAU_Murugan_2_VID_Aug14_LS",RAW_Adset!$B$2:$B$401,"3"))/(SUMIFS(RAW_Adset!$D$2:$D$401,RAW_Adset!$A$2:$A$401,"TN_002_BHKT_DL_BAU_Murugan_2_VID_Aug14_LS",RAW_Adset!$B$2:$B$401,"2")/SUMIFS(RAW_Adset!$E$2:$E$401,RAW_Adset!$A$2:$A$401,"TN_002_BHKT_DL_BAU_Murugan_2_VID_Aug14_LS",RAW_Adset!$B$2:$B$401,"2"))-1,"-")
A22: TE_001_BHKT_DL_AI Explainer_TE365 - TE368_VID_LS | B22: =SUMIFS(RAW_Adset!$D$2:$D$401,RAW_Adset!$A$2:$A$401,"TE_001_BHKT_DL_AI Explainer_TE365 - TE368_VID_LS",RAW_Adset!$B$2:$B$401,"2") | C22: =IFERROR(SUMIFS(RAW_Adset!$D$2:$D$401,RAW_Adset!$A$2:$A$401,"TE_001_BHKT_DL_AI Explainer_TE365 - TE368_VID_LS",RAW_Adset!$B$2:$B$401,"2")/SUMIFS(RAW_Adset!$E$2:$E$401,RAW_Adset!$A$2:$A$401,"TE_001_BHKT_DL_AI Explainer_TE365 - TE368_VID_LS",RAW_Adset!$B$2:$B$401,"2"),"-") | D22: =SUMIFS(RAW_Adset!$D$2:$D$401,RAW_Adset!$A$2:$A$401,"TE_001_BHKT_DL_AI Explainer_TE365 - TE368_VID_LS",RAW_Adset!$B$2:$B$401,"3") | E22: =IFERROR(SUMIFS(RAW_Adset!$D$2:$D$401,RAW_Adset!$A$2:$A$401,"TE_001_BHKT_DL_AI Explainer_TE365 - TE368_VID_LS",RAW_Adset!$B$2:$B$401,"3")/SUMIFS(RAW_Adset!$E$2:$E$401,RAW_Adset!$A$2:$A$401,"TE_001_BHKT_DL_AI Explainer_TE365 - TE368_VID_LS",RAW_Adset!$B$2:$B$401,"3"),"-") | F22: =IFERROR((SUMIFS(RAW_Adset!$D$2:$D$401,RAW_Adset!$A$2:$A$401,"TE_001_BHKT_DL_AI Explainer_TE365 - TE368_VID_LS",RAW_Adset!$B$2:$B$401,"3")/SUMIFS(RAW_Adset!$E$2:$E$401,RAW_Adset!$A$2:$A$401,"TE_001_BHKT_DL_AI Explainer_TE365 - TE368_VID_LS",RAW_Adset!$B$2:$B$401,"3"))/(SUMIFS(RAW_Adset!$D$2:$D$401,RAW_Adset!$A$2:$A$401,"TE_001_BHKT_DL_AI Explainer_TE365 - TE368_VID_LS",RAW_Adset!$B$2:$B$401,"2")/SUMIFS(RAW_Adset!$E$2:$E$401,RAW_Adset!$A$2:$A$401,"TE_001_BHKT_DL_AI Explainer_TE365 - TE368_VID_LS",RAW_Adset!$B$2:$B$401,"2"))-1,"-")
A23: HI_005_POL_DL_BAU_Panchayat_VID_Sep03_LS | B23: =SUMIFS(RAW_Adset!$D$2:$D$401,RAW_Adset!$A$2:$A$401,"HI_005_POL_DL_BAU_Panchayat_VID_Sep03_LS",RAW_Adset!$B$2:$B$401,"2") | C23: =IFERROR(SUMIFS(RAW_Adset!$D$2:$D$401,RAW_Adset!$A$2:$A$401,"HI_005_POL_DL_BAU_Panchayat_VID_Sep03_LS",RAW_Adset!$B$2:$B$401,"2")/SUMIFS(RAW_Adset!$E$2:$E$401,RAW_Adset!$A$2:$A$401,"HI_005_POL_DL_BAU_Panchayat_VID_Sep03_LS",RAW_Adset!$B$2:$B$401,"2"),"-") | D23: =SUMIFS(RAW_Adset!$D$2:$D$401,RAW_Adset!$A$2:$A$401,"HI_005_POL_DL_BAU_Panchayat_VID_Sep03_LS",RAW_Adset!$B$2:$B$401,"3") | E23: =IFERROR(SUMIFS(RAW_Adset!$D$2:$D$401,RAW_Adset!$A$2:$A$401,"HI_005_POL_DL_BAU_Panchayat_VID_Sep03_LS",RAW_Adset!$B$2:$B$401,"3")/SUMIFS(RAW_Adset!$E$2:$E$401,RAW_Adset!$A$2:$A$401,"HI_005_POL_DL_BAU_Panchayat_VID_Sep03_LS",RAW_Adset!$B$2:$B$401,"3"),"-") | F23: =IFERROR((SUMIFS(RAW_Adset!$D$2:$D$401,RAW_Adset!$A$2:$A$401,"HI_005_POL_DL_BAU_Panchayat_VID_Sep03_LS",RAW_Adset!$B$2:$B$401,"3")/SUMIFS(RAW_Adset!$E$2:$E$401,RAW_Adset!$A$2:$A$401,"HI_005_POL_DL_BAU_Panchayat_VID_Sep03_LS",RAW_Adset!$B$2:$B$401,"3"))/(SUMIFS(RAW_Adset!$D$2:$D$401,RAW_Adset!$A$2:$A$401,"HI_005_POL_DL_BAU_Panchayat_VID_Sep03_LS",RAW_Adset!$B$2:$B$401,"2")/SUMIFS(RAW_Adset!$E$2:$E$401,RAW_Adset!$A$2:$A$401,"HI_005_POL_DL_BAU_Panchayat_VID_Sep03_LS",RAW_Adset!$B$2:$B$401,"2"))-1,"-")
A24: HI_005_BHKT_BAU_DL_28Sep26_LS | B24: =SUMIFS(RAW_Adset!$D$2:$D$401,RAW_Adset!$A$2:$A$401,"HI_005_BHKT_BAU_DL_28Sep26_LS",RAW_Adset!$B$2:$B$401,"2") | C24: =IFERROR(SUMIFS(RAW_Adset!$D$2:$D$401,RAW_Adset!$A$2:$A$401,"HI_005_BHKT_BAU_DL_28Sep26_LS",RAW_Adset!$B$2:$B$401,"2")/SUMIFS(RAW_Adset!$E$2:$E$401,RAW_Adset!$A$2:$A$401,"HI_005_BHKT_BAU_DL_28Sep26_LS",RAW_Adset!$B$2:$B$401,"2"),"-") | D24: =SUMIFS(RAW_Adset!$D$2:$D$401,RAW_Adset!$A$2:$A$401,"HI_005_BHKT_BAU_DL_28Sep26_LS",RAW_Adset!$B$2:$B$401,"3") | E24: =IFERROR(SUMIFS(RAW_Adset!$D$2:$D$401,RAW_Adset!$A$2:$A$401,"HI_005_BHKT_BAU_DL_28Sep26_LS",RAW_Adset!$B$2:$B$401,"3")/SUMIFS(RAW_Adset!$E$2:$E$401,RAW_Adset!$A$2:$A$401,"HI_005_BHKT_BAU_DL_28Sep26_LS",RAW_Adset!$B$2:$B$401,"3"),"-") | F24: =IFERROR((SUMIFS(RAW_Adset!$D$2:$D$401,RAW_Adset!$A$2:$A$401,"HI_005_BHKT_BAU_DL_28Sep26_LS",RAW_Adset!$B$2:$B$401,"3")/SUMIFS(RAW_Adset!$E$2:$E$401,RAW_Adset!$A$2:$A$401,"HI_005_BHKT_BAU_DL_28Sep26_LS",RAW_Adset!$B$2:$B$401,"3"))/(SUMIFS(RAW_Adset!$D$2:$D$401,RAW_Adset!$A$2:$A$401,"HI_005_BHKT_BAU_DL_28Sep26_LS",RAW_Adset!$B$2:$B$401,"2")/SUMIFS(RAW_Adset!$E$2:$E$401,RAW_Adset!$A$2:$A$401,"HI_005_BHKT_BAU_DL_28Sep26_LS",RAW_Adset!$B$2:$B$401,"2"))-1,"-")
A25: TN_002_BHKT_DL_AI Explainer_3 samples_2_LS | B25: =SUMIFS(RAW_Adset!$D$2:$D$401,RAW_Adset!$A$2:$A$401,"TN_002_BHKT_DL_AI Explainer_3 samples_2_LS",RAW_Adset!$B$2:$B$401,"2") | C25: =IFERROR(SUMIFS(RAW_Adset!$D$2:$D$401,RAW_Adset!$A$2:$A$401,"TN_002_BHKT_DL_AI Explainer_3 samples_2_LS",RAW_Adset!$B$2:$B$401,"2")/SUMIFS(RAW_Adset!$E$2:$E$401,RAW_Adset!$A$2:$A$401,"TN_002_BHKT_DL_AI Explainer_3 samples_2_LS",RAW_Adset!$B$2:$B$401,"2"),"-") | D25: =SUMIFS(RAW_Adset!$D$2:$D$401,RAW_Adset!$A$2:$A$401,"TN_002_BHKT_DL_AI Explainer_3 samples_2_LS",RAW_Adset!$B$2:$B$401,"3") | E25: =IFERROR(SUMIFS(RAW_Adset!$D$2:$D$401,RAW_Adset!$A$2:$A$401,"TN_002_BHKT_DL_AI Explainer_3 samples_2_LS",RAW_Adset!$B$2:$B$401,"3")/SUMIFS(RAW_Adset!$E$2:$E$401,RAW_Adset!$A$2:$A$401,"TN_002_BHKT_DL_AI Explainer_3 samples_2_LS",RAW_Adset!$B$2:$B$401,"3"),"-") | F25: =IFERROR((SUMIFS(RAW_Adset!$D$2:$D$401,RAW_Adset!$A$2:$A$401,"TN_002_BHKT_DL_AI Explainer_3 samples_2_LS",RAW_Adset!$B$2:$B$401,"3")/SUMIFS(RAW_Adset!$E$2:$E$401,RAW_Adset!$A$2:$A$401,"TN_002_BHKT_DL_AI Explainer_3 samples_2_LS",RAW_Adset!$B$2:$B$401,"3"))/(SUMIFS(RAW_Adset!$D$2:$D$401,RAW_Adset!$A$2:$A$401,"TN_002_BHKT_DL_AI Explainer_3 samples_2_LS",RAW_Adset!$B$2:$B$401,"2")/SUMIFS(RAW_Adset!$E$2:$E$401,RAW_Adset!$A$2:$A$401,"TN_002_BHKT_DL_AI Explainer_3 samples_2_LS",RAW_Adset!$B$2:$B$401,"2"))-1,"-")
A26: HI_005_POL_VID_Cat_DL_BAU_LS_Yogi_BJP_VID_29Sep_LS | B26: =SUMIFS(RAW_Adset!$D$2:$D$401,RAW_Adset!$A$2:$A$401,"HI_005_POL_VID_Cat_DL_BAU_LS_Yogi_BJP_VID_29Sep_LS",RAW_Adset!$B$2:$B$401,"2") | C26: =IFERROR(SUMIFS(RAW_Adset!$D$2:$D$401,RAW_Adset!$A$2:$A$401,"HI_005_POL_VID_Cat_DL_BAU_LS_Yogi_BJP_VID_29Sep_LS",RAW_Adset!$B$2:$B$401,"2")/SUMIFS(RAW_Adset!$E$2:$E$401,RAW_Adset!$A$2:$A$401,"HI_005_POL_VID_Cat_DL_BAU_LS_Yogi_BJP_VID_29Sep_LS",RAW_Adset!$B$2:$B$401,"2"),"-") | D26: =SUMIFS(RAW_Adset!$D$2:$D$401,RAW_Adset!$A$2:$A$401,"HI_005_POL_VID_Cat_DL_BAU_LS_Yogi_BJP_VID_29Sep_LS",RAW_Adset!$B$2:$B$401,"3") | E26: =IFERROR(SUMIFS(RAW_Adset!$D$2:$D$401,RAW_Adset!$A$2:$A$401,"HI_005_POL_VID_Cat_DL_BAU_LS_Yogi_BJP_VID_29Sep_LS",RAW_Adset!$B$2:$B$401,"3")/SUMIFS(RAW_Adset!$E$2:$E$401,RAW_Adset!$A$2:$A$401,"HI_005_POL_VID_Cat_DL_BAU_LS_Yogi_BJP_VID_29Sep_LS",RAW_Adset!$B$2:$B$401,"3"),"-") | F26: =IFERROR((SUMIFS(RAW_Adset!$D$2:$D$401,RAW_Adset!$A$2:$A$401,"HI_005_POL_VID_Cat_DL_BAU_LS_Yogi_BJP_VID_29Sep_LS",RAW_Adset!$B$2:$B$401,"3")/SUMIFS(RAW_Adset!$E$2:$E$401,RAW_Adset!$A$2:$A$401,"HI_005_POL_VID_Cat_DL_BAU_LS_Yogi_BJP_VID_29Sep_LS",RAW_Adset!$B$2:$B$401,"3"))/(SUMIFS(RAW_Adset!$D$2:$D$401,RAW_Adset!$A$2:$A$401,"HI_005_POL_VID_Cat_DL_BAU_LS_Yogi_BJP_VID_29Sep_LS",RAW_Adset!$B$2:$B$401,"2")/SUMIFS(RAW_Adset!$E$2:$E$401,RAW_Adset!$A$2:$A$401,"HI_005_POL_VID_Cat_DL_BAU_LS_Yogi_BJP_VID_29Sep_LS",RAW_Adset!$B$2:$B$401,"2"))-1,"-")
A27: TN_002_BHKT_Murugan_DL_UGC_AI_VID_23Sep26_LS | B27: =SUMIFS(RAW_Adset!$D$2:$D$401,RAW_Adset!$A$2:$A$401,"TN_002_BHKT_Murugan_DL_UGC_AI_VID_23Sep26_LS",RAW_Adset!$B$2:$B$401,"2") | C27: =IFERROR(SUMIFS(RAW_Adset!$D$2:$D$401,RAW_Adset!$A$2:$A$401,"TN_002_BHKT_Murugan_DL_UGC_AI_VID_23Sep26_LS",RAW_Adset!$B$2:$B$401,"2")/SUMIFS(RAW_Adset!$E$2:$E$401,RAW_Adset!$A$2:$A$401,"TN_002_BHKT_Murugan_DL_UGC_AI_VID_23Sep26_LS",RAW_Adset!$B$2:$B$401,"2"),"-") | D27: =SUMIFS(RAW_Adset!$D$2:$D$401,RAW_Adset!$A$2:$A$401,"TN_002_BHKT_Murugan_DL_UGC_AI_VID_23Sep26_LS",RAW_Adset!$B$2:$B$401,"3") | E27: =IFERROR(SUMIFS(RAW_Adset!$D$2:$D$401,RAW_Adset!$A$2:$A$401,"TN_002_BHKT_Murugan_DL_UGC_AI_VID_23Sep26_LS",RAW_Adset!$B$2:$B$401,"3")/SUMIFS(RAW_Adset!$E$2:$E$401,RAW_Adset!$A$2:$A$401,"TN_002_BHKT_Murugan_DL_UGC_AI_VID_23Sep26_LS",RAW_Adset!$B$2:$B$401,"3"),"-") | F27: =IFERROR((SUMIFS(RAW_Adset!$D$2:$D$401,RAW_Adset!$A$2:$A$401,"TN_002_BHKT_Murugan_DL_UGC_AI_VID_23Sep26_LS",RAW_Adset!$B$2:$B$401,"3")/SUMIFS(RAW_Adset!$E$2:$E$401,RAW_Adset!$A$2:$A$401,"TN_002_BHKT_Murugan_DL_UGC_AI_VID_23Sep26_LS",RAW_Adset!$B$2:$B$401,"3"))/(SUMIFS(RAW_Adset!$D$2:$D$401,RAW_Adset!$A$2:$A$401,"TN_002_BHKT_Murugan_DL_UGC_AI_VID_23Sep26_LS",RAW_Adset!$B$2:$B$401,"2")/SUMIFS(RAW_Adset!$E$2:$E$401,RAW_Adset!$A$2:$A$401,"TN_002_BHKT_Murugan_DL_UGC_AI_VID_23Sep26_LS",RAW_Adset!$B$2:$B$401,"2"))-1,"-")
A28: HI_005_BHKT_Hanuman_DL_BAU_Testimonial_Small_Business_Owner_Facebook_Post_VID_22Sep26_LS | B28: =SUMIFS(RAW_Adset!$D$2:$D$401,RAW_Adset!$A$2:$A$401,"HI_005_BHKT_Hanuman_DL_BAU_Testimonial_Small_Business_Owner_Facebook_Post_VID_22Sep26_LS",RAW_Adset!$B$2:$B$401,"2") | C28: =IFERROR(SUMIFS(RAW_Adset!$D$2:$D$401,RAW_Adset!$A$2:$A$401,"HI_005_BHKT_Hanuman_DL_BAU_Testimonial_Small_Business_Owner_Facebook_Post_VID_22Sep26_LS",RAW_Adset!$B$2:$B$401,"2")/SUMIFS(RAW_Adset!$E$2:$E$401,RAW_Adset!$A$2:$A$401,"HI_005_BHKT_Hanuman_DL_BAU_Testimonial_Small_Business_Owner_Facebook_Post_VID_22Sep26_LS",RAW_Adset!$B$2:$B$401,"2"),"-") | D28: =SUMIFS(RAW_Adset!$D$2:$D$401,RAW_Adset!$A$2:$A$401,"HI_005_BHKT_Hanuman_DL_BAU_Testimonial_Small_Business_Owner_Facebook_Post_VID_22Sep26_LS",RAW_Adset!$B$2:$B$401,"3") | E28: =IFERROR(SUMIFS(RAW_Adset!$D$2:$D$401,RAW_Adset!$A$2:$A$401,"HI_005_BHKT_Hanuman_DL_BAU_Testimonial_Small_Business_Owner_Facebook_Post_VID_22Sep26_LS",RAW_Adset!$B$2:$B$401,"3")/SUMIFS(RAW_Adset!$E$2:$E$401,RAW_Adset!$A$2:$A$401,"HI_005_BHKT_Hanuman_DL_BAU_Testimonial_Small_Business_Owner_Facebook_Post_VID_22Sep26_LS",RAW_Adset!$B$2:$B$401,"3"),"-") | F28: =IFERROR((SUMIFS(RAW_Adset!$D$2:$D$401,RAW_Adset!$A$2:$A$401,"HI_005_BHKT_Hanuman_DL_BAU_Testimonial_Small_Business_Owner_Facebook_Post_VID_22Sep26_LS",RAW_Adset!$B$2:$B$401,"3")/SUMIFS(RAW_Adset!$E$2:$E$401,RAW_Adset!$A$2:$A$401,"HI_005_BHKT_Hanuman_DL_BAU_Testimonial_Small_Business_Owner_Facebook_Post_VID_22Sep26_LS",RAW_Adset!$B$2:$B$401,"3"))/(SUMIFS(RAW_Adset!$D$2:$D$401,RAW_Adset!$A$2:$A$401,"HI_005_BHKT_Hanuman_DL_BAU_Testimonial_Small_Business_Owner_Facebook_Post_VID_22Sep26_LS",RAW_Adset!$B$2:$B$401,"2")/SUMIFS(RAW_Adset!$E$2:$E$401,RAW_Adset!$A$2:$A$401,"HI_005_BHKT_Hanuman_DL_BAU_Testimonial_Small_Business_Owner_Facebook_Post_VID_22Sep26_LS",RAW_Adset!$B$2:$B$401,"2"))-1,"-")
A29: MH_003_BHKT_DL_BAU_Hanuman_ID_Card_VID_16Sep26_LS | B29: =SUMIFS(RAW_Adset!$D$2:$D$401,RAW_Adset!$A$2:$A$401,"MH_003_BHKT_DL_BAU_Hanuman_ID_Card_VID_16Sep26_LS",RAW_Adset!$B$2:$B$401,"2") | C29: =IFERROR(SUMIFS(RAW_Adset!$D$2:$D$401,RAW_Adset!$A$2:$A$401,"MH_003_BHKT_DL_BAU_Hanuman_ID_Card_VID_16Sep26_LS",RAW_Adset!$B$2:$B$401,"2")/SUMIFS(RAW_Adset!$E$2:$E$401,RAW_Adset!$A$2:$A$401,"MH_003_BHKT_DL_BAU_Hanuman_ID_Card_VID_16Sep26_LS",RAW_Adset!$B$2:$B$401,"2"),"-") | D29: =SUMIFS(RAW_Adset!$D$2:$D$401,RAW_Adset!$A$2:$A$401,"MH_003_BHKT_DL_BAU_Hanuman_ID_Card_VID_16Sep26_LS",RAW_Adset!$B$2:$B$401,"3") | E29: =IFERROR(SUMIFS(RAW_Adset!$D$2:$D$401,RAW_Adset!$A$2:$A$401,"MH_003_BHKT_DL_BAU_Hanuman_ID_Card_VID_16Sep26_LS",RAW_Adset!$B$2:$B$401,"3")/SUMIFS(RAW_Adset!$E$2:$E$401,RAW_Adset!$A$2:$A$401,"MH_003_BHKT_DL_BAU_Hanuman_ID_Card_VID_16Sep26_LS",RAW_Adset!$B$2:$B$401,"3"),"-") | F29: =IFERROR((SUMIFS(RAW_Adset!$D$2:$D$401,RAW_Adset!$A$2:$A$401,"MH_003_BHKT_DL_BAU_Hanuman_ID_Card_VID_16Sep26_LS",RAW_Adset!$B$2:$B$401,"3")/SUMIFS(RAW_Adset!$E$2:$E$401,RAW_Adset!$A$2:$A$401,"MH_003_BHKT_DL_BAU_Hanuman_ID_Card_VID_16Sep26_LS",RAW_Adset!$B$2:$B$401,"3"))/(SUMIFS(RAW_Adset!$D$2:$D$401,RAW_Adset!$A$2:$A$401,"MH_003_BHKT_DL_BAU_Hanuman_ID_Card_VID_16Sep26_LS",RAW_Adset!$B$2:$B$401,"2")/SUMIFS(RAW_Adset!$E$2:$E$401,RAW_Adset!$A$2:$A$401,"MH_003_BHKT_DL_BAU_Hanuman_ID_Card_VID_16Sep26_LS",RAW_Adset!$B$2:$B$401,"2"))-1,"-")
A30: TN_002_BHKT_Murugan_DL_BAU_VID_Sep22_1_LS | B30: =SUMIFS(RAW_Adset!$D$2:$D$401,RAW_Adset!$A$2:$A$401,"TN_002_BHKT_Murugan_DL_BAU_VID_Sep22_1_LS",RAW_Adset!$B$2:$B$401,"2") | C30: =IFERROR(SUMIFS(RAW_Adset!$D$2:$D$401,RAW_Adset!$A$2:$A$401,"TN_002_BHKT_Murugan_DL_BAU_VID_Sep22_1_LS",RAW_Adset!$B$2:$B$401,"2")/SUMIFS(RAW_Adset!$E$2:$E$401,RAW_Adset!$A$2:$A$401,"TN_002_BHKT_Murugan_DL_BAU_VID_Sep22_1_LS",RAW_Adset!$B$2:$B$401,"2"),"-") | D30: =SUMIFS(RAW_Adset!$D$2:$D$401,RAW_Adset!$A$2:$A$401,"TN_002_BHKT_Murugan_DL_BAU_VID_Sep22_1_LS",RAW_Adset!$B$2:$B$401,"3") | E30: =IFERROR(SUMIFS(RAW_Adset!$D$2:$D$401,RAW_Adset!$A$2:$A$401,"TN_002_BHKT_Murugan_DL_BAU_VID_Sep22_1_LS",RAW_Adset!$B$2:$B$401,"3")/SUMIFS(RAW_Adset!$E$2:$E$401,RAW_Adset!$A$2:$A$401,"TN_002_BHKT_Murugan_DL_BAU_VID_Sep22_1_LS",RAW_Adset!$B$2:$B$401,"3"),"-") | F30: =IFERROR((SUMIFS(RAW_Adset!$D$2:$D$401,RAW_Adset!$A$2:$A$401,"TN_002_BHKT_Murugan_DL_BAU_VID_Sep22_1_LS",RAW_Adset!$B$2:$B$401,"3")/SUMIFS(RAW_Adset!$E$2:$E$401,RAW_Adset!$A$2:$A$401,"TN_002_BHKT_Murugan_DL_BAU_VID_Sep22_1_LS",RAW_Adset!$B$2:$B$401,"3"))/(SUMIFS(RAW_Adset!$D$2:$D$401,RAW_Adset!$A$2:$A$401,"TN_002_BHKT_Murugan_DL_BAU_VID_Sep22_1_LS",RAW_Adset!$B$2:$B$401,"2")/SUMIFS(RAW_Adset!$E$2:$E$401,RAW_Adset!$A$2:$A$401,"TN_002_BHKT_Murugan_DL_BAU_VID_Sep22_1_LS",RAW_Adset!$B$2:$B$401,"2"))-1,"-")
A31: HI_005_POL_VID_Cat_DL_BAU_IDCard_BJP_Modi_Parivar_VID_28Aug_LS | B31: =SUMIFS(RAW_Adset!$D$2:$D$401,RAW_Adset!$A$2:$A$401,"HI_005_POL_VID_Cat_DL_BAU_IDCard_BJP_Modi_Parivar_VID_28Aug_LS",RAW_Adset!$B$2:$B$401,"2") | C31: =IFERROR(SUMIFS(RAW_Adset!$D$2:$D$401,RAW_Adset!$A$2:$A$401,"HI_005_POL_VID_Cat_DL_BAU_IDCard_BJP_Modi_Parivar_VID_28Aug_LS",RAW_Adset!$B$2:$B$401,"2")/SUMIFS(RAW_Adset!$E$2:$E$401,RAW_Adset!$A$2:$A$401,"HI_005_POL_VID_Cat_DL_BAU_IDCard_BJP_Modi_Parivar_VID_28Aug_LS",RAW_Adset!$B$2:$B$401,"2"),"-") | D31: =SUMIFS(RAW_Adset!$D$2:$D$401,RAW_Adset!$A$2:$A$401,"HI_005_POL_VID_Cat_DL_BAU_IDCard_BJP_Modi_Parivar_VID_28Aug_LS",RAW_Adset!$B$2:$B$401,"3") | E31: =IFERROR(SUMIFS(RAW_Adset!$D$2:$D$401,RAW_Adset!$A$2:$A$401,"HI_005_POL_VID_Cat_DL_BAU_IDCard_BJP_Modi_Parivar_VID_28Aug_LS",RAW_Adset!$B$2:$B$401,"3")/SUMIFS(RAW_Adset!$E$2:$E$401,RAW_Adset!$A$2:$A$401,"HI_005_POL_VID_Cat_DL_BAU_IDCard_BJP_Modi_Parivar_VID_28Aug_LS",RAW_Adset!$B$2:$B$401,"3"),"-") | F31: =IFERROR((SUMIFS(RAW_Adset!$D$2:$D$401,RAW_Adset!$A$2:$A$401,"HI_005_POL_VID_Cat_DL_BAU_IDCard_BJP_Modi_Parivar_VID_28Aug_LS",RAW_Adset!$B$2:$B$401,"3")/SUMIFS(RAW_Adset!$E$2:$E$401,RAW_Adset!$A$2:$A$401,"HI_005_POL_VID_Cat_DL_BAU_IDCard_BJP_Modi_Parivar_VID_28Aug_LS",RAW_Adset!$B$2:$B$401,"3"))/(SUMIFS(RAW_Adset!$D$2:$D$401,RAW_Adset!$A$2:$A$401,"HI_005_POL_VID_Cat_DL_BAU_IDCard_BJP_Modi_Parivar_VID_28Aug_LS",RAW_Adset!$B$2:$B$401,"2")/SUMIFS(RAW_Adset!$E$2:$E$401,RAW_Adset!$A$2:$A$401,"HI_005_POL_VID_Cat_DL_BAU_IDCard_BJP_Modi_Parivar_VID_28Aug_LS",RAW_Adset!$B$2:$B$401,"2"))-1,"-")
A32: HI_005_BHKT_Hanuman_DL_BAU_IMG_VID_Sep04_2_LS | B32: =SUMIFS(RAW_Adset!$D$2:$D$401,RAW_Adset!$A$2:$A$401,"HI_005_BHKT_Hanuman_DL_BAU_IMG_VID_Sep04_2_LS",RAW_Adset!$B$2:$B$401,"2") | C32: =IFERROR(SUMIFS(RAW_Adset!$D$2:$D$401,RAW_Adset!$A$2:$A$401,"HI_005_BHKT_Hanuman_DL_BAU_IMG_VID_Sep04_2_LS",RAW_Adset!$B$2:$B$401,"2")/SUMIFS(RAW_Adset!$E$2:$E$401,RAW_Adset!$A$2:$A$401,"HI_005_BHKT_Hanuman_DL_BAU_IMG_VID_Sep04_2_LS",RAW_Adset!$B$2:$B$401,"2"),"-") | D32: =SUMIFS(RAW_Adset!$D$2:$D$401,RAW_Adset!$A$2:$A$401,"HI_005_BHKT_Hanuman_DL_BAU_IMG_VID_Sep04_2_LS",RAW_Adset!$B$2:$B$401,"3") | E32: =IFERROR(SUMIFS(RAW_Adset!$D$2:$D$401,RAW_Adset!$A$2:$A$401,"HI_005_BHKT_Hanuman_DL_BAU_IMG_VID_Sep04_2_LS",RAW_Adset!$B$2:$B$401,"3")/SUMIFS(RAW_Adset!$E$2:$E$401,RAW_Adset!$A$2:$A$401,"HI_005_BHKT_Hanuman_DL_BAU_IMG_VID_Sep04_2_LS",RAW_Adset!$B$2:$B$401,"3"),"-") | F32: =IFERROR((SUMIFS(RAW_Adset!$D$2:$D$401,RAW_Adset!$A$2:$A$401,"HI_005_BHKT_Hanuman_DL_BAU_IMG_VID_Sep04_2_LS",RAW_Adset!$B$2:$B$401,"3")/SUMIFS(RAW_Adset!$E$2:$E$401,RAW_Adset!$A$2:$A$401,"HI_005_BHKT_Hanuman_DL_BAU_IMG_VID_Sep04_2_LS",RAW_Adset!$B$2:$B$401,"3"))/(SUMIFS(RAW_Adset!$D$2:$D$401,RAW_Adset!$A$2:$A$401,"HI_005_BHKT_Hanuman_DL_BAU_IMG_VID_Sep04_2_LS",RAW_Adset!$B$2:$B$401,"2")/SUMIFS(RAW_Adset!$E$2:$E$401,RAW_Adset!$A$2:$A$401,"HI_005_BHKT_Hanuman_DL_BAU_IMG_VID_Sep04_2_LS",RAW_Adset!$B$2:$B$401,"2"))-1,"-")
A33: TN_002_BHKT_Murugan_DL_UGC_AI_Money_Career_VID_26Sep26_LS | B33: =SUMIFS(RAW_Adset!$D$2:$D$401,RAW_Adset!$A$2:$A$401,"TN_002_BHKT_Murugan_DL_UGC_AI_Money_Career_VID_26Sep26_LS",RAW_Adset!$B$2:$B$401,"2") | C33: =IFERROR(SUMIFS(RAW_Adset!$D$2:$D$401,RAW_Adset!$A$2:$A$401,"TN_002_BHKT_Murugan_DL_UGC_AI_Money_Career_VID_26Sep26_LS",RAW_Adset!$B$2:$B$401,"2")/SUMIFS(RAW_Adset!$E$2:$E$401,RAW_Adset!$A$2:$A$401,"TN_002_BHKT_Murugan_DL_UGC_AI_Money_Career_VID_26Sep26_LS",RAW_Adset!$B$2:$B$401,"2"),"-") | D33: =SUMIFS(RAW_Adset!$D$2:$D$401,RAW_Adset!$A$2:$A$401,"TN_002_BHKT_Murugan_DL_UGC_AI_Money_Career_VID_26Sep26_LS",RAW_Adset!$B$2:$B$401,"3") | E33: =IFERROR(SUMIFS(RAW_Adset!$D$2:$D$401,RAW_Adset!$A$2:$A$401,"TN_002_BHKT_Murugan_DL_UGC_AI_Money_Career_VID_26Sep26_LS",RAW_Adset!$B$2:$B$401,"3")/SUMIFS(RAW_Adset!$E$2:$E$401,RAW_Adset!$A$2:$A$401,"TN_002_BHKT_Murugan_DL_UGC_AI_Money_Career_VID_26Sep26_LS",RAW_Adset!$B$2:$B$401,"3"),"-") | F33: =IFERROR((SUMIFS(RAW_Adset!$D$2:$D$401,RAW_Adset!$A$2:$A$401,"TN_002_BHKT_Murugan_DL_UGC_AI_Money_Career_VID_26Sep26_LS",RAW_Adset!$B$2:$B$401,"3")/SUMIFS(RAW_Adset!$E$2:$E$401,RAW_Adset!$A$2:$A$401,"TN_002_BHKT_Murugan_DL_UGC_AI_Money_Career_VID_26Sep26_LS",RAW_Adset!$B$2:$B$401,"3"))/(SUMIFS(RAW_Adset!$D$2:$D$401,RAW_Adset!$A$2:$A$401,"TN_002_BHKT_Murugan_DL_UGC_AI_Money_Career_VID_26Sep26_LS",RAW_Adset!$B$2:$B$401,"2")/SUMIFS(RAW_Adset!$E$2:$E$401,RAW_Adset!$A$2:$A$401,"TN_002_BHKT_Murugan_DL_UGC_AI_Money_Career_VID_26Sep26_LS",RAW_Adset!$B$2:$B$401,"2"))-1,"-") | G33: Yes
A34: HI_005_BHKT_Hanuman_NDL_VOX_POP_VID_Aug24_LS | B34: =SUMIFS(RAW_Adset!$D$2:$D$401,RAW_Adset!$A$2:$A$401,"HI_005_BHKT_Hanuman_NDL_VOX_POP_VID_Aug24_LS",RAW_Adset!$B$2:$B$401,"2") | C34: =IFERROR(SUMIFS(RAW_Adset!$D$2:$D$401,RAW_Adset!$A$2:$A$401,"HI_005_BHKT_Hanuman_NDL_VOX_POP_VID_Aug24_LS",RAW_Adset!$B$2:$B$401,"2")/SUMIFS(RAW_Adset!$E$2:$E$401,RAW_Adset!$A$2:$A$401,"HI_005_BHKT_Hanuman_NDL_VOX_POP_VID_Aug24_LS",RAW_Adset!$B$2:$B$401,"2"),"-") | D34: =SUMIFS(RAW_Adset!$D$2:$D$401,RAW_Adset!$A$2:$A$401,"HI_005_BHKT_Hanuman_NDL_VOX_POP_VID_Aug24_LS",RAW_Adset!$B$2:$B$401,"3") | E34: =IFERROR(SUMIFS(RAW_Adset!$D$2:$D$401,RAW_Adset!$A$2:$A$401,"HI_005_BHKT_Hanuman_NDL_VOX_POP_VID_Aug24_LS",RAW_Adset!$B$2:$B$401,"3")/SUMIFS(RAW_Adset!$E$2:$E$401,RAW_Adset!$A$2:$A$401,"HI_005_BHKT_Hanuman_NDL_VOX_POP_VID_Aug24_LS",RAW_Adset!$B$2:$B$401,"3"),"-") | F34: =IFERROR((SUMIFS(RAW_Adset!$D$2:$D$401,RAW_Adset!$A$2:$A$401,"HI_005_BHKT_Hanuman_NDL_VOX_POP_VID_Aug24_LS",RAW_Adset!$B$2:$B$401,"3")/SUMIFS(RAW_Adset!$E$2:$E$401,RAW_Adset!$A$2:$A$401,"HI_005_BHKT_Hanuman_NDL_VOX_POP_VID_Aug24_LS",RAW_Adset!$B$2:$B$401,"3"))/(SUMIFS(RAW_Adset!$D$2:$D$401,RAW_Adset!$A$2:$A$401,"HI_005_BHKT_Hanuman_NDL_VOX_POP_VID_Aug24_LS",RAW_Adset!$B$2:$B$401,"2")/SUMIFS(RAW_Adset!$E$2:$E$401,RAW_Adset!$A$2:$A$401,"HI_005_BHKT_Hanuman_NDL_VOX_POP_VID_Aug24_LS",RAW_Adset!$B$2:$B$401,"2"))-1,"-")
A35: MH_003_BHKT_MIX_T2_DL_CL_EXT_002_LS | B35: =SUMIFS(RAW_Adset!$D$2:$D$401,RAW_Adset!$A$2:$A$401,"MH_003_BHKT_MIX_T2_DL_CL_EXT_002_LS",RAW_Adset!$B$2:$B$401,"2") | C35: =IFERROR(SUMIFS(RAW_Adset!$D$2:$D$401,RAW_Adset!$A$2:$A$401,"MH_003_BHKT_MIX_T2_DL_CL_EXT_002_LS",RAW_Adset!$B$2:$B$401,"2")/SUMIFS(RAW_Adset!$E$2:$E$401,RAW_Adset!$A$2:$A$401,"MH_003_BHKT_MIX_T2_DL_CL_EXT_002_LS",RAW_Adset!$B$2:$B$401,"2"),"-") | D35: =SUMIFS(RAW_Adset!$D$2:$D$401,RAW_Adset!$A$2:$A$401,"MH_003_BHKT_MIX_T2_DL_CL_EXT_002_LS",RAW_Adset!$B$2:$B$401,"3") | E35: =IFERROR(SUMIFS(RAW_Adset!$D$2:$D$401,RAW_Adset!$A$2:$A$401,"MH_003_BHKT_MIX_T2_DL_CL_EXT_002_LS",RAW_Adset!$B$2:$B$401,"3")/SUMIFS(RAW_Adset!$E$2:$E$401,RAW_Adset!$A$2:$A$401,"MH_003_BHKT_MIX_T2_DL_CL_EXT_002_LS",RAW_Adset!$B$2:$B$401,"3"),"-") | F35: =IFERROR((SUMIFS(RAW_Adset!$D$2:$D$401,RAW_Adset!$A$2:$A$401,"MH_003_BHKT_MIX_T2_DL_CL_EXT_002_LS",RAW_Adset!$B$2:$B$401,"3")/SUMIFS(RAW_Adset!$E$2:$E$401,RAW_Adset!$A$2:$A$401,"MH_003_BHKT_MIX_T2_DL_CL_EXT_002_LS",RAW_Adset!$B$2:$B$401,"3"))/(SUMIFS(RAW_Adset!$D$2:$D$401,RAW_Adset!$A$2:$A$401,"MH_003_BHKT_MIX_T2_DL_CL_EXT_002_LS",RAW_Adset!$B$2:$B$401,"2")/SUMIFS(RAW_Adset!$E$2:$E$401,RAW_Adset!$A$2:$A$401,"MH_003_BHKT_MIX_T2_DL_CL_EXT_002_LS",RAW_Adset!$B$2:$B$401,"2"))-1,"-")
A36: TE_001_BHKT_DL_background_vo_TE373 - TE375_VID_LS | B36: =SUMIFS(RAW_Adset!$D$2:$D$401,RAW_Adset!$A$2:$A$401,"TE_001_BHKT_DL_background_vo_TE373 - TE375_VID_LS",RAW_Adset!$B$2:$B$401,"2") | C36: =IFERROR(SUMIFS(RAW_Adset!$D$2:$D$401,RAW_Adset!$A$2:$A$401,"TE_001_BHKT_DL_background_vo_TE373 - TE375_VID_LS",RAW_Adset!$B$2:$B$401,"2")/SUMIFS(RAW_Adset!$E$2:$E$401,RAW_Adset!$A$2:$A$401,"TE_001_BHKT_DL_background_vo_TE373 - TE375_VID_LS",RAW_Adset!$B$2:$B$401,"2"),"-") | D36: =SUMIFS(RAW_Adset!$D$2:$D$401,RAW_Adset!$A$2:$A$401,"TE_001_BHKT_DL_background_vo_TE373 - TE375_VID_LS",RAW_Adset!$B$2:$B$401,"3") | E36: =IFERROR(SUMIFS(RAW_Adset!$D$2:$D$401,RAW_Adset!$A$2:$A$401,"TE_001_BHKT_DL_background_vo_TE373 - TE375_VID_LS",RAW_Adset!$B$2:$B$401,"3")/SUMIFS(RAW_Adset!$E$2:$E$401,RAW_Adset!$A$2:$A$401,"TE_001_BHKT_DL_background_vo_TE373 - TE375_VID_LS",RAW_Adset!$B$2:$B$401,"3"),"-") | F36: =IFERROR((SUMIFS(RAW_Adset!$D$2:$D$401,RAW_Adset!$A$2:$A$401,"TE_001_BHKT_DL_background_vo_TE373 - TE375_VID_LS",RAW_Adset!$B$2:$B$401,"3")/SUMIFS(RAW_Adset!$E$2:$E$401,RAW_Adset!$A$2:$A$401,"TE_001_BHKT_DL_background_vo_TE373 - TE375_VID_LS",RAW_Adset!$B$2:$B$401,"3"))/(SUMIFS(RAW_Adset!$D$2:$D$401,RAW_Adset!$A$2:$A$401,"TE_001_BHKT_DL_background_vo_TE373 - TE375_VID_LS",RAW_Adset!$B$2:$B$401,"2")/SUMIFS(RAW_Adset!$E$2:$E$401,RAW_Adset!$A$2:$A$401,"TE_001_BHKT_DL_background_vo_TE373 - TE375_VID_LS",RAW_Adset!$B$2:$B$401,"2"))-1,"-")
A37: TN_002_BHKT_Murugan_DL_Winners_TN070_B1354_B1355_B1357_VID_27Sep26_LS | B37: =SUMIFS(RAW_Adset!$D$2:$D$401,RAW_Adset!$A$2:$A$401,"TN_002_BHKT_Murugan_DL_Winners_TN070_B1354_B1355_B1357_VID_27Sep26_LS",RAW_Adset!$B$2:$B$401,"2") | C37: =IFERROR(SUMIFS(RAW_Adset!$D$2:$D$401,RAW_Adset!$A$2:$A$401,"TN_002_BHKT_Murugan_DL_Winners_TN070_B1354_B1355_B1357_VID_27Sep26_LS",RAW_Adset!$B$2:$B$401,"2")/SUMIFS(RAW_Adset!$E$2:$E$401,RAW_Adset!$A$2:$A$401,"TN_002_BHKT_Murugan_DL_Winners_TN070_B1354_B1355_B1357_VID_27Sep26_LS",RAW_Adset!$B$2:$B$401,"2"),"-") | D37: =SUMIFS(RAW_Adset!$D$2:$D$401,RAW_Adset!$A$2:$A$401,"TN_002_BHKT_Murugan_DL_Winners_TN070_B1354_B1355_B1357_VID_27Sep26_LS",RAW_Adset!$B$2:$B$401,"3") | E37: =IFERROR(SUMIFS(RAW_Adset!$D$2:$D$401,RAW_Adset!$A$2:$A$401,"TN_002_BHKT_Murugan_DL_Winners_TN070_B1354_B1355_B1357_VID_27Sep26_LS",RAW_Adset!$B$2:$B$401,"3")/SUMIFS(RAW_Adset!$E$2:$E$401,RAW_Adset!$A$2:$A$401,"TN_002_BHKT_Murugan_DL_Winners_TN070_B1354_B1355_B1357_VID_27Sep26_LS",RAW_Adset!$B$2:$B$401,"3"),"-") | F37: =IFERROR((SUMIFS(RAW_Adset!$D$2:$D$401,RAW_Adset!$A$2:$A$401,"TN_002_BHKT_Murugan_DL_Winners_TN070_B1354_B1355_B1357_VID_27Sep26_LS",RAW_Adset!$B$2:$B$401,"3")/SUMIFS(RAW_Adset!$E$2:$E$401,RAW_Adset!$A$2:$A$401,"TN_002_BHKT_Murugan_DL_Winners_TN070_B1354_B1355_B1357_VID_27Sep26_LS",RAW_Adset!$B$2:$B$401,"3"))/(SUMIFS(RAW_Adset!$D$2:$D$401,RAW_Adset!$A$2:$A$401,"TN_002_BHKT_Murugan_DL_Winners_TN070_B1354_B1355_B1357_VID_27Sep26_LS",RAW_Adset!$B$2:$B$401,"2")/SUMIFS(RAW_Adset!$E$2:$E$401,RAW_Adset!$A$2:$A$401,"TN_002_BHKT_Murugan_DL_Winners_TN070_B1354_B1355_B1357_VID_27Sep26_LS",RAW_Adset!$B$2:$B$401,"2"))-1,"-")
A38: MH_003_BHKT_Poster_DL_BAU_VID_21Aug26_1_LS | B38: =SUMIFS(RAW_Adset!$D$2:$D$401,RAW_Adset!$A$2:$A$401,"MH_003_BHKT_Poster_DL_BAU_VID_21Aug26_1_LS",RAW_Adset!$B$2:$B$401,"2") | C38: =IFERROR(SUMIFS(RAW_Adset!$D$2:$D$401,RAW_Adset!$A$2:$A$401,"MH_003_BHKT_Poster_DL_BAU_VID_21Aug26_1_LS",RAW_Adset!$B$2:$B$401,"2")/SUMIFS(RAW_Adset!$E$2:$E$401,RAW_Adset!$A$2:$A$401,"MH_003_BHKT_Poster_DL_BAU_VID_21Aug26_1_LS",RAW_Adset!$B$2:$B$401,"2"),"-") | D38: =SUMIFS(RAW_Adset!$D$2:$D$401,RAW_Adset!$A$2:$A$401,"MH_003_BHKT_Poster_DL_BAU_VID_21Aug26_1_LS",RAW_Adset!$B$2:$B$401,"3") | E38: =IFERROR(SUMIFS(RAW_Adset!$D$2:$D$401,RAW_Adset!$A$2:$A$401,"MH_003_BHKT_Poster_DL_BAU_VID_21Aug26_1_LS",RAW_Adset!$B$2:$B$401,"3")/SUMIFS(RAW_Adset!$E$2:$E$401,RAW_Adset!$A$2:$A$401,"MH_003_BHKT_Poster_DL_BAU_VID_21Aug26_1_LS",RAW_Adset!$B$2:$B$401,"3"),"-") | F38: =IFERROR((SUMIFS(RAW_Adset!$D$2:$D$401,RAW_Adset!$A$2:$A$401,"MH_003_BHKT_Poster_DL_BAU_VID_21Aug26_1_LS",RAW_Adset!$B$2:$B$401,"3")/SUMIFS(RAW_Adset!$E$2:$E$401,RAW_Adset!$A$2:$A$401,"MH_003_BHKT_Poster_DL_BAU_VID_21Aug26_1_LS",RAW_Adset!$B$2:$B$401,"3"))/(SUMIFS(RAW_Adset!$D$2:$D$401,RAW_Adset!$A$2:$A$401,"MH_003_BHKT_Poster_DL_BAU_VID_21Aug26_1_LS",RAW_Adset!$B$2:$B$401,"2")/SUMIFS(RAW_Adset!$E$2:$E$401,RAW_Adset!$A$2:$A$401,"MH_003_BHKT_Poster_DL_BAU_VID_21Aug26_1_LS",RAW_Adset!$B$2:$B$401,"2"))-1,"-")
A39: HI_005_POL_VID_Hanuman_Cat_DL_BAU_BJP_Hanuman_VID_15Sep_LS | B39: =SUMIFS(RAW_Adset!$D$2:$D$401,RAW_Adset!$A$2:$A$401,"HI_005_POL_VID_Hanuman_Cat_DL_BAU_BJP_Hanuman_VID_15Sep_LS",RAW_Adset!$B$2:$B$401,"2") | C39: =IFERROR(SUMIFS(RAW_Adset!$D$2:$D$401,RAW_Adset!$A$2:$A$401,"HI_005_POL_VID_Hanuman_Cat_DL_BAU_BJP_Hanuman_VID_15Sep_LS",RAW_Adset!$B$2:$B$401,"2")/SUMIFS(RAW_Adset!$E$2:$E$401,RAW_Adset!$A$2:$A$401,"HI_005_POL_VID_Hanuman_Cat_DL_BAU_BJP_Hanuman_VID_15Sep_LS",RAW_Adset!$B$2:$B$401,"2"),"-") | D39: =SUMIFS(RAW_Adset!$D$2:$D$401,RAW_Adset!$A$2:$A$401,"HI_005_POL_VID_Hanuman_Cat_DL_BAU_BJP_Hanuman_VID_15Sep_LS",RAW_Adset!$B$2:$B$401,"3") | E39: =IFERROR(SUMIFS(RAW_Adset!$D$2:$D$401,RAW_Adset!$A$2:$A$401,"HI_005_POL_VID_Hanuman_Cat_DL_BAU_BJP_Hanuman_VID_15Sep_LS",RAW_Adset!$B$2:$B$401,"3")/SUMIFS(RAW_Adset!$E$2:$E$401,RAW_Adset!$A$2:$A$401,"HI_005_POL_VID_Hanuman_Cat_DL_BAU_BJP_Hanuman_VID_15Sep_LS",RAW_Adset!$B$2:$B$401,"3"),"-") | F39: =IFERROR((SUMIFS(RAW_Adset!$D$2:$D$401,RAW_Adset!$A$2:$A$401,"HI_005_POL_VID_Hanuman_Cat_DL_BAU_BJP_Hanuman_VID_15Sep_LS",RAW_Adset!$B$2:$B$401,"3")/SUMIFS(RAW_Adset!$E$2:$E$401,RAW_Adset!$A$2:$A$401,"HI_005_POL_VID_Hanuman_Cat_DL_BAU_BJP_Hanuman_VID_15Sep_LS",RAW_Adset!$B$2:$B$401,"3"))/(SUMIFS(RAW_Adset!$D$2:$D$401,RAW_Adset!$A$2:$A$401,"HI_005_POL_VID_Hanuman_Cat_DL_BAU_BJP_Hanuman_VID_15Sep_LS",RAW_Adset!$B$2:$B$401,"2")/SUMIFS(RAW_Adset!$E$2:$E$401,RAW_Adset!$A$2:$A$401,"HI_005_POL_VID_Hanuman_Cat_DL_BAU_BJP_Hanuman_VID_15Sep_LS",RAW_Adset!$B$2:$B$401,"2"))-1,"-")
A40: MH_003_HI_BHKT_Hanuman_DL_Flexi_VID_Aug30_LS | B40: =SUMIFS(RAW_Adset!$D$2:$D$401,RAW_Adset!$A$2:$A$401,"MH_003_HI_BHKT_Hanuman_DL_Flexi_VID_Aug30_LS",RAW_Adset!$B$2:$B$401,"2") | C40: =IFERROR(SUMIFS(RAW_Adset!$D$2:$D$401,RAW_Adset!$A$2:$A$401,"MH_003_HI_BHKT_Hanuman_DL_Flexi_VID_Aug30_LS",RAW_Adset!$B$2:$B$401,"2")/SUMIFS(RAW_Adset!$E$2:$E$401,RAW_Adset!$A$2:$A$401,"MH_003_HI_BHKT_Hanuman_DL_Flexi_VID_Aug30_LS",RAW_Adset!$B$2:$B$401,"2"),"-") | D40: =SUMIFS(RAW_Adset!$D$2:$D$401,RAW_Adset!$A$2:$A$401,"MH_003_HI_BHKT_Hanuman_DL_Flexi_VID_Aug30_LS",RAW_Adset!$B$2:$B$401,"3") | E40: =IFERROR(SUMIFS(RAW_Adset!$D$2:$D$401,RAW_Adset!$A$2:$A$401,"MH_003_HI_BHKT_Hanuman_DL_Flexi_VID_Aug30_LS",RAW_Adset!$B$2:$B$401,"3")/SUMIFS(RAW_Adset!$E$2:$E$401,RAW_Adset!$A$2:$A$401,"MH_003_HI_BHKT_Hanuman_DL_Flexi_VID_Aug30_LS",RAW_Adset!$B$2:$B$401,"3"),"-") | F40: =IFERROR((SUMIFS(RAW_Adset!$D$2:$D$401,RAW_Adset!$A$2:$A$401,"MH_003_HI_BHKT_Hanuman_DL_Flexi_VID_Aug30_LS",RAW_Adset!$B$2:$B$401,"3")/SUMIFS(RAW_Adset!$E$2:$E$401,RAW_Adset!$A$2:$A$401,"MH_003_HI_BHKT_Hanuman_DL_Flexi_VID_Aug30_LS",RAW_Adset!$B$2:$B$401,"3"))/(SUMIFS(RAW_Adset!$D$2:$D$401,RAW_Adset!$A$2:$A$401,"MH_003_HI_BHKT_Hanuman_DL_Flexi_VID_Aug30_LS",RAW_Adset!$B$2:$B$401,"2")/SUMIFS(RAW_Adset!$E$2:$E$401,RAW_Adset!$A$2:$A$401,"MH_003_HI_BHKT_Hanuman_DL_Flexi_VID_Aug30_LS",RAW_Adset!$B$2:$B$401,"2"))-1,"-")
A41: HI_005_BHKT_Hanuman_DL_BAU_Sep04_2_Daypart_No2to5PM_Scheduled_VID_28Sep26_LS | B41: =SUMIFS(RAW_Adset!$D$2:$D$401,RAW_Adset!$A$2:$A$401,"HI_005_BHKT_Hanuman_DL_BAU_Sep04_2_Daypart_No2to5PM_Scheduled_VID_28Sep26_LS",RAW_Adset!$B$2:$B$401,"2") | C41: =IFERROR(SUMIFS(RAW_Adset!$D$2:$D$401,RAW_Adset!$A$2:$A$401,"HI_005_BHKT_Hanuman_DL_BAU_Sep04_2_Daypart_No2to5PM_Scheduled_VID_28Sep26_LS",RAW_Adset!$B$2:$B$401,"2")/SUMIFS(RAW_Adset!$E$2:$E$401,RAW_Adset!$A$2:$A$401,"HI_005_BHKT_Hanuman_DL_BAU_Sep04_2_Daypart_No2to5PM_Scheduled_VID_28Sep26_LS",RAW_Adset!$B$2:$B$401,"2"),"-") | D41: =SUMIFS(RAW_Adset!$D$2:$D$401,RAW_Adset!$A$2:$A$401,"HI_005_BHKT_Hanuman_DL_BAU_Sep04_2_Daypart_No2to5PM_Scheduled_VID_28Sep26_LS",RAW_Adset!$B$2:$B$401,"3") | E41: =IFERROR(SUMIFS(RAW_Adset!$D$2:$D$401,RAW_Adset!$A$2:$A$401,"HI_005_BHKT_Hanuman_DL_BAU_Sep04_2_Daypart_No2to5PM_Scheduled_VID_28Sep26_LS",RAW_Adset!$B$2:$B$401,"3")/SUMIFS(RAW_Adset!$E$2:$E$401,RAW_Adset!$A$2:$A$401,"HI_005_BHKT_Hanuman_DL_BAU_Sep04_2_Daypart_No2to5PM_Scheduled_VID_28Sep26_LS",RAW_Adset!$B$2:$B$401,"3"),"-") | F41: =IFERROR((SUMIFS(RAW_Adset!$D$2:$D$401,RAW_Adset!$A$2:$A$401,"HI_005_BHKT_Hanuman_DL_BAU_Sep04_2_Daypart_No2to5PM_Scheduled_VID_28Sep26_LS",RAW_Adset!$B$2:$B$401,"3")/SUMIFS(RAW_Adset!$E$2:$E$401,RAW_Adset!$A$2:$A$401,"HI_005_BHKT_Hanuman_DL_BAU_Sep04_2_Daypart_No2to5PM_Scheduled_VID_28Sep26_LS",RAW_Adset!$B$2:$B$401,"3"))/(SUMIFS(RAW_Adset!$D$2:$D$401,RAW_Adset!$A$2:$A$401,"HI_005_BHKT_Hanuman_DL_BAU_Sep04_2_Daypart_No2to5PM_Scheduled_VID_28Sep26_LS",RAW_Adset!$B$2:$B$401,"2")/SUMIFS(RAW_Adset!$E$2:$E$401,RAW_Adset!$A$2:$A$401,"HI_005_BHKT_Hanuman_DL_BAU_Sep04_2_Daypart_No2to5PM_Scheduled_VID_28Sep26_LS",RAW_Adset!$B$2:$B$401,"2"))-1,"-")
A42: TN_002_BHKT_Murugan_DL_BAU_VID_Sep22_5_LS | B42: =SUMIFS(RAW_Adset!$D$2:$D$401,RAW_Adset!$A$2:$A$401,"TN_002_BHKT_Murugan_DL_BAU_VID_Sep22_5_LS",RAW_Adset!$B$2:$B$401,"2") | C42: =IFERROR(SUMIFS(RAW_Adset!$D$2:$D$401,RAW_Adset!$A$2:$A$401,"TN_002_BHKT_Murugan_DL_BAU_VID_Sep22_5_LS",RAW_Adset!$B$2:$B$401,"2")/SUMIFS(RAW_Adset!$E$2:$E$401,RAW_Adset!$A$2:$A$401,"TN_002_BHKT_Murugan_DL_BAU_VID_Sep22_5_LS",RAW_Adset!$B$2:$B$401,"2"),"-") | D42: =SUMIFS(RAW_Adset!$D$2:$D$401,RAW_Adset!$A$2:$A$401,"TN_002_BHKT_Murugan_DL_BAU_VID_Sep22_5_LS",RAW_Adset!$B$2:$B$401,"3") | E42: =IFERROR(SUMIFS(RAW_Adset!$D$2:$D$401,RAW_Adset!$A$2:$A$401,"TN_002_BHKT_Murugan_DL_BAU_VID_Sep22_5_LS",RAW_Adset!$B$2:$B$401,"3")/SUMIFS(RAW_Adset!$E$2:$E$401,RAW_Adset!$A$2:$A$401,"TN_002_BHKT_Murugan_DL_BAU_VID_Sep22_5_LS",RAW_Adset!$B$2:$B$401,"3"),"-") | F42: =IFERROR((SUMIFS(RAW_Adset!$D$2:$D$401,RAW_Adset!$A$2:$A$401,"TN_002_BHKT_Murugan_DL_BAU_VID_Sep22_5_LS",RAW_Adset!$B$2:$B$401,"3")/SUMIFS(RAW_Adset!$E$2:$E$401,RAW_Adset!$A$2:$A$401,"TN_002_BHKT_Murugan_DL_BAU_VID_Sep22_5_LS",RAW_Adset!$B$2:$B$401,"3"))/(SUMIFS(RAW_Adset!$D$2:$D$401,RAW_Adset!$A$2:$A$401,"TN_002_BHKT_Murugan_DL_BAU_VID_Sep22_5_LS",RAW_Adset!$B$2:$B$401,"2")/SUMIFS(RAW_Adset!$E$2:$E$401,RAW_Adset!$A$2:$A$401,"TN_002_BHKT_Murugan_DL_BAU_VID_Sep22_5_LS",RAW_Adset!$B$2:$B$401,"2"))-1,"-") | G42: Yes
A43: TN_002_BHKT_Murugan_DL_UGC_AI_VID_18Sep26_LS - Copy | B43: =SUMIFS(RAW_Adset!$D$2:$D$401,RAW_Adset!$A$2:$A$401,"TN_002_BHKT_Murugan_DL_UGC_AI_VID_18Sep26_LS - Copy",RAW_Adset!$B$2:$B$401,"2") | C43: =IFERROR(SUMIFS(RAW_Adset!$D$2:$D$401,RAW_Adset!$A$2:$A$401,"TN_002_BHKT_Murugan_DL_UGC_AI_VID_18Sep26_LS - Copy",RAW_Adset!$B$2:$B$401,"2")/SUMIFS(RAW_Adset!$E$2:$E$401,RAW_Adset!$A$2:$A$401,"TN_002_BHKT_Murugan_DL_UGC_AI_VID_18Sep26_LS - Copy",RAW_Adset!$B$2:$B$401,"2"),"-") | D43: =SUMIFS(RAW_Adset!$D$2:$D$401,RAW_Adset!$A$2:$A$401,"TN_002_BHKT_Murugan_DL_UGC_AI_VID_18Sep26_LS - Copy",RAW_Adset!$B$2:$B$401,"3") | E43: =IFERROR(SUMIFS(RAW_Adset!$D$2:$D$401,RAW_Adset!$A$2:$A$401,"TN_002_BHKT_Murugan_DL_UGC_AI_VID_18Sep26_LS - Copy",RAW_Adset!$B$2:$B$401,"3")/SUMIFS(RAW_Adset!$E$2:$E$401,RAW_Adset!$A$2:$A$401,"TN_002_BHKT_Murugan_DL_UGC_AI_VID_18Sep26_LS - Copy",RAW_Adset!$B$2:$B$401,"3"),"-") | F43: =IFERROR((SUMIFS(RAW_Adset!$D$2:$D$401,RAW_Adset!$A$2:$A$401,"TN_002_BHKT_Murugan_DL_UGC_AI_VID_18Sep26_LS - Copy",RAW_Adset!$B$2:$B$401,"3")/SUMIFS(RAW_Adset!$E$2:$E$401,RAW_Adset!$A$2:$A$401,"TN_002_BHKT_Murugan_DL_UGC_AI_VID_18Sep26_LS - Copy",RAW_Adset!$B$2:$B$401,"3"))/(SUMIFS(RAW_Adset!$D$2:$D$401,RAW_Adset!$A$2:$A$401,"TN_002_BHKT_Murugan_DL_UGC_AI_VID_18Sep26_LS - Copy",RAW_Adset!$B$2:$B$401,"2")/SUMIFS(RAW_Adset!$E$2:$E$401,RAW_Adset!$A$2:$A$401,"TN_002_BHKT_Murugan_DL_UGC_AI_VID_18Sep26_LS - Copy",RAW_Adset!$B$2:$B$401,"2"))-1,"-")
A44: KA_004_BHKT_DL_AI Explainer_K324 - K327_VID_LS | B44: =SUMIFS(RAW_Adset!$D$2:$D$401,RAW_Adset!$A$2:$A$401,"KA_004_BHKT_DL_AI Explainer_K324 - K327_VID_LS",RAW_Adset!$B$2:$B$401,"2") | C44: =IFERROR(SUMIFS(RAW_Adset!$D$2:$D$401,RAW_Adset!$A$2:$A$401,"KA_004_BHKT_DL_AI Explainer_K324 - K327_VID_LS",RAW_Adset!$B$2:$B$401,"2")/SUMIFS(RAW_Adset!$E$2:$E$401,RAW_Adset!$A$2:$A$401,"KA_004_BHKT_DL_AI Explainer_K324 - K327_VID_LS",RAW_Adset!$B$2:$B$401,"2"),"-") | D44: =SUMIFS(RAW_Adset!$D$2:$D$401,RAW_Adset!$A$2:$A$401,"KA_004_BHKT_DL_AI Explainer_K324 - K327_VID_LS",RAW_Adset!$B$2:$B$401,"3") | E44: =IFERROR(SUMIFS(RAW_Adset!$D$2:$D$401,RAW_Adset!$A$2:$A$401,"KA_004_BHKT_DL_AI Explainer_K324 - K327_VID_LS",RAW_Adset!$B$2:$B$401,"3")/SUMIFS(RAW_Adset!$E$2:$E$401,RAW_Adset!$A$2:$A$401,"KA_004_BHKT_DL_AI Explainer_K324 - K327_VID_LS",RAW_Adset!$B$2:$B$401,"3"),"-") | F44: =IFERROR((SUMIFS(RAW_Adset!$D$2:$D$401,RAW_Adset!$A$2:$A$401,"KA_004_BHKT_DL_AI Explainer_K324 - K327_VID_LS",RAW_Adset!$B$2:$B$401,"3")/SUMIFS(RAW_Adset!$E$2:$E$401,RAW_Adset!$A$2:$A$401,"KA_004_BHKT_DL_AI Explainer_K324 - K327_VID_LS",RAW_Adset!$B$2:$B$401,"3"))/(SUMIFS(RAW_Adset!$D$2:$D$401,RAW_Adset!$A$2:$A$401,"KA_004_BHKT_DL_AI Explainer_K324 - K327_VID_LS",RAW_Adset!$B$2:$B$401,"2")/SUMIFS(RAW_Adset!$E$2:$E$401,RAW_Adset!$A$2:$A$401,"KA_004_BHKT_DL_AI Explainer_K324 - K327_VID_LS",RAW_Adset!$B$2:$B$401,"2"))-1,"-")
A45: KA_004_BHKT_DL_UGC AI_K293 - K295_VID_LS | B45: =SUMIFS(RAW_Adset!$D$2:$D$401,RAW_Adset!$A$2:$A$401,"KA_004_BHKT_DL_UGC AI_K293 - K295_VID_LS",RAW_Adset!$B$2:$B$401,"2") | C45: =IFERROR(SUMIFS(RAW_Adset!$D$2:$D$401,RAW_Adset!$A$2:$A$401,"KA_004_BHKT_DL_UGC AI_K293 - K295_VID_LS",RAW_Adset!$B$2:$B$401,"2")/SUMIFS(RAW_Adset!$E$2:$E$401,RAW_Adset!$A$2:$A$401,"KA_004_BHKT_DL_UGC AI_K293 - K295_VID_LS",RAW_Adset!$B$2:$B$401,"2"),"-") | D45: =SUMIFS(RAW_Adset!$D$2:$D$401,RAW_Adset!$A$2:$A$401,"KA_004_BHKT_DL_UGC AI_K293 - K295_VID_LS",RAW_Adset!$B$2:$B$401,"3") | E45: =IFERROR(SUMIFS(RAW_Adset!$D$2:$D$401,RAW_Adset!$A$2:$A$401,"KA_004_BHKT_DL_UGC AI_K293 - K295_VID_LS",RAW_Adset!$B$2:$B$401,"3")/SUMIFS(RAW_Adset!$E$2:$E$401,RAW_Adset!$A$2:$A$401,"KA_004_BHKT_DL_UGC AI_K293 - K295_VID_LS",RAW_Adset!$B$2:$B$401,"3"),"-") | F45: =IFERROR((SUMIFS(RAW_Adset!$D$2:$D$401,RAW_Adset!$A$2:$A$401,"KA_004_BHKT_DL_UGC AI_K293 - K295_VID_LS",RAW_Adset!$B$2:$B$401,"3")/SUMIFS(RAW_Adset!$E$2:$E$401,RAW_Adset!$A$2:$A$401,"KA_004_BHKT_DL_UGC AI_K293 - K295_VID_LS",RAW_Adset!$B$2:$B$401,"3"))/(SUMIFS(RAW_Adset!$D$2:$D$401,RAW_Adset!$A$2:$A$401,"KA_004_BHKT_DL_UGC AI_K293 - K295_VID_LS",RAW_Adset!$B$2:$B$401,"2")/SUMIFS(RAW_Adset!$E$2:$E$401,RAW_Adset!$A$2:$A$401,"KA_004_BHKT_DL_UGC AI_K293 - K295_VID_LS",RAW_Adset!$B$2:$B$401,"2"))-1,"-")
A46: TN_002_MOTV_BAU_Status_DL_30Jun_LS | B46: =SUMIFS(RAW_Adset!$D$2:$D$401,RAW_Adset!$A$2:$A$401,"TN_002_MOTV_BAU_Status_DL_30Jun_LS",RAW_Adset!$B$2:$B$401,"2") | C46: =IFERROR(SUMIFS(RAW_Adset!$D$2:$D$401,RAW_Adset!$A$2:$A$401,"TN_002_MOTV_BAU_Status_DL_30Jun_LS",RAW_Adset!$B$2:$B$401,"2")/SUMIFS(RAW_Adset!$E$2:$E$401,RAW_Adset!$A$2:$A$401,"TN_002_MOTV_BAU_Status_DL_30Jun_LS",RAW_Adset!$B$2:$B$401,"2"),"-") | D46: =SUMIFS(RAW_Adset!$D$2:$D$401,RAW_Adset!$A$2:$A$401,"TN_002_MOTV_BAU_Status_DL_30Jun_LS",RAW_Adset!$B$2:$B$401,"3") | E46: =IFERROR(SUMIFS(RAW_Adset!$D$2:$D$401,RAW_Adset!$A$2:$A$401,"TN_002_MOTV_BAU_Status_DL_30Jun_LS",RAW_Adset!$B$2:$B$401,"3")/SUMIFS(RAW_Adset!$E$2:$E$401,RAW_Adset!$A$2:$A$401,"TN_002_MOTV_BAU_Status_DL_30Jun_LS",RAW_Adset!$B$2:$B$401,"3"),"-") | F46: =IFERROR((SUMIFS(RAW_Adset!$D$2:$D$401,RAW_Adset!$A$2:$A$401,"TN_002_MOTV_BAU_Status_DL_30Jun_LS",RAW_Adset!$B$2:$B$401,"3")/SUMIFS(RAW_Adset!$E$2:$E$401,RAW_Adset!$A$2:$A$401,"TN_002_MOTV_BAU_Status_DL_30Jun_LS",RAW_Adset!$B$2:$B$401,"3"))/(SUMIFS(RAW_Adset!$D$2:$D$401,RAW_Adset!$A$2:$A$401,"TN_002_MOTV_BAU_Status_DL_30Jun_LS",RAW_Adset!$B$2:$B$401,"2")/SUMIFS(RAW_Adset!$E$2:$E$401,RAW_Adset!$A$2:$A$401,"TN_002_MOTV_BAU_Status_DL_30Jun_LS",RAW_Adset!$B$2:$B$401,"2"))-1,"-")
A47: HI_005_POL_VID_Cat_DL_BAU_IDCard_Cong_Rahul_Parivar_VID_28Aug_LS | B47: =SUMIFS(RAW_Adset!$D$2:$D$401,RAW_Adset!$A$2:$A$401,"HI_005_POL_VID_Cat_DL_BAU_IDCard_Cong_Rahul_Parivar_VID_28Aug_LS",RAW_Adset!$B$2:$B$401,"2") | C47: =IFERROR(SUMIFS(RAW_Adset!$D$2:$D$401,RAW_Adset!$A$2:$A$401,"HI_005_POL_VID_Cat_DL_BAU_IDCard_Cong_Rahul_Parivar_VID_28Aug_LS",RAW_Adset!$B$2:$B$401,"2")/SUMIFS(RAW_Adset!$E$2:$E$401,RAW_Adset!$A$2:$A$401,"HI_005_POL_VID_Cat_DL_BAU_IDCard_Cong_Rahul_Parivar_VID_28Aug_LS",RAW_Adset!$B$2:$B$401,"2"),"-") | D47: =SUMIFS(RAW_Adset!$D$2:$D$401,RAW_Adset!$A$2:$A$401,"HI_005_POL_VID_Cat_DL_BAU_IDCard_Cong_Rahul_Parivar_VID_28Aug_LS",RAW_Adset!$B$2:$B$401,"3") | E47: =IFERROR(SUMIFS(RAW_Adset!$D$2:$D$401,RAW_Adset!$A$2:$A$401,"HI_005_POL_VID_Cat_DL_BAU_IDCard_Cong_Rahul_Parivar_VID_28Aug_LS",RAW_Adset!$B$2:$B$401,"3")/SUMIFS(RAW_Adset!$E$2:$E$401,RAW_Adset!$A$2:$A$401,"HI_005_POL_VID_Cat_DL_BAU_IDCard_Cong_Rahul_Parivar_VID_28Aug_LS",RAW_Adset!$B$2:$B$401,"3"),"-") | F47: =IFERROR((SUMIFS(RAW_Adset!$D$2:$D$401,RAW_Adset!$A$2:$A$401,"HI_005_POL_VID_Cat_DL_BAU_IDCard_Cong_Rahul_Parivar_VID_28Aug_LS",RAW_Adset!$B$2:$B$401,"3")/SUMIFS(RAW_Adset!$E$2:$E$401,RAW_Adset!$A$2:$A$401,"HI_005_POL_VID_Cat_DL_BAU_IDCard_Cong_Rahul_Parivar_VID_28Aug_LS",RAW_Adset!$B$2:$B$401,"3"))/(SUMIFS(RAW_Adset!$D$2:$D$401,RAW_Adset!$A$2:$A$401,"HI_005_POL_VID_Cat_DL_BAU_IDCard_Cong_Rahul_Parivar_VID_28Aug_LS",RAW_Adset!$B$2:$B$401,"2")/SUMIFS(RAW_Adset!$E$2:$E$401,RAW_Adset!$A$2:$A$401,"HI_005_POL_VID_Cat_DL_BAU_IDCard_Cong_Rahul_Parivar_VID_28Aug_LS",RAW_Adset!$B$2:$B$401,"2"))-1,"-")
A49: Adsets with a valid CAC both days: | C49: =SUMPRODUCT((ISNUMBER(C3:C47))*(ISNUMBER(E3:E47)))
A50: Of those, CAC UP Oct 2 to Oct 3: | C50: =SUMPRODUCT((ISNUMBER(C3:C47))*(ISNUMBER(E3:E47))*(E3:E47>C3:C47))
A51: Of those, CAC DOWN Oct 2 to Oct 3: | C51: =SUMPRODUCT((ISNUMBER(C3:C47))*(ISNUMBER(E3:E47))*(E3:E47<C3:C47))

Sheet RAW_Daily
A1: Date | B1: DayIdx | C1: Spend | D1: Impressions | E1: CPM | F1: CTR | G1: Installs | H1: Trials
A2: Oct 1 | B2: 1 | C2: 286325 | D2: 7524906 | E2: 38.05 | F2: 0.55 | G2: 9094 | H2: 902
A3: Oct 2 | B3: 2 | C3: 316399 | D3: 7440497 | E3: 42.52 | F3: 0.61 | G3: 10774 | H3: 1104
A4: Oct 3 | B4: 3 | C4: 351298 | D4: 8203897 | E4: 42.82 | F4: 0.57 | G4: 10533 | H4: 1010
A5: Oct 4 | B5: 4 | C5: 449267 | D5: 9790690 | E5: 45.89 | F5: 0.57 | G5: 12969 | H5: 1218
A6: Oct 5 | B6: 5 | C6: 74743 | D6: 1684167 | E6: 44.38 | F6: 0.57 | G6: 2030 | H6: 234

Sheet RAW_Network
A1: Date | B1: DayIdx | C1: Network | D1: Spend | E1: Installs | F1: Trials
A2: Oct 1 | B2: 1 | C2: Facebook | D2: 180252 | E2: 5606 | F2: 570
A3: Oct 1 | B3: 1 | C3: Instagram | D3: 105933 | E3: 3484 | F3: 332
A4: Oct 1 | B4: 1 | C4: Audience Network | D4: 46 | E4: 1 | F4: 0
A5: Oct 1 | B5: 1 | C5: Threads | D5: 93 | E5: 3 | F5: 0
A6: Oct 2 | B6: 2 | C6: Facebook | D6: 191350 | E6: 6363 | F6: 666
A7: Oct 2 | B7: 2 | C7: Instagram | D7: 124871 | E7: 4408 | F7: 438
A8: Oct 2 | B8: 2 | C8: Audience Network | D8: 71 | E8: 0 | F8: 0
A9: Oct 2 | B9: 2 | C9: Threads | D9: 100 | E9: 3 | F9: 0
A10: Oct 3 | B10: 3 | C10: Facebook | D10: 202424 | E10: 6043 | F10: 626
A11: Oct 3 | B11: 3 | C11: Instagram | D11: 148658 | E11: 4479 | F11: 384
A12: Oct 3 | B12: 3 | C12: Audience Network | D12: 81 | E12: 3 | F12: 0
A13: Oct 3 | B13: 3 | C13: Threads | D13: 127 | E13: 8 | F13: 0
... A21: Oct 5 | B21: 5 | C21: Threads | D21: 23 | E21: 1 | F21: 0

Sheet RAW_Age
A1: Date | B1: DayIdx | C1: Age | D1: Spend | E1: Installs | F1: Trials
A2: Oct 1 | B2: 1 | C2: 18-24 | D2: 33221 | E2: 1244 | F2: 91
A3: Oct 1 | B3: 1 | C3: 25-34 | D3: 98401 | E3: 3390 | F3: 333
A4: Oct 1 | B4: 1 | C4: 35-44 | D4: 88102 | E4: 2573 | F4: 287
A5: Oct 1 | B5: 1 | C5: 45-54 | D5: 45170 | E5: 1254 | F5: 127
A6: Oct 1 | B6: 1 | C6: 55-64 | D6: 16310 | E6: 465 | F6: 39
A7: Oct 1 | B7: 1 | C7: 65+ | D7: 5121 | E7: 168 | F7: 20
A8: Oct 2 | B8: 2 | C8: 18-24 | D8: 38044 | E8: 1571 | F8: 104
A9: Oct 2 | B9: 2 | C9: 25-34 | D9: 109657 | E9: 3951 | F9: 418
A10: Oct 2 | B10: 2 | C10: 35-44 | D10: 93644 | E10: 2899 | F10: 360
A11: Oct 2 | B11: 2 | C11: 45-54 | D11: 50055 | E11: 1556 | F11: 157
A12: Oct 2 | B12: 2 | C12: 55-64 | D12: 18921 | E12: 601 | F12: 50
A13: Oct 2 | B13: 2 | C13: 65+ | D13: 6079 | E13: 194 | F13: 10
... A31: Oct 5 | B31: 5 | C31: 65+ | D31: 1315 | E31: 38 | F31: 5

Sheet RAW_Gender
A1: Date | B1: DayIdx | C1: Gender | D1: Spend | E1: Installs | F1: Trials
A2: Oct 1 | B2: 1 | C2: Male | D2: 224890 | E2: 7185 | F2: 685
A3: Oct 1 | B3: 1 | C3: Female | D3: 60631 | E3: 1880 | F3: 209
A4: Oct 2 | B4: 2 | C4: Male | D4: 248743 | E4: 8471 | F4: 894
A5: Oct 2 | B5: 2 | C5: Female | D5: 66588 | E5: 2258 | F5: 201
A6: Oct 3 | B6: 3 | C6: Male | D6: 269489 | E6: 7996 | F6: 792
A7: Oct 3 | B7: 3 | C7: Female | D7: 80585 | E7: 2494 | F7: 212
A8: Oct 4 | B8: 4 | C8: Male | D8: 349255 | E8: 10061 | F8: 946
A9: Oct 4 | B9: 4 | C9: Female | D9: 98355 | E9: 2857 | F9: 261
A10: Oct 5 | B10: 5 | C10: Male | D10: 58785 | E10: 1572 | F10: 191
A11: Oct 5 | B11: 5 | C11: Female | D11: 15671 | E11: 448 | F11: 43

Sheet RAW_Placement
A1: Date | B1: DayIdx | C1: Placement | D1: Spend | E1: Installs | F1: Trials
A2: Oct 1 | B2: 1 | C2: Facebook Reels | D2: 100065 | E2: 3083 | F2: 255
A3: Oct 1 | B3: 1 | C3: Facebook Feed | D3: 50629 | E3: 1382 | F3: 218
A4: Oct 1 | B4: 1 | C4: Facebook Stories | D4: 22065 | E4: 957 | F4: 71
A5: Oct 1 | B5: 1 | C5: Instream Video | D5: 7140 | E5: 170 | F5: 26
A6: Oct 1 | B6: 1 | C6: Instagram Reels | D6: 60511 | E6: 1968 | F6: 181
A7: Oct 1 | B7: 1 | C7: Instagram Feed | D7: 40793 | E7: 1296 | F7: 133
A8: Oct 1 | B8: 1 | C8: Instagram Stories | D8: 4556 | E8: 218 | F8: 18
A9: Oct 2 | B9: 2 | C9: Facebook Reels | D9: 115454 | E9: 3886 | F9: 390
A10: Oct 2 | B10: 2 | C10: Facebook Feed | D10: 46488 | E10: 1420 | F10: 163
A11: Oct 2 | B11: 2 | C11: Facebook Stories | D11: 21053 | E11: 863 | F11: 86
A12: Oct 2 | B12: 2 | C12: Instream Video | D12: 7914 | E12: 177 | F12: 23
A13: Oct 2 | B13: 2 | C13: Instagram Reels | D13: 70442 | E13: 2601 | F13: 240
... A36: Oct 5 | B36: 5 | C36: Instagram Stories | D36: 961 | E36: 31 | F36: 5

Sheet RAW_Device
A1: Date | B1: DayIdx | C1: Device | D1: Spend | E1: Installs | F1: Trials
A2: Oct 1 | B2: 1 | C2: Android smartphone | D2: 286269 | E2: 9093 | F2: 902
A3: Oct 1 | B3: 1 | C3: Android tablet | D3: 54 | E3: 1 | F3: 0
A4: Oct 2 | B4: 2 | C4: Android smartphone | D4: 316306 | E4: 10768 | F4: 1104
A5: Oct 2 | B5: 2 | C5: Android tablet | D5: 85 | E5: 4 | F5: 0
A6: Oct 3 | B6: 3 | C6: Android smartphone | D6: 351178 | E6: 10530 | F6: 1010
A7: Oct 3 | B7: 3 | C7: Android tablet | D7: 112 | E7: 3 | F7: 0
A8: Oct 4 | B8: 4 | C8: Android smartphone | D8: 449080 | E8: 12961 | F8: 1218
A9: Oct 4 | B9: 4 | C9: Android tablet | D9: 174 | E9: 3 | F9: 0
A10: Oct 5 | B10: 5 | C10: Android smartphone | D10: 74723 | E10: 2027 | F10: 234
A11: Oct 5 | B11: 5 | C11: Android tablet | D11: 18 | E11: 2 | F11: 0

Sheet RAW_Campaign
A1: Date | B1: DayIdx | C1: Campaign | D1: Spend | E1: Installs | F1: Trials
A2: Oct 1 | B2: 1 | C2: TN_002_MIX_Purchase_CBO | D2: 10741 | E2: 248 | F2: 23
A3: Oct 1 | B3: 1 | C3: TE_001_MIX_Purchase_ABO | D3: 25168 | E3: 516 | F3: 55
A4: Oct 1 | B4: 1 | C4: TN_002_MIX_Purchase_ABO | D4: 21900 | E4: 339 | F4: 59
A5: Oct 1 | B5: 1 | C5: KA_004_MIX_Purchase_ABO | D5: 26498 | E5: 819 | F5: 93
A6: Oct 1 | B6: 1 | C6: HI_005_MIX_Purchase_ABO | D6: 104401 | E6: 3553 | F6: 341
A7: Oct 1 | B7: 1 | C7: MH_003_MIX_Purchase_ABO | D7: 14518 | E7: 396 | F7: 50
A8: Oct 1 | B8: 1 | C8: HI_005_Political_Purchase_ABO | D8: 15494 | E8: 520 | F8: 39
A9: Oct 1 | B9: 1 | C9: HI_005_MIX_All_India_CBO | D9: 64088 | E9: 2609 | F9: 232
A10: Oct 1 | B10: 1 | C10: HI_005_EVNT_Purchase_ABO | D10: 2571 | E10: 90 | F10: 7
A11: Oct 1 | B11: 1 | C11: TN_002_EVNT_Purchase_ABO | D11: 947 | E11: 4 | F11: 3
A12: Oct 2 | B12: 2 | C12: TN_002_MIX_Purchase_CBO | D12: 6596 | E12: 152 | F12: 16
A13: Oct 2 | B13: 2 | C13: TE_001_MIX_Purchase_ABO | D13: 27483 | E13: 683 | F13: 127
... A55: Oct 5 | B55: 5 | C55: TN_002_EVNT_Purchase_ABO | D55: 211 | E55: 1 | F55: 0

Sheet RAW_Adset
A1: Adset | B1: DayIdx | C1: Date | D1: Spend | E1: Trials
A2: HI_005_BHKT_BAU_DL_25Jun_03_LS | B2: 2 | C2: Oct 2 | D2: 976 | E2: 5
A3: TN_002_MOTV_BAU_Status_DL_30Jun_LS | B3: 2 | C3: Oct 2 | D3: 1138 | E3: 3
A4: TN_002_BHKT_BAU_T2_DL_02Jul_LS | B4: 2 | C4: Oct 2 | D4: 2 | E4: 0
A5: TN_002_MOTV_BAU_T2_CL_02Jul_LS | B5: 2 | C5: Oct 2 | D5: 0 | E5: 0
A6: TN_002_GMOR_BAU_T2_DL_06Jul_LS | B6: 2 | C6: Oct 2 | D6: 515 | E6: 0
A7: HI_005_BHKT_Khatu_Shyam_VID_LS | B7: 2 | C7: Oct 2 | D7: 665 | E7: 1
A8: TN_002_BHKT_DL_BAU_Collage_VID_Jul22_LS | B8: 2 | C8: Oct 2 | D8: 0 | E8: 0
A9: MH_003_BHKT_MIX_T2_DL_CL_EXT_002_LS | B9: 2 | C9: Oct 2 | D9: 1721 | E9: 4
A10: HI_005_POL_DL_BAU_VID_05Aug26_LS | B10: 2 | C10: Oct 2 | D10: 13657 | E10: 48
A11: TN_002_BHKT_DL_BAU_Murugan_1_VID_Aug14_LS | B11: 2 | C11: Oct 2 | D11: 875 | E11: 3
A12: TN_002_BHKT_DL_BAU_Murugan_2_VID_Aug14_LS | B12: 2 | C12: Oct 2 | D12: 2419 | E12: 8
A13: MH_003_BHKT_Poster_DL_BAU_VID_21Aug26_1_LS | B13: 2 | C13: Oct 2 | D13: 1545 | E13: 7
... A401: TE_001_ANIV_DL_BAU_B1794 - B1802_VID_LS | B401: 4 | C401: Oct 4 | D401: 358 | E401: 0
